Workbook

Sheet Dashboard
A2: Executive Dashboard
A4: Monthly Billing Tab | D4: Receipt Template | G4: Available Bed Spaces | J4: Arrears Report
G8: =Calc_Data!B8 -> 5500 | J8: Total Grace Period

Sheet Master Roster
A1: Master Roster | I1: All Available
D2: Search Tenant: | E2: Chanda Lutashima
A3: Unique ID | B3: Room Number | C3: House/ Block | D3: Bed Space | E3: Tenant Name | F3: Phone Number | G3: Entry Date | H3: Monthly Rent | I3: ID & Name | J3: Room Gender
A4: BBH-1-A | B4: 1 | C4: BBH | D4: A | E4: Adrian mulale | F4: 260977146630 | G4: 46203 | H4: 950 | I4: =A4 & " - " & E4 -> BBH-1-A - Adrian mulale | J4: Male
A5: BBH-2-A | B5: 2 | C5: BBH | D5: A | E5: Wisdom Bwani | F5: 260776960320 | G5: 46178 | H5: 900 | I5: =A5 & " - " & E5 -> BBH-2-A - Wisdom Bwani | J5: Male
A6: BBH-2-B | B6: 2 | C6: BBH | D6: B | E6: Jackson Mwanza | F6: 260976625656 | G6: 46181 | H6: 900 | I6: =A6 & " - " & E6 -> BBH-2-B - Jackson Mwanza | J6: Male
A7: BBH-3-A | B7: 3 | C7: BBH | D7: A | E7: Prosper Kalayi | F7: 260970522913 | G7: 46186 | H7: 900 | I7: =A7 & " - " & E7 -> BBH-3-A - Prosper Kalayi | J7: Male
A8: BBH-3-B | B8: 3 | C8: BBH | D8: B | E8: Shadrach Munganini | F8: 260979567550 | G8: 46228 | H8: 900 | I8: =A8 & " - " & E8 -> BBH-3-B - Shadrach Munganini | J8: Male
A9: BBH-3-C | B9: 3 | C9: BBH | D9: C | E9: Collins Mubanga | F9: 260777237029 | G9: 46176 | H9: 900 | I9: =A9 & " - " & E9 -> BBH-3-C - Collins Mubanga | J9: Male
A10: BBH-4-A | B10: 4 | C10: BBH | D10: A | E10: Himalikiti Saviour | F10: 260975547126 | G10: 46195 | H10: 950 | I10: =A10 & " - " & E10 -> BBH-4-A - Himalikiti Saviour | J10: Male
A11: BBH-5-A | B11: 5 | C11: BBH | D11: A | E11: Wampa | F11: 260971071877 | G11: 46225 | H11: 0 | I11: =A11 & " - " & E11 -> BBH-5-A - Wampa | J11: Female
A12: BBH-6-A | B12: 6 | C12: BBH | D12: A | E12: McDonald | F12: 260773456119 | G12: 46174 | H12: 900 | I12: =A12 & " - " & E12 -> BBH-6-A - McDonald | J12: Male
A13: BBH-6-B | B13: 6 | C13: BBH | D13: B | E13: Nanga Obrien | F13: 260770838758 | G13: 46048 | H13: 900 | I13: =A13 & " - " & E13 -> BBH-6-B - Nanga Obrien | J13: Male
A14: BBH-6-C | B14: 6 | C14: BBH | D14: C | E14: Zick Phiri | F14: 260973072762 | G14: 46184 | H14: 900 | I14: =A14 & " - " & E14 -> BBH-6-C - Zick Phiri | J14: Male
A15: BBH-7-A | B15: 7 | C15: BBH | D15: A | E15: Funny Muyamina | F15: 260771096585 | G15: 46178 | H15: 900 | I15: =A15 & " - " & E15 -> BBH-7-A - Funny Muyamina | J15: Female
A16: BBH-7-B | B16: 7 | C16: BBH | D16: B | E16: Treasure Simeenda | F16: 260772393278 | G16: 46178 | H16: 900 | I16: =A16 & " - " & E16 -> BBH-7-B - Treasure Simeenda | J16: Female
A17: BBH-7-C | B17: 7 | C17: BBH | D17: C | E17: Vacant | H17: 900 | I17: =A17 & " - " & E17 -> BBH-7-C - Vacant | J17: Female
A18: BBH-8-A | B18: 8 | C18: BBH | D18: A | E18: Kangwa Kunda | F18: 260972024337 | G18: 46198 | H18: 900 | I18: =A18 & " - " & E18 -> BBH-8-A - Kangwa Kunda | J18: Male
A19: BBH-8-B | B19: 8 | C19: BBH | D19: B | E19: Vacant | H19: 900 | I19: =A19 & " - " & E19 -> BBH-8-B - Vacant | J19: Male
A20: BBH-9-A | B20: 9 | C20: BBH | D20: A | E20: Felistus Mweemba | F20: 260764785030 | G20: 46182 | H20: 900 | I20: =A20 & " - " & E20 -> BBH-9-A - Felistus Mweemba | J20: Female
A21: BBH-9-B | B21: 9 | C21: BBH | D21: B | E21: Wendy Mpakise | F21: 260971977845 | G21: 46200 | H21: 900 | I21: =A21 & " - " & E21 -> BBH-9-B - Wendy Mpakise | J21: Female
A22: BBH-9-C | B22: 9 | C22: BBH | D22: C | E22: Vacant | H22: 900 | I22: =A22 & " - " & E22 -> BBH-9-C - Vacant | J22: Female
A23: UPV-10-A | B23: 10 | C23: UPV | D23: A | E23: Emely Mwale | F23: 260777238633 | G23: 46178 | H23: 900 | I23: =A23 & " - " & E23 -> UPV-10-A - Emely Mwale | J23: Female
A24: UPV-10-B | B24: 10 | C24: UPV | D24: B | E24: Melody Mumba | F24: 260973551911 | G24: 46186 | H24: 900 | I24: =A24 & " - " & E24 -> UPV-10-B - Melody Mumba | J24: Female
A25: UPV-10-C | B25: 10 | C25: UPV | D25: C | E25: Sara Matakala | F25: 260970522825 | G25: 46198 | H25: 900 | I25: =A25 & " - " & E25 -> UPV-10-C - Sara Matakala | J25: Female
A26: UPV-10-D | B26: 10 | C26: UPV | D26: D | E26: Vacant | H26: 900 | I26: =A26 & " - " & E26 -> UPV-10-D - Vacant | J26: Female
A27: UPV-11-A | B27: 11 | C27: UPV | D27: A | E27: Gift Nankamba | F27: 260970956759 | G27: 46178 | H27: 1000 | I27: =A27 & " - " & E27 -> UPV-11-A - Gift Nankamba | J27: Female
A28: UPV-12-A | B28: 12 | C28: UPV | D28: A | E28: chilulu chiliulu | F28: 260975185330 | G28: 46182 | H28: 1600 | I28: =A28 & " - " & E28 -> UPV-12-A - chilulu chiliulu | J28: Male
A29: UPV-13-A | B29: 13 | C29: UPV | D29: A | E29: Chibesa Chisembe | F29: 260970270037 | G29: 46175 | H29: 1800 | I29: =A29 & " - " & E29 -> UPV-13-A - Chibesa Chisembe | J29: Male
A30: UPV-14-A | B30: 14 | C30: UPV | D30: A | E30: Reuben Ngusulu | F30: 260763503053 | G30: 46184 | H30: 950 | I30: =A30 & " - " & E30 -> UPV-14-A - Reuben Ngusulu | J30: Male
A31: UPV-15-A | B31: 15 | C31: UPV | D31: A | E31: Harriet nanyangwe | F31: 260974130584 | G31: 46176 | H31: 1100 | I31: =A31 & " - " & E31 -> UPV-15-A - Harriet nanyangwe | J31: Female
A32: CRV-16-A | B32: 16 | C32: CRV | D32: A | E32: Vacant | F32: 20772046008 | G32: 46223 | H32: 0 | I32: =A32 & " - " & E32 -> CRV-16-A - Vacant | J32: Male
A33: CRV-16-B | B33: 16 | C33: CRV | D33: B | E33: Ackim Siamafuko | F33: 20772046008 | G33: 46223 | H33: 1200 | I33: =A33 & " - " & E33 -> CRV-16-B - Ackim Siamafuko | J33: Male
A34: CRV-17-A | B34: 17 | C34: CRV | D34: A | E34: Kwitu Khalu | F34: 260960785114 | G34: 46175 | H34: 900 | I34: =A34 & " - " & E34 -> CRV-17-A - Kwitu Khalu | J34: Male
A35: CRV-18-A | B35: 18 | C35: CRV | D35: A | E35: Christopher Tambule | F35: 260972108866 | G35: 46190 | H35: 1200 | I35: =A35 & " - " & E35 -> CRV-18-A - Christopher Tambule | J35: Male
A36: ANX-19-A | B36: 19 | C36: ANX | D36: A | E36: Samantha Musako (Kakompe) | F36: 260977227794 | G36: 46199 | H36: 1200 | I36: =A36 & " - " & E36 -> ANX-19-A - Samantha Musako (Kakompe) | J36: Female
A37: ANX-19-B | B37: 19 | C37: ANX | D37: B | E37: Chanda Lutashima | F37: 260977951894 | G37: 46180 | H37: 1200 | I37: =A37 & " - " & E37 -> ANX-19-B - Chanda Lutashima | J37: Female
A38: ANX-19-C | B38: 19 | C38: ANX | D38: C | E38: Josephine Nyirenda | F38: 260779841908 | G38: 46148 | H38: 1200 | I38: =A38 & " - " & E38 -> ANX-19-C - Josephine Nyirenda | J38: Female
A39: ANX-19-D | B39: 19 | C39: ANX | D39: D | E39: Lubono Ruthendo | F39: 260953618278 | G39: 46207 | H39: 1200 | I39: =A39 & " - " & E39 -> ANX-19-D - Lubono Ruthendo | J39: Female
A40: ANX-20-A | B40: 20 | C40: ANX | D40: A | E40: Steven Musonda | F40: 260975303236 | G40: 46178 | H40: 1400 | I40: =A40 & " - " & E40 -> ANX-20-A - Steven Musonda | J40: Male
A41: NWG-21-A | B41: 21 | C41: NWG | D41: A | E41: Lukundo Siame | F41: 260760833629 | G41: 46191 | H41: 1200 | I41: =A41 & " - " & E41 -> NWG-21-A - Lukundo Siame | J41: Male
A42: NWG-21-B | B42: 21 | C42: NWG | D42: B | E42: Gabirel Kabwe | F42: 260968723095 | G42: 46143 | H42: 1200 | I42: =A42 & " - " & E42 -> NWG-21-B - Gabirel Kabwe | J42: Male
A43: NWG-21-C | B43: 21 | C43: NWG | D43: C | E43: Chama Kampamba | F43: 260770055753 | G43: 46179 | H43: 1200 | I43: =A43 & " - " & E43 -> NWG-21-C - Chama Kampamba | J43: Male
A44: NWG-21-D | B44: 21 | C44: NWG | D44: D | E44: Jairos Banda | F44: 260776136398 | G44: 46174 | H44: 1200 | I44: =A44 & " - " & E44 -> NWG-21-D - Jairos Banda | J44: Male
A45: NWG-22-A | B45: 22 | C45: NWG | D45: A | E45: Vacant | H45: 1200 | I45: =A45 & " - " & E45 -> NWG-22-A - Vacant | J45: Male
A46: NWG-22-B | B46: 22 | C46: NWG | D46: B | E46: David Mulila | F46: 260775161085 | G46: 46191 | H46: 1200 | I46: =A46 & " - " & E46 -> NWG-22-B - David Mulila | J46: Male
A47: NWG-22-C | B47: 22 | C47: NWG | D47: C | E47: Ongani Madaliso Gabriel | F47: 260771736585 | G47: 46174 | H47: 1200 | I47: =A47 & " - " & E47 -> NWG-22-C - Ongani Madaliso Gabriel | J47: Male
A48: NWG-22-D | B48: 22 | C48: NWG | D48: D | E48: Christopher Phiri | F48: 260772109688 | G48: 46176 | H48: 1200 | I48: =A48 & " - " & E48 -> NWG-22-D - Christopher Phiri | J48: Male
A49: NWG-23-A | B49: 23 | C49: NWG | D49: A | E49: Vacant | F49: 260973131421 | G49: 46198 | H49: 1200 | I49: =A49 & " - " & E49 -> NWG-23-A - Vacant | J49: Female
A50: NWG-23-B | B50: 23 | C50: NWG | D50: B | E50: Catherine Mphande | F50: 260963575803 | G50: 46187 | H50: 1200 | I50: =A50 & " - " & E50 -> NWG-23-B - Catherine Mphande | J50: Female
A51: NWG-23-C | B51: 23 | C51: NWG | D51: C | E51: Grace Mwamba | F51: 260957144512 | G51: 46184 | H51: 1200 | I51: =A51 & " - " & E51 -> NWG-23-C - Grace Mwamba | J51: Female
A52: NWG-23-D | B52: 23 | C52: NWG | D52: D | E52: Lushomo gambwe | F52: 260970183545 | G52: 46078 | H52: 1200 | I52: =A52 & " - " & E52 -> NWG-23-D - Lushomo gambwe | J52: Female
A53: NWG-23-E | B53: 23 | C53: NWG | D53: E | E53: Jacqueline Mwape | F53: 260761423674 | G53: 46190 | H53: 1200 | I53: =A53 & " - " & E53 -> NWG-23-E - Jacqueline Mwape | J53: Female
A54: NWG-24-A | B54: 24 | C54: NWG | D54: A | E54: Chami Soneka | F54: 260969410900 | G54: 46235 | H54: 1200 | I54: =A54 & " - " & E54 -> NWG-24-A - Chami Soneka | J54: Female
A55: NWG-24-B | B55: 24 | C55: NWG | D55: B | E55: Kuwunda Makondo | F55: 260774614576 | G55: 46263 | H55: 1200 | I55: =A55 & " - " & E55 -> NWG-24-B - Kuwunda Makondo | J55: Female
A56: NWG-24-C | B56: 24 | C56: NWG | D56: C | E56: Chansa Chinyama | F56: 260974051468 | G56: 46189 | H56: 1200 | I56: =A56 & " - " & E56 -> NWG-24-C - Chansa Chinyama | J56: Female
A57: NWG-24-D | B57: 24 | C57: NWG | D57: D | E57: Kawina Florence | F57: 260976534878 | G57: 46180 | H57: 1200 | I57: =A57 & " - " & E57 -> NWG-24-D - Kawina Florence | J57: Female

Sheet Arrears Report
A1: Arrears Report
F2: =SUM(F4:F1002) -> 21950
A3: Tenant Name | B3: Phone Number | C3: Unique ID | D3: Due Date | E3: Days Overdue | F3: Total Balance | G3: Send via WhatsApp | H3: Send via SMS?
A4: =IFERROR(__xludf.DUMMYFUNCTION("FILTER({'Monthly Billing Tab'!D4:D1002, 'Monthly Billing Tab'!E4:E1002, 'Monthly Billing Tab'!B4:B1002, 'Monthly Billing Tab'!J4:J1002, TODAY() - DATE(YEAR(TODAY()), MONTH('Monthly Billing Tab'!J4:J1002&"" 1""), DAY('Monthly Billing Tab'!G4:G1002)), 'Mont"&"hly Billing Tab'!L4:L1002}, 'Monthly Billing Tab'!D4:D1002<>""Vacant"", 'Monthly Billing Tab'!D4:D1002<>""Reserved"", 'Monthly Billing Tab'!D4:D1002<>"""", 'Monthly Billing Tab'!M4:M1002=""❌ OVERDUE / UNPAID"")"),"Jackson Mwanza") -> Jackson Mwanza | B4: =IFERROR(__xludf.DUMMYFUNCTION("""COMPUTED_VALUE"""),"260976625656") -> 260976625656 | C4: =IFERROR(__xludf.DUMMYFUNCTION("""COMPUTED_VALUE"""),"BBH-2-B") -> BBH-2-B | D4: =IFERROR(__xludf.DUMMYFUNCTION("""COMPUTED_VALUE"""),"Jul") -> Jul | E4: =IFERROR(__xludf.DUMMYFUNCTION("""COMPUTED_VALUE"""),61.0) -> 61 | F4: =IFERROR(__xludf.DUMMYFUNCTION("""COMPUTED_VALUE"""),1200.0) -> 1200 | G4: =IF(A4="", "", HYPERLINK("https://wa.me/" & B4 & "?text=" & ENCODEURL("Hello " & IF(IFERROR(VLOOKUP(C4, 'Master Roster'!A:J, 10, FALSE), "")="Male", "Mr. ", "Ms. ") & A4 & ", this is a reminder that your rent balance of K" & F4 & " is due. Please make a payment,"), "Message on WhatsApp")) -> Message on WhatsApp | H4: =IF(ISBLANK(A4), "", HYPERLINK("sms:"&B4&"?body=Hello "&A4&", this is a reminder that your rent balance of "&F4&" is overdue.", "Send SMS")) -> Send SMS
A5: =IFERROR(__xludf.DUMMYFUNCTION("""COMPUTED_VALUE"""),"Himalikiti Saviour") -> Himalikiti Saviour | B5: =IFERROR(__xludf.DUMMYFUNCTION("""COMPUTED_VALUE"""),2.60975547126E11) -> 260975547126 | C5: =IFERROR(__xludf.DUMMYFUNCTION("""COMPUTED_VALUE"""),"BBH-4-A") -> BBH-4-A | D5: =IFERROR(__xludf.DUMMYFUNCTION("""COMPUTED_VALUE"""),"Jul") -> Jul | E5: =IFERROR(__xludf.DUMMYFUNCTION("""COMPUTED_VALUE"""),47.0) -> 47 | F5: =IFERROR(__xludf.DUMMYFUNCTION("""COMPUTED_VALUE"""),1900.0) -> 1900 | G5: =IF(A5="", "", HYPERLINK("https://wa.me/" & B5 & "?text=" & ENCODEURL("Hello " & IF(IFERROR(VLOOKUP(C5, 'Master Roster'!A:J, 10, FALSE), "")="Male", "Mr. ", "Ms. ") & A5 & ", this is a reminder that your rent balance of K" & F5 & " is due. Please make a payment,"), "Message on WhatsApp")) -> Message on WhatsApp | H5: =IF(ISBLANK(A5), "", HYPERLINK("sms:"&B5&"?body=Hello "&A5&", this is a reminder that your rent balance of "&F5&" is overdue.", "Send SMS")) -> Send SMS
A6: =IFERROR(__xludf.DUMMYFUNCTION("""COMPUTED_VALUE"""),"McDonald") -> McDonald | B6: =IFERROR(__xludf.DUMMYFUNCTION("""COMPUTED_VALUE"""),2.60773456119E11) -> 260773456119 | C6: =IFERROR(__xludf.DUMMYFUNCTION("""COMPUTED_VALUE"""),"BBH-6-A") -> BBH-6-A | D6: =IFERROR(__xludf.DUMMYFUNCTION("""COMPUTED_VALUE"""),"May") -> May | E6: =IFERROR(__xludf.DUMMYFUNCTION("""COMPUTED_VALUE"""),129.0) -> 129 | F6: =IFERROR(__xludf.DUMMYFUNCTION("""COMPUTED_VALUE"""),2600.0) -> 2600 | G6: =IF(A6="", "", HYPERLINK("https://wa.me/" & B6 & "?text=" & ENCODEURL("Hello " & IF(IFERROR(VLOOKUP(C6, 'Master Roster'!A:J, 10, FALSE), "")="Male", "Mr. ", "Ms. ") & A6 & ", this is a reminder that your rent balance of K" & F6 & " is due. Please make a payment,"), "Message on WhatsApp")) -> Message on WhatsApp | H6: =IF(ISBLANK(A6), "", HYPERLINK("sms:"&B6&"?body=Hello "&A6&", this is a reminder that your rent balance of "&F6&" is overdue.", "Send SMS")) -> Send SMS
A7: =IFERROR(__xludf.DUMMYFUNCTION("""COMPUTED_VALUE"""),"Nanga Obrien") -> Nanga Obrien | B7: =IFERROR(__xludf.DUMMYFUNCTION("""COMPUTED_VALUE"""),2.60770838758E11) -> 260770838758 | C7: =IFERROR(__xludf.DUMMYFUNCTION("""COMPUTED_VALUE"""),"BBH-6-B") -> BBH-6-B | D7: =IFERROR(__xludf.DUMMYFUNCTION("""COMPUTED_VALUE"""),"May") -> May | E7: =IFERROR(__xludf.DUMMYFUNCTION("""COMPUTED_VALUE"""),104.0) -> 104 | F7: =IFERROR(__xludf.DUMMYFUNCTION("""COMPUTED_VALUE"""),3600.0) -> 3600 | G7: =IF(A7="", "", HYPERLINK("https://wa.me/" & B7 & "?text=" & ENCODEURL("Hello " & IF(IFERROR(VLOOKUP(C7, 'Master Roster'!A:J, 10, FALSE), "")="Male", "Mr. ", "Ms. ") & A7 & ", this is a reminder that your rent balance of K" & F7 & " is due. Please make a payment,"), "Message on WhatsApp")) -> Message on WhatsApp | H7: =IF(ISBLANK(A7), "", HYPERLINK("sms:"&B7&"?body=Hello "&A7&", this is a reminder that your rent balance of "&F7&" is overdue.", "Send SMS")) -> Send SMS
A8: =IFERROR(__xludf.DUMMYFUNCTION("""COMPUTED_VALUE"""),"Wendy Mpakise") -> Wendy Mpakise | B8: =IFERROR(__xludf.DUMMYFUNCTION("""COMPUTED_VALUE"""),2.60971977845E11) -> 260971977845 | C8: =IFERROR(__xludf.DUMMYFUNCTION("""COMPUTED_VALUE"""),"BBH-9-B") -> BBH-9-B | D8: =IFERROR(__xludf.DUMMYFUNCTION("""COMPUTED_VALUE"""),"Jul") -> Jul | E8: =IFERROR(__xludf.DUMMYFUNCTION("""COMPUTED_VALUE"""),42.0) -> 42 | F8: =IFERROR(__xludf.DUMMYFUNCTION("""COMPUTED_VALUE"""),1800.0) -> 1800 | G8: =IF(A8="", "", HYPERLINK("https://wa.me/" & B8 & "?text=" & ENCODEURL("Hello " & IF(IFERROR(VLOOKUP(C8, 'Master Roster'!A:J, 10, FALSE), "")="Male", "Mr. ", "Ms. ") & A8 & ", this is a reminder that your rent balance of K" & F8 & " is due. Please make a payment,"), "Message on WhatsApp")) -> Message on WhatsApp | H8: =IF(ISBLANK(A8), "", HYPERLINK("sms:"&B8&"?body=Hello "&A8&", this is a reminder that your rent balance of "&F8&" is overdue.", "Send SMS")) -> Send SMS
A9: =IFERROR(__xludf.DUMMYFUNCTION("""COMPUTED_VALUE"""),"Lukundo Siame") -> Lukundo Siame | B9: =IFERROR(__xludf.DUMMYFUNCTION("""COMPUTED_VALUE"""),2.60760833629E11) -> 260760833629 | C9: =IFERROR(__xludf.DUMMYFUNCTION("""COMPUTED_VALUE"""),"NWG-21-A") -> NWG-21-A | D9: =IFERROR(__xludf.DUMMYFUNCTION("""COMPUTED_VALUE"""),"Jul") -> Jul | E9: =IFERROR(__xludf.DUMMYFUNCTION("""COMPUTED_VALUE"""),51.0) -> 51 | F9: =IFERROR(__xludf.DUMMYFUNCTION("""COMPUTED_VALUE"""),1250.0) -> 1250 | G9: =IF(A9="", "", HYPERLINK("https://wa.me/" & B9 & "?text=" & ENCODEURL("Hello " & IF(IFERROR(VLOOKUP(C9, 'Master Roster'!A:J, 10, FALSE), "")="Male", "Mr. ", "Ms. ") & A9 & ", this is a reminder that your rent balance of K" & F9 & " is due. Please make a payment,"), "Message on WhatsApp")) -> Message on WhatsApp | H9: =IF(ISBLANK(A9), "", HYPERLINK("sms:"&B9&"?body=Hello "&A9&", this is a reminder that your rent balance of "&F9&" is overdue.", "Send SMS")) -> Send SMS
A10: =IFERROR(__xludf.DUMMYFUNCTION("""COMPUTED_VALUE"""),"Gabirel Kabwe") -> Gabirel Kabwe | B10: =IFERROR(__xludf.DUMMYFUNCTION("""COMPUTED_VALUE"""),2.60968723095E11) -> 260968723095 | C10: =IFERROR(__xludf.DUMMYFUNCTION("""COMPUTED_VALUE"""),"NWG-21-B") -> NWG-21-B | D10: =IFERROR(__xludf.DUMMYFUNCTION("""COMPUTED_VALUE"""),"Aug") -> Aug | E10: =IFERROR(__xludf.DUMMYFUNCTION("""COMPUTED_VALUE"""),37.0) -> 37 | F10: =IFERROR(__xludf.DUMMYFUNCTION("""COMPUTED_VALUE"""),1200.0) -> 1200 | G10: =IF(A10="", "", HYPERLINK("https://wa.me/" & B10 & "?text=" & ENCODEURL("Hello " & IF(IFERROR(VLOOKUP(C10, 'Master Roster'!A:J, 10, FALSE), "")="Male", "Mr. ", "Ms. ") & A10 & ", this is a reminder that your rent balance of K" & F10 & " is due. Please make a payment,"), "Message on WhatsApp")) -> Message on WhatsApp | H10: =IF(ISBLANK(A10), "", HYPERLINK("sms:"&B10&"?body=Hello "&A10&", this is a reminder that your rent balance of "&F10&" is overdue.", "Send SMS")) -> Send SMS
A11: =IFERROR(__xludf.DUMMYFUNCTION("""COMPUTED_VALUE"""),"Chama Kampamba") -> Chama Kampamba | B11: =IFERROR(__xludf.DUMMYFUNCTION("""COMPUTED_VALUE"""),2.60770055753E11) -> 260770055753 | C11: =IFERROR(__xludf.DUMMYFUNCTION("""COMPUTED_VALUE"""),"NWG-21-C") -> NWG-21-C | D11: =IFERROR(__xludf.DUMMYFUNCTION("""COMPUTED_VALUE"""),"Jul") -> Jul | E11: =IFERROR(__xludf.DUMMYFUNCTION("""COMPUTED_VALUE"""),63.0) -> 63 | F11: =IFERROR(__xludf.DUMMYFUNCTION("""COMPUTED_VALUE"""),2400.0) -> 2400 | G11: =IF(A11="", "", HYPERLINK("https://wa.me/" & B11 & "?text=" & ENCODEURL("Hello " & IF(IFERROR(VLOOKUP(C11, 'Master Roster'!A:J, 10, FALSE), "")="Male", "Mr. ", "Ms. ") & A11 & ", this is a reminder that your rent balance of K" & F11 & " is due. Please make a payment,"), "Message on WhatsApp")) -> Message on WhatsApp | H11: =IF(ISBLANK(A11), "", HYPERLINK("sms:"&B11&"?body=Hello "&A11&", this is a reminder that your rent balance of "&F11&" is overdue.", "Send SMS")) -> Send SMS
A12: =IFERROR(__xludf.DUMMYFUNCTION("""COMPUTED_VALUE"""),"Chansa Chinyama") -> Chansa Chinyama | B12: =IFERROR(__xludf.DUMMYFUNCTION("""COMPUTED_VALUE"""),2.60974051468E11) -> 260974051468 | C12: =IFERROR(__xludf.DUMMYFUNCTION("""COMPUTED_VALUE"""),"NWG-24-C") -> NWG-24-C | D12: =IFERROR(__xludf.DUMMYFUNCTION("""COMPUTED_VALUE"""),"Jul") -> Jul | E12: =IFERROR(__xludf.DUMMYFUNCTION("""COMPUTED_VALUE"""),53.0) -> 53 | F12: =IFERROR(__xludf.DUMMYFUNCTION("""COMPUTED_VALUE"""),2400.0) -> 2400 | G12: =IF(A12="", "", HYPERLINK("https://wa.me/" & B12 & "?text=" & ENCODEURL("Hello " & IF(IFERROR(VLOOKUP(C12, 'Master Roster'!A:J, 10, FALSE), "")="Male", "Mr. ", "Ms. ") & A12 & ", this is a reminder that your rent balance of K" & F12 & " is due. Please make a payment,"), "Message on WhatsApp")) -> Message on WhatsApp | H12: =IF(ISBLANK(A12), "", HYPERLINK("sms:"&B12&"?body=Hello "&A12&", this is a reminder that your rent balance of "&F12&" is overdue.", "Send SMS")) -> Send SMS
A13: =IFERROR(__xludf.DUMMYFUNCTION("""COMPUTED_VALUE"""),"Kawina Florence") -> Kawina Florence | B13: =IFERROR(__xludf.DUMMYFUNCTION("""COMPUTED_VALUE"""),2.60976534878E11) -> 260976534878 | C13: =IFERROR(__xludf.DUMMYFUNCTION("""COMPUTED_VALUE"""),"NWG-24-D") -> NWG-24-D | D13: =IFERROR(__xludf.DUMMYFUNCTION("""COMPUTED_VALUE"""),"Jun") -> Jun | E13: =IFERROR(__xludf.DUMMYFUNCTION("""COMPUTED_VALUE"""),92.0) -> 92 | F13: =IFERROR(__xludf.DUMMYFUNCTION("""COMPUTED_VALUE"""),3600.0) -> 3600 | G13: =IF(A13="", "", HYPERLINK("https://wa.me/" & B13 & "?text=" & ENCODEURL("Hello " & IF(IFERROR(VLOOKUP(C13, 'Master Roster'!A:J, 10, FALSE), "")="Male", "Mr. ", "Ms. ") & A13 & ", this is a reminder that your rent balance of K" & F13 & " is due. Please make a payment,"), "Message on WhatsApp")) -> Message on WhatsApp | H13: =IF(ISBLANK(A13), "", HYPERLINK("sms:"&B13&"?body=Hello "&A13&", this is a reminder that your rent balance of "&F13&" is overdue.", "Send SMS")) -> Send SMS
G14: =IF(A14="", "", HYPERLINK("https://wa.me/" & B14 & "?text=" & ENCODEURL("Hello " & IF(IFERROR(VLOOKUP(C14, 'Master Roster'!A:J, 10, FALSE), "")="Male", "Mr. ", "Ms. ") & A14 & ", this is a reminder that your rent balance of K" & F14 & " is due. Please make a payment,"), "Message on WhatsApp")) | H14: =IF(ISBLANK(A14), "", HYPERLINK("sms:"&B14&"?body=Hello "&A14&", this is a reminder that your rent balance of "&F14&" is overdue.", "Send SMS"))
G15: =IF(A15="", "", HYPERLINK("https://wa.me/" & B15 & "?text=" & ENCODEURL("Hello " & IF(IFERROR(VLOOKUP(C15, 'Master Roster'!A:J, 10, FALSE), "")="Male", "Mr. ", "Ms. ") & A15 & ", this is a reminder that your rent balance of K" & F15 & " is due. Please make a payment,"), "Message on WhatsApp")) | H15: =IF(ISBLANK(A15), "", HYPERLINK("sms:"&B15&"?body=Hello "&A15&", this is a reminder that your rent balance of "&F15&" is overdue.", "Send SMS"))
G16: =IF(A16="", "", HYPERLINK("https://wa.me/" & B16 & "?text=" & ENCODEURL("Hello " & IF(IFERROR(VLOOKUP(C16, 'Master Roster'!A:J, 10, FALSE), "")="Male", "Mr. ", "Ms. ") & A16 & ", this is a reminder that your rent balance of K" & F16 & " is due. Please make a payment,"), "Message on WhatsApp")) | H16: =IF(ISBLANK(A16), "", HYPERLINK("sms:"&B16&"?body=Hello "&A16&", this is a reminder that your rent balance of "&F16&" is overdue.", "Send SMS"))
G17: =IF(A17="", "", HYPERLINK("https://wa.me/" & B17 & "?text=" & ENCODEURL("Hello " & IF(IFERROR(VLOOKUP(C17, 'Master Roster'!A:J, 10, FALSE), "")="Male", "Mr. ", "Ms. ") & A17 & ", this is a reminder that your rent balance of K" & F17 & " is due. Please make a payment,"), "Message on WhatsApp")) | H17: =IF(ISBLANK(A17), "", HYPERLINK("sms:"&B17&"?body=Hello "&A17&", this is a reminder that your rent balance of "&F17&" is overdue.", "Send SMS"))
G18: =IF(A18="", "", HYPERLINK("https://wa.me/" & B18 & "?text=" & ENCODEURL("Hello " & IF(IFERROR(VLOOKUP(C18, 'Master Roster'!A:J, 10, FALSE), "")="Male", "Mr. ", "Ms. ") & A18 & ", this is a reminder that your rent balance of K" & F18 & " is due. Please make a payment,"), "Message on WhatsApp")) | H18: =IF(ISBLANK(A18), "", HYPERLINK("sms:"&B18&"?body=Hello "&A18&", this is a reminder that your rent balance of "&F18&" is overdue.", "Send SMS"))
G19: =IF(A19="", "", HYPERLINK("https://wa.me/" & B19 & "?text=" & ENCODEURL("Hello " & IF(IFERROR(VLOOKUP(C19, 'Master Roster'!A:J, 10, FALSE), "")="Male", "Mr. ", "Ms. ") & A19 & ", this is a reminder that your rent balance of K" & F19 & " is due. Please make a payment,"), "Message on WhatsApp")) | H19: =IF(ISBLANK(A19), "", HYPERLINK("sms:"&B19&"?body=Hello "&A19&", this is a reminder that your rent balance of "&F19&" is overdue.", "Send SMS"))
G20: =IF(A20="", "", HYPERLINK("https://wa.me/" & B20 & "?text=" & ENCODEURL("Hello " & IF(IFERROR(VLOOKUP(C20, 'Master Roster'!A:J, 10, FALSE), "")="Male", "Mr. ", "Ms. ") & A20 & ", this is a reminder that your rent balance of K" & F20 & " is due. Please make a payment,"), "Message on WhatsApp")) | H20: =IF(ISBLANK(A20), "", HYPERLINK("sms:"&B20&"?body=Hello "&A20&", this is a reminder that your rent balance of "&F20&" is overdue.", "Send SMS"))
G21: =IF(A21="", "", HYPERLINK("https://wa.me/" & B21 & "?text=" & ENCODEURL("Hello " & IF(IFERROR(VLOOKUP(C21, 'Master Roster'!A:J, 10, FALSE), "")="Male", "Mr. ", "Ms. ") & A21 & ", this is a reminder that your rent balance of K" & F21 & " is due. Please make a payment,"), "Message on WhatsApp")) | H21: =IF(ISBLANK(A21), "", HYPERLINK("sms:"&B21&"?body=Hello "&A21&", this is a reminder that your rent balance of "&F21&" is overdue.", "Send SMS"))
G22: =IF(A22="", "", HYPERLINK("https://wa.me/" & B22 & "?text=" & ENCODEURL("Hello " & IF(IFERROR(VLOOKUP(C22, 'Master Roster'!A:J, 10, FALSE), "")="Male", "Mr. ", "Ms. ") & A22 & ", this is a reminder that your rent balance of K" & F22 & " is due. Please make a payment,"), "Message on WhatsApp")) | H22: =IF(ISBLANK(A22), "", HYPERLINK("sms:"&B22&"?body=Hello "&A22&", this is a reminder that your rent balance of "&F22&" is overdue.", "Send SMS"))
G23: =IF(A23="", "", HYPERLINK("https://wa.me/" & B23 & "?text=" & ENCODEURL("Hello " & IF(IFERROR(VLOOKUP(C23, 'Master Roster'!A:J, 10, FALSE), "")="Male", "Mr. ", "Ms. ") & A23 & ", this is a reminder that your rent balance of K" & F23 & " is due. Please make a payment,"), "Message on WhatsApp")) | H23: =IF(ISBLANK(A23), "", HYPERLINK("sms:"&B23&"?body=Hello "&A23&", this is a reminder that your rent balance of "&F23&" is overdue.", "Send SMS"))
G24: =IF(A24="", "", HYPERLINK("https://wa.me/" & B24 & "?text=" & ENCODEURL("Hello " & IF(IFERROR(VLOOKUP(C24, 'Master Roster'!A:J, 10, FALSE), "")="Male", "Mr. ", "Ms. ") & A24 & ", this is a reminder that your rent balance of K" & F24 & " is due. Please make a payment,"), "Message on WhatsApp")) | H24: =IF(ISBLANK(A24), "", HYPERLINK("sms:"&B24&"?body=Hello "&A24&", this is a reminder that your rent balance of "&F24&" is overdue.", "Send SMS"))
G25: =IF(A25="", "", HYPERLINK("https://wa.me/" & B25 & "?text=" & ENCODEURL("Hello " & IF(IFERROR(VLOOKUP(C25, 'Master Roster'!A:J, 10, FALSE), "")="Male", "Mr. ", "Ms. ") & A25 & ", this is a reminder that your rent balance of K" & F25 & " is due. Please make a payment,"), "Message on WhatsApp")) | H25: =IF(ISBLANK(A25), "", HYPERLINK("sms:"&B25&"?body=Hello "&A25&", this is a reminder that your rent balance of "&F25&" is overdue.", "Send SMS"))
... G100: =IF(A100="", "", HYPERLINK("https://wa.me/" & B100 & "?text=" & ENCODEURL("Hello " & IF(IFERROR(VLOOKUP(C100, 'Master Roster'!A:J, 10, FALSE), "")="Male", "Mr. ", "Ms. ") & A100 & ", this is a reminder that your rent balance of K" & F100 & " is due. Please make a payment,"), "Message on WhatsApp")) | H100: =IF(ISBLANK(A100), "", HYPERLINK("sms:"&B100&"?body=Hello "&A100&", this is a reminder that your rent balance of "&F100&" is overdue.", "Send SMS"))

Sheet Available Bed Spaces
A1: Available Bed Spaces | H1: Occupancy Report
A3: House/ Block | B3: Room No. | C3: Bed Space | D3: Monthly Rent | E3: Status | F3: Room Gender | H3: Gender | I3: Vacant | J3: Reserved | K3: Total
A4: =IFERROR(__xludf.DUMMYFUNCTION("IFERROR(FILTER({'Master Roster'!C4:C1006, 'Master Roster'!B4:B1006, 'Master Roster'!D4:D1006, 'Master Roster'!H4:H1006, 'Master Roster'!E4:E1006, 'Master Roster'!J4:J1006}, IF('Master Roster'!I1=""All Available"", (UPPER('Master Roster'!E4:E1006)=""VACANT"&""") + (UPPER('Master Roster'!E4:E1006)=""RESERVED""), UPPER('Master Roster'!E4:E1006)=UPPER('Master Roster'!I1))), {""No beds match the selected status"", """", """", """", """", """"})"),"BBH") -> BBH | B4: =IFERROR(__xludf.DUMMYFUNCTION("""COMPUTED_VALUE"""),7.0) -> 7 | C4: =IFERROR(__xludf.DUMMYFUNCTION("""COMPUTED_VALUE"""),"C") -> C | D4: =IFERROR(__xludf.DUMMYFUNCTION("""COMPUTED_VALUE"""),900.0) -> 900 | E4: =IFERROR(__xludf.DUMMYFUNCTION("""COMPUTED_VALUE"""),"Vacant") -> Vacant | F4: =IFERROR(__xludf.DUMMYFUNCTION("""COMPUTED_VALUE"""),"Female") -> Female | H4: Male | I4: =COUNTIFS('Master Roster'!$E$4:$E$1006, "Vacant", 'Master Roster'!$J$4:$J$1006, $H4) -> 3 | J4: =COUNTIFS('Master Roster'!$E$4:$E$1006, "Reserved", 'Master Roster'!$J$4:$J$1006, $H4) -> 0 | K4: =SUM(I4:J4) -> 3
A5: =IFERROR(__xludf.DUMMYFUNCTION("""COMPUTED_VALUE"""),"BBH") -> BBH | B5: =IFERROR(__xludf.DUMMYFUNCTION("""COMPUTED_VALUE"""),8.0) -> 8 | C5: =IFERROR(__xludf.DUMMYFUNCTION("""COMPUTED_VALUE"""),"B") -> B | D5: =IFERROR(__xludf.DUMMYFUNCTION("""COMPUTED_VALUE"""),900.0) -> 900 | E5: =IFERROR(__xludf.DUMMYFUNCTION("""COMPUTED_VALUE"""),"Vacant") -> Vacant | F5: =IFERROR(__xludf.DUMMYFUNCTION("""COMPUTED_VALUE"""),"Male") -> Male | H5: Female | I5: =COUNTIFS('Master Roster'!$E$4:$E$1006, "Vacant", 'Master Roster'!$J$4:$J$1006, $H5) -> 4 | J5: =COUNTIFS('Master Roster'!$E$4:$E$1006, "Reserved", 'Master Roster'!$J$4:$J$1006, $H5) -> 0 | K5: =SUM(I5:J5) -> 4
A6: =IFERROR(__xludf.DUMMYFUNCTION("""COMPUTED_VALUE"""),"BBH") -> BBH | B6: =IFERROR(__xludf.DUMMYFUNCTION("""COMPUTED_VALUE"""),9.0) -> 9 | C6: =IFERROR(__xludf.DUMMYFUNCTION("""COMPUTED_VALUE"""),"C") -> C | D6: =IFERROR(__xludf.DUMMYFUNCTION("""COMPUTED_VALUE"""),900.0) -> 900 | E6: =IFERROR(__xludf.DUMMYFUNCTION("""COMPUTED_VALUE"""),"Vacant") -> Vacant | F6: =IFERROR(__xludf.DUMMYFUNCTION("""COMPUTED_VALUE"""),"Female") -> Female | H6: Total | I6: =SUM(I4:I5) -> 7 | J6: =SUM(J4:J5) -> 0 | K6: =SUM(K4:K5) -> 7
A7: =IFERROR(__xludf.DUMMYFUNCTION("""COMPUTED_VALUE"""),"UPV") -> UPV | B7: =IFERROR(__xludf.DUMMYFUNCTION("""COMPUTED_VALUE"""),10.0) -> 10 | C7: =IFERROR(__xludf.DUMMYFUNCTION("""COMPUTED_VALUE"""),"D") -> D | D7: =IFERROR(__xludf.DUMMYFUNCTION("""COMPUTED_VALUE"""),900.0) -> 900 | E7: =IFERROR(__xludf.DUMMYFUNCTION("""COMPUTED_VALUE"""),"Vacant") -> Vacant | F7: =IFERROR(__xludf.DUMMYFUNCTION("""COMPUTED_VALUE"""),"Female") -> Female | H7: Bed Space Report
A8: =IFERROR(__xludf.DUMMYFUNCTION("""COMPUTED_VALUE"""),"CRV") -> CRV | B8: =IFERROR(__xludf.DUMMYFUNCTION("""COMPUTED_VALUE"""),16.0) -> 16 | C8: =IFERROR(__xludf.DUMMYFUNCTION("""COMPUTED_VALUE"""),"A") -> A | D8: =IFERROR(__xludf.DUMMYFUNCTION("""COMPUTED_VALUE"""),0.0) -> 0 | E8: =IFERROR(__xludf.DUMMYFUNCTION("""COMPUTED_VALUE"""),"Vacant") -> Vacant | F8: =IFERROR(__xludf.DUMMYFUNCTION("""COMPUTED_VALUE"""),"Male") -> Male | H8: Active Tenants | I8: =COUNTIFS('Master Roster'!E4:E1006, "<>VACANT", 'Master Roster'!E4:E1006, "<>RESERVED", 'Master Roster'!E4:E1006, "<>") -> 47
A9: =IFERROR(__xludf.DUMMYFUNCTION("""COMPUTED_VALUE"""),"NWG") -> NWG | B9: =IFERROR(__xludf.DUMMYFUNCTION("""COMPUTED_VALUE"""),22.0) -> 22 | C9: =IFERROR(__xludf.DUMMYFUNCTION("""COMPUTED_VALUE"""),"A") -> A | D9: =IFERROR(__xludf.DUMMYFUNCTION("""COMPUTED_VALUE"""),1200.0) -> 1200 | E9: =IFERROR(__xludf.DUMMYFUNCTION("""COMPUTED_VALUE"""),"Vacant") -> Vacant | F9: =IFERROR(__xludf.DUMMYFUNCTION("""COMPUTED_VALUE"""),"Male") -> Male | H9: Vacant/Reserved. | I9: =K6 -> 7
A10: =IFERROR(__xludf.DUMMYFUNCTION("""COMPUTED_VALUE"""),"NWG") -> NWG | B10: =IFERROR(__xludf.DUMMYFUNCTION("""COMPUTED_VALUE"""),23.0) -> 23 | C10: =IFERROR(__xludf.DUMMYFUNCTION("""COMPUTED_VALUE"""),"A") -> A | D10: =IFERROR(__xludf.DUMMYFUNCTION("""COMPUTED_VALUE"""),1200.0) -> 1200 | E10: =IFERROR(__xludf.DUMMYFUNCTION("""COMPUTED_VALUE"""),"Vacant") -> Vacant | F10: =IFERROR(__xludf.DUMMYFUNCTION("""COMPUTED_VALUE"""),"Female") -> Female | H10: Total Bed Spaces | I10: =I8+I9 -> 54
H11: Expeted Revenue | I11: =SUMIFS('Master Roster'!H4:H1006, 'Master Roster'!E4:E1006, "<>Vacant") -> 50250
H12: Full Capacity Revenue | I12: =SUM('Master Roster'!H:H) -> 56250
H13: Days 20-30 | I13: {=SUM(IF(ISNUMBER('Master Roster'!G4:G1006), IF((DAY('Master Roster'!G4:G1006)>=20)*(DAY('Master Roster'!G4:G1006)<=31), 'Master Roster'!H4:H1006, 0), 0))} -> 12400
H14: Days 1-5 | I14: {=SUM(IF(ISNUMBER('Master Roster'!G4:G1006), IF((DAY('Master Roster'!G4:G1006)>=1)*(DAY('Master Roster'!G4:G1006)<=5), 'Master Roster'!H4:H1006, 0), 0))} -> 18800 | J14: =I13+I14 -> 31200
H15: Days 1-5 Total | I15: =SUM(I17:I1006) -> 29500 | L15: Days 20-30 Total | M15: =SUM(M17:M1006) -> 20300
H16: Tenant Name | I16: Amount | J16: Entry Date | L16: Tenant Name | M16: Amount | N16: Entry Date
H17: =IFERROR(__xludf.DUMMYFUNCTION("IFERROR(ARRAYFORMULA(LET(names, 'Master Roster'!E4:E1006, base_amounts, 'Master Roster'!H4:H1006, dates, 'Master Roster'!G4:G1006, day_val, IF(dates="""", 0, IF(ISNUMBER(dates), DAY(dates), IFERROR(VALUE(LEFT(dates, FIND(""/"", dates)-1)), 0))), balances,"&" IFERROR(VLOOKUP(names, {'Monthly Billing Tab'!D4:D1006, 'Monthly Billing Tab'!L4:L1006}, 2, FALSE), 0), valid, (names<>"""") * (base_amounts<>"""") * (balances<>0), mask2, (day_val>=1)*(day_val<=5), keep, valid * mask2, SORT(FILTER({names, base_amounts, "&"dates}, keep), 3, TRUE))), ""No tenants found"")"),"Gabirel Kabwe") -> Gabirel Kabwe | I17: =IFERROR(__xludf.DUMMYFUNCTION("""COMPUTED_VALUE"""),1200.0) -> 1200 | J17: =IFERROR(__xludf.DUMMYFUNCTION("""COMPUTED_VALUE"""),46143.0) -> 46143 | L17: =IFERROR(__xludf.DUMMYFUNCTION("IFERROR(ARRAYFORMULA(LET(names, 'Master Roster'!E4:E1006, base_amounts, 'Master Roster'!H4:H1006, dates, 'Master Roster'!G4:G1006, day_val, IF(dates="""", 0, IF(ISNUMBER(dates), DAY(dates), IFERROR(VALUE(LEFT(dates, FIND(""/"", dates)-1)), 0))), balances,"&" IFERROR(VLOOKUP(names, {'Monthly Billing Tab'!D4:D1006, 'Monthly Billing Tab'!L4:L1006}, 2, FALSE), 0), valid, (names<>"""") * (base_amounts<>"""") * (balances<>0), mask2, (day_val>=20)*(day_val<=31), keep, valid * mask2, SORT(FILTER({names, base_amounts"&", dates}, keep), 3, TRUE))), ""No tenants found"")"),"Nanga Obrien") -> Nanga Obrien | M17: =IFERROR(__xludf.DUMMYFUNCTION("""COMPUTED_VALUE"""),900.0) -> 900 | N17: =IFERROR(__xludf.DUMMYFUNCTION("""COMPUTED_VALUE"""),46048.0) -> 46048
H18: =IFERROR(__xludf.DUMMYFUNCTION("""COMPUTED_VALUE"""),"McDonald") -> McDonald | I18: =IFERROR(__xludf.DUMMYFUNCTION("""COMPUTED_VALUE"""),900.0) -> 900 | J18: =IFERROR(__xludf.DUMMYFUNCTION("""COMPUTED_VALUE"""),46174.0) -> 46174 | L18: =IFERROR(__xludf.DUMMYFUNCTION("""COMPUTED_VALUE"""),"Lushomo gambwe") -> Lushomo gambwe | M18: =IFERROR(__xludf.DUMMYFUNCTION("""COMPUTED_VALUE"""),1200.0) -> 1200 | N18: =IFERROR(__xludf.DUMMYFUNCTION("""COMPUTED_VALUE"""),46078.0) -> 46078
H19: =IFERROR(__xludf.DUMMYFUNCTION("""COMPUTED_VALUE"""),"Collins Mubanga") -> Collins Mubanga | I19: =IFERROR(__xludf.DUMMYFUNCTION("""COMPUTED_VALUE"""),900.0) -> 900 | J19: =IFERROR(__xludf.DUMMYFUNCTION("""COMPUTED_VALUE"""),46176.0) -> 46176 | L19: =IFERROR(__xludf.DUMMYFUNCTION("""COMPUTED_VALUE"""),"Himalikiti Saviour") -> Himalikiti Saviour | M19: =IFERROR(__xludf.DUMMYFUNCTION("""COMPUTED_VALUE"""),950.0) -> 950 | N19: =IFERROR(__xludf.DUMMYFUNCTION("""COMPUTED_VALUE"""),46195.0) -> 46195
H20: =IFERROR(__xludf.DUMMYFUNCTION("""COMPUTED_VALUE"""),"Harriet nanyangwe") -> Harriet nanyangwe | I20: =IFERROR(__xludf.DUMMYFUNCTION("""COMPUTED_VALUE"""),1100.0) -> 1100 | J20: =IFERROR(__xludf.DUMMYFUNCTION("""COMPUTED_VALUE"""),46176.0) -> 46176 | L20: =IFERROR(__xludf.DUMMYFUNCTION("""COMPUTED_VALUE"""),"Kangwa Kunda") -> Kangwa Kunda | M20: =IFERROR(__xludf.DUMMYFUNCTION("""COMPUTED_VALUE"""),900.0) -> 900 | N20: =IFERROR(__xludf.DUMMYFUNCTION("""COMPUTED_VALUE"""),46198.0) -> 46198
H21: =IFERROR(__xludf.DUMMYFUNCTION("""COMPUTED_VALUE"""),"Wisdom Bwani") -> Wisdom Bwani | I21: =IFERROR(__xludf.DUMMYFUNCTION("""COMPUTED_VALUE"""),900.0) -> 900 | J21: =IFERROR(__xludf.DUMMYFUNCTION("""COMPUTED_VALUE"""),46178.0) -> 46178 | L21: =IFERROR(__xludf.DUMMYFUNCTION("""COMPUTED_VALUE"""),"Sara Matakala") -> Sara Matakala | M21: =IFERROR(__xludf.DUMMYFUNCTION("""COMPUTED_VALUE"""),900.0) -> 900 | N21: =IFERROR(__xludf.DUMMYFUNCTION("""COMPUTED_VALUE"""),46198.0) -> 46198
H22: =IFERROR(__xludf.DUMMYFUNCTION("""COMPUTED_VALUE"""),"Funny Muyamina") -> Funny Muyamina | I22: =IFERROR(__xludf.DUMMYFUNCTION("""COMPUTED_VALUE"""),900.0) -> 900 | J22: =IFERROR(__xludf.DUMMYFUNCTION("""COMPUTED_VALUE"""),46178.0) -> 46178 | L22: =IFERROR(__xludf.DUMMYFUNCTION("""COMPUTED_VALUE"""),"Samantha Musako (Kakompe)") -> Samantha Musako (Kakompe) | M22: =IFERROR(__xludf.DUMMYFUNCTION("""COMPUTED_VALUE"""),1200.0) -> 1200 | N22: =IFERROR(__xludf.DUMMYFUNCTION("""COMPUTED_VALUE"""),46199.0) -> 46199
H23: =IFERROR(__xludf.DUMMYFUNCTION("""COMPUTED_VALUE"""),"Treasure Simeenda") -> Treasure Simeenda | I23: =IFERROR(__xludf.DUMMYFUNCTION("""COMPUTED_VALUE"""),900.0) -> 900 | J23: =IFERROR(__xludf.DUMMYFUNCTION("""COMPUTED_VALUE"""),46178.0) -> 46178 | L23: =IFERROR(__xludf.DUMMYFUNCTION("""COMPUTED_VALUE"""),"Wendy Mpakise") -> Wendy Mpakise | M23: =IFERROR(__xludf.DUMMYFUNCTION("""COMPUTED_VALUE"""),900.0) -> 900 | N23: =IFERROR(__xludf.DUMMYFUNCTION("""COMPUTED_VALUE"""),46200.0) -> 46200
L24: =IFERROR(__xludf.DUMMYFUNCTION("""COMPUTED_VALUE"""),"Adrian mulale") -> Adrian mulale | M24: =IFERROR(__xludf.DUMMYFUNCTION("""COMPUTED_VALUE"""),950.0) -> 950 | N24: =IFERROR(__xludf.DUMMYFUNCTION("""COMPUTED_VALUE"""),46203.0) -> 46203
L25: =IFERROR(__xludf.DUMMYFUNCTION("""COMPUTED_VALUE"""),"Ackim Siamafuko") -> Ackim Siamafuko | M25: =IFERROR(__xludf.DUMMYFUNCTION("""COMPUTED_VALUE"""),1200.0) -> 1200 | N25: =IFERROR(__xludf.DUMMYFUNCTION("""COMPUTED_VALUE"""),46223.0) -> 46223
L26: =IFERROR(__xludf.DUMMYFUNCTION("""COMPUTED_VALUE"""),"Shadrach Munganini") -> Shadrach Munganini | M26: =IFERROR(__xludf.DUMMYFUNCTION("""COMPUTED_VALUE"""),900.0) -> 900 | N26: =IFERROR(__xludf.DUMMYFUNCTION("""COMPUTED_VALUE"""),46228.0) -> 46228
L27: =IFERROR(__xludf.DUMMYFUNCTION("""COMPUTED_VALUE"""),"Kuwunda Makondo") -> Kuwunda Makondo | M27: =IFERROR(__xludf.DUMMYFUNCTION("""COMPUTED_VALUE"""),1200.0) -> 1200 | N27: =IFERROR(__xludf.DUMMYFUNCTION("""COMPUTED_VALUE"""),46263.0) -> 46263
H30: TOTAL | I30: =SUM(I17:I25) -> 6800 | L30: TOTAL | M30: =SUM(M17:M25) -> 9100
H32: GRAND TOTAL | I32: =I30+M30 -> 15900

Sheet Monthly Billing Tab
A1: Monthly Billing Tab
C2: Search Tenant: | D2: Emely Mwale
A3: No. | B3: Billing ID | C3: House/Block | D3: Tenant Name | E3: Phone Number | F3: Current Rent | G3: Entry Date | H3: Adjustments / Fees | I3: Adjustment Notes | J3: Target Month | K3: {={"Accumulated Total"; IFERROR(IF(F4:F999="","", IF(J4:J999="","", F4:F999 * MONTH(J4:J999 & " 1"))), "")}} -> Accumulated Total | L3: {={"Total Balance"; IFERROR(IF(B4:B999="", "", IF((D4:D999="Vacant")+(D4:D999="Reserved"), 0, IF(((MONTH(TODAY())*F4:F999)+N(H4:H999)-K4:K999) < 0, 0, (MONTH(TODAY())*F4:F999)+N(H4:H999)-K4:K999))), "")}} -> Total Balance | M3: {={"Billing Status"; IF(D4:D999="", "", IF(D4:D999="Vacant", "Vacant", IF(L4:L999<=0, "✅ Paid / Secured", IF((L4:L999>F4:F999) + (TODAY() > DATE(YEAR(TODAY()), MONTH(TODAY()), DAY(G4:G999)) + 5), "❌ OVERDUE / UNPAID", IF(TODAY() >= DATE(YEAR(TODAY()), MONTH(TODAY()), DAY(G4:G999)), "⏳ Grace Period", "🟢 Open Window")))))}} -> Billing Status
A4: {=SEQUENCE(COUNTA(B4:B999),1)} -> 1 | B4: ANX-19-A | C4: =IFERROR(VLOOKUP($B4, 'Master Roster'!$A:$C, 3, FALSE), "") -> ANX | D4: =IFERROR(VLOOKUP($B4, 'Master Roster'!$A:$E, 5, FALSE), "") -> Samantha Musako (Kakompe) | E4: =IFERROR(VLOOKUP($B4, 'Master Roster'!$A:$F, 6, FALSE), "") -> 260977227794 | F4: =IFERROR(VLOOKUP($B4, 'Master Roster'!$A:$H, 8, FALSE), "") -> 1200 | G4: =IFERROR(VLOOKUP($B4, 'Master Roster'!$A:$G, 7, FALSE), "") -> 46199 | J4: Aug | K4: 9600 | L4: 1200 | M4: 🟢 Open Window
A5: 2 | B5: ANX-19-B | C5: =IFERROR(VLOOKUP($B5, 'Master Roster'!$A:$C, 3, FALSE), "") -> ANX | D5: =IFERROR(VLOOKUP($B5, 'Master Roster'!$A:$E, 5, FALSE), "") -> Chanda Lutashima | E5: =IFERROR(VLOOKUP($B5, 'Master Roster'!$A:$F, 6, FALSE), "") -> 260977951894 | F5: =IFERROR(VLOOKUP($B5, 'Master Roster'!$A:$H, 8, FALSE), "") -> 1200 | G5: =IFERROR(VLOOKUP($B5, 'Master Roster'!$A:$G, 7, FALSE), "") -> 46180 | J5: Sep | K5: 10800 | L5: 0 | M5: ✅ Paid / Secured
A6: 3 | B6: ANX-19-C | C6: =IFERROR(VLOOKUP($B6, 'Master Roster'!$A:$C, 3, FALSE), "") -> ANX | D6: =IFERROR(VLOOKUP($B6, 'Master Roster'!$A:$E, 5, FALSE), "") -> Josephine Nyirenda | E6: =IFERROR(VLOOKUP($B6, 'Master Roster'!$A:$F, 6, FALSE), "") -> 260779841908 | F6: =IFERROR(VLOOKUP($B6, 'Master Roster'!$A:$H, 8, FALSE), "") -> 1200 | G6: =IFERROR(VLOOKUP($B6, 'Master Roster'!$A:$G, 7, FALSE), "") -> 46148 | J6: Aug | K6: 9600 | L6: 1200 | M6: ⏳ Grace Period
A7: 4 | B7: ANX-19-D | C7: =IFERROR(VLOOKUP($B7, 'Master Roster'!$A:$C, 3, FALSE), "") -> ANX | D7: =IFERROR(VLOOKUP($B7, 'Master Roster'!$A:$E, 5, FALSE), "") -> Lubono Ruthendo | E7: =IFERROR(VLOOKUP($B7, 'Master Roster'!$A:$F, 6, FALSE), "") -> 260953618278 | F7: =IFERROR(VLOOKUP($B7, 'Master Roster'!$A:$H, 8, FALSE), "") -> 1200 | G7: =IFERROR(VLOOKUP($B7, 'Master Roster'!$A:$G, 7, FALSE), "") -> 46207 | J7: Sep | K7: 10800 | L7: 0 | M7: ✅ Paid / Secured
A8: 5 | B8: ANX-20-A | C8: =IFERROR(VLOOKUP($B8, 'Master Roster'!$A:$C, 3, FALSE), "") -> ANX | D8: =IFERROR(VLOOKUP($B8, 'Master Roster'!$A:$E, 5, FALSE), "") -> Steven Musonda | E8: =IFERROR(VLOOKUP($B8, 'Master Roster'!$A:$F, 6, FALSE), "") -> 260975303236 | F8: =IFERROR(VLOOKUP($B8, 'Master Roster'!$A:$H, 8, FALSE), "") -> 1400 | G8: =IFERROR(VLOOKUP($B8, 'Master Roster'!$A:$G, 7, FALSE), "") -> 46178 | J8: Sep | K8: 12600 | L8: 0 | M8: ✅ Paid / Secured
A9: 6 | B9: BBH-1-A | C9: =IFERROR(VLOOKUP($B9, 'Master Roster'!$A:$C, 3, FALSE), "") -> BBH | D9: =IFERROR(VLOOKUP($B9, 'Master Roster'!$A:$E, 5, FALSE), "") -> Adrian mulale | E9: =IFERROR(VLOOKUP($B9, 'Master Roster'!$A:$F, 6, FALSE), "") -> 260977146630 | F9: =IFERROR(VLOOKUP($B9, 'Master Roster'!$A:$H, 8, FALSE), "") -> 950 | G9: =IFERROR(VLOOKUP($B9, 'Master Roster'!$A:$G, 7, FALSE), "") -> 46203 | J9: Aug | K9: 7600 | L9: 950 | M9: 🟢 Open Window
A10: 7 | B10: BBH-2-A | C10: =IFERROR(VLOOKUP($B10, 'Master Roster'!$A:$C, 3, FALSE), "") -> BBH | D10: =IFERROR(VLOOKUP($B10, 'Master Roster'!$A:$E, 5, FALSE), "") -> Wisdom Bwani | E10: =IFERROR(VLOOKUP($B10, 'Master Roster'!$A:$F, 6, FALSE), "") -> 260776960320 | F10: =IFERROR(VLOOKUP($B10, 'Master Roster'!$A:$H, 8, FALSE), "") -> 900 | G10: =IFERROR(VLOOKUP($B10, 'Master Roster'!$A:$G, 7, FALSE), "") -> 46178 | J10: Aug | K10: 7200 | L10: 900 | M10: ⏳ Grace Period
A11: 8 | B11: BBH-2-B | C11: =IFERROR(VLOOKUP($B11, 'Master Roster'!$A:$C, 3, FALSE), "") -> BBH | D11: =IFERROR(VLOOKUP($B11, 'Master Roster'!$A:$E, 5, FALSE), "") -> Jackson Mwanza | E11: =IFERROR(VLOOKUP($B11, 'Master Roster'!$A:$F, 6, FALSE), "") -> 260976625656 | F11: =IFERROR(VLOOKUP($B11, 'Master Roster'!$A:$H, 8, FALSE), "") -> 900 | G11: =IFERROR(VLOOKUP($B11, 'Master Roster'!$A:$G, 7, FALSE), "") -> 46181 | H11: -600 | J11: Jul | K11: 6300 | L11: 1200 | M11: ❌ OVERDUE / UNPAID
A12: 9 | B12: BBH-3-A | C12: =IFERROR(VLOOKUP($B12, 'Master Roster'!$A:$C, 3, FALSE), "") -> BBH | D12: =IFERROR(VLOOKUP($B12, 'Master Roster'!$A:$E, 5, FALSE), "") -> Prosper Kalayi | E12: =IFERROR(VLOOKUP($B12, 'Master Roster'!$A:$F, 6, FALSE), "") -> 260970522913 | F12: =IFERROR(VLOOKUP($B12, 'Master Roster'!$A:$H, 8, FALSE), "") -> 900 | G12: =IFERROR(VLOOKUP($B12, 'Master Roster'!$A:$G, 7, FALSE), "") -> 46186 | J12: Aug | K12: 7200 | L12: 900 | M12: 🟢 Open Window
A13: 10 | B13: BBH-3-B | C13: =IFERROR(VLOOKUP($B13, 'Master Roster'!$A:$C, 3, FALSE), "") -> BBH | D13: =IFERROR(VLOOKUP($B13, 'Master Roster'!$A:$E, 5, FALSE), "") -> Shadrach Munganini | E13: =IFERROR(VLOOKUP($B13, 'Master Roster'!$A:$F, 6, FALSE), "") -> 260979567550 | F13: =IFERROR(VLOOKUP($B13, 'Master Roster'!$A:$H, 8, FALSE), "") -> 900 | G13: =IFERROR(VLOOKUP($B13, 'Master Roster'!$A:$G, 7, FALSE), "") -> 46228 | J13: Aug | K13: 7200 | L13: 900 | M13: 🟢 Open Window
A14: 11 | B14: BBH-3-C | C14: =IFERROR(VLOOKUP($B14, 'Master Roster'!$A:$C, 3, FALSE), "") -> BBH | D14: =IFERROR(VLOOKUP($B14, 'Master Roster'!$A:$E, 5, FALSE), "") -> Collins Mubanga | E14: =IFERROR(VLOOKUP($B14, 'Master Roster'!$A:$F, 6, FALSE), "") -> 260777237029 | F14: =IFERROR(VLOOKUP($B14, 'Master Roster'!$A:$H, 8, FALSE), "") -> 900 | G14: =IFERROR(VLOOKUP($B14, 'Master Roster'!$A:$G, 7, FALSE), "") -> 46176 | J14: Aug | K14: 7200 | L14: 900 | M14: ⏳ Grace Period
A15: 12 | B15: BBH-4-A | C15: =IFERROR(VLOOKUP($B15, 'Master Roster'!$A:$C, 3, FALSE), "") -> BBH | D15: =IFERROR(VLOOKUP($B15, 'Master Roster'!$A:$E, 5, FALSE), "") -> Himalikiti Saviour | E15: =IFERROR(VLOOKUP($B15, 'Master Roster'!$A:$F, 6, FALSE), "") -> 260975547126 | F15: =IFERROR(VLOOKUP($B15, 'Master Roster'!$A:$H, 8, FALSE), "") -> 950 | G15: =IFERROR(VLOOKUP($B15, 'Master Roster'!$A:$G, 7, FALSE), "") -> 46195 | J15: Jul | K15: 6650 | L15: 1900 | M15: ❌ OVERDUE / UNPAID
A16: 13 | B16: BBH-5-A | C16: =IFERROR(VLOOKUP($B16, 'Master Roster'!$A:$C, 3, FALSE), "") -> BBH | D16: =IFERROR(VLOOKUP($B16, 'Master Roster'!$A:$E, 5, FALSE), "") -> Wampa | E16: =IFERROR(VLOOKUP($B16, 'Master Roster'!$A:$F, 6, FALSE), "") -> 260971071877 | F16: =IFERROR(VLOOKUP($B16, 'Master Roster'!$A:$H, 8, FALSE), "") -> 0 | G16: =IFERROR(VLOOKUP($B16, 'Master Roster'!$A:$G, 7, FALSE), "") -> 46225 | I16: Excluded - Wampa | J16: Jul | K16: 0 | L16: 0 | M16: ✅ Paid / Secured
A17: 14 | B17: BBH-6-A | C17: =IFERROR(VLOOKUP($B17, 'Master Roster'!$A:$C, 3, FALSE), "") -> BBH | D17: =IFERROR(VLOOKUP($B17, 'Master Roster'!$A:$E, 5, FALSE), "") -> McDonald | E17: =IFERROR(VLOOKUP($B17, 'Master Roster'!$A:$F, 6, FALSE), "") -> 260773456119 | F17: =IFERROR(VLOOKUP($B17, 'Master Roster'!$A:$H, 8, FALSE), "") -> 900 | G17: =IFERROR(VLOOKUP($B17, 'Master Roster'!$A:$G, 7, FALSE), "") -> 46174 | H17: -1000 | I17: Part Payment | J17: May | K17: 4500 | L17: 2600 | M17: ❌ OVERDUE / UNPAID
A18: 15 | B18: BBH-6-B | C18: =IFERROR(VLOOKUP($B18, 'Master Roster'!$A:$C, 3, FALSE), "") -> BBH | D18: =IFERROR(VLOOKUP($B18, 'Master Roster'!$A:$E, 5, FALSE), "") -> Nanga Obrien | E18: =IFERROR(VLOOKUP($B18, 'Master Roster'!$A:$F, 6, FALSE), "") -> 260770838758 | F18: =IFERROR(VLOOKUP($B18, 'Master Roster'!$A:$H, 8, FALSE), "") -> 900 | G18: =IFERROR(VLOOKUP($B18, 'Master Roster'!$A:$G, 7, FALSE), "") -> 46048 | J18: May | K18: 4500 | L18: 3600 | M18: ❌ OVERDUE / UNPAID
A19: 16 | B19: BBH-6-C | C19: =IFERROR(VLOOKUP($B19, 'Master Roster'!$A:$C, 3, FALSE), "") -> BBH | D19: =IFERROR(VLOOKUP($B19, 'Master Roster'!$A:$E, 5, FALSE), "") -> Zick Phiri | E19: =IFERROR(VLOOKUP($B19, 'Master Roster'!$A:$F, 6, FALSE), "") -> 260973072762 | F19: =IFERROR(VLOOKUP($B19, 'Master Roster'!$A:$H, 8, FALSE), "") -> 900 | G19: =IFERROR(VLOOKUP($B19, 'Master Roster'!$A:$G, 7, FALSE), "") -> 46184 | J19: Aug | K19: 7200 | L19: 900 | M19: 🟢 Open Window
A20: 17 | B20: BBH-7-A | C20: =IFERROR(VLOOKUP($B20, 'Master Roster'!$A:$C, 3, FALSE), "") -> BBH | D20: =IFERROR(VLOOKUP($B20, 'Master Roster'!$A:$E, 5, FALSE), "") -> Funny Muyamina | E20: =IFERROR(VLOOKUP($B20, 'Master Roster'!$A:$F, 6, FALSE), "") -> 260771096585 | F20: =IFERROR(VLOOKUP($B20, 'Master Roster'!$A:$H, 8, FALSE), "") -> 900 | G20: =IFERROR(VLOOKUP($B20, 'Master Roster'!$A:$G, 7, FALSE), "") -> 46178 | J20: Aug | K20: 7200 | L20: 900 | M20: ⏳ Grace Period
A21: 18 | B21: BBH-7-B | C21: =IFERROR(VLOOKUP($B21, 'Master Roster'!$A:$C, 3, FALSE), "") -> BBH | D21: =IFERROR(VLOOKUP($B21, 'Master Roster'!$A:$E, 5, FALSE), "") -> Treasure Simeenda | E21: =IFERROR(VLOOKUP($B21, 'Master Roster'!$A:$F, 6, FALSE), "") -> 260772393278 | F21: =IFERROR(VLOOKUP($B21, 'Master Roster'!$A:$H, 8, FALSE), "") -> 900 | G21: =IFERROR(VLOOKUP($B21, 'Master Roster'!$A:$G, 7, FALSE), "") -> 46178 | J21: Aug | K21: 7200 | L21: 900 | M21: ⏳ Grace Period
A22: 19 | B22: BBH-7-C | C22: =IFERROR(VLOOKUP($B22, 'Master Roster'!$A:$C, 3, FALSE), "") -> BBH | D22: =IFERROR(VLOOKUP($B22, 'Master Roster'!$A:$E, 5, FALSE), "") -> Vacant | E22: =IFERROR(VLOOKUP($B22, 'Master Roster'!$A:$F, 6, FALSE), "") | F22: =IFERROR(VLOOKUP($B22, 'Master Roster'!$A:$H, 8, FALSE), "") -> 900 | G22: =IFERROR(VLOOKUP($B22, 'Master Roster'!$A:$G, 7, FALSE), "") | J22: Jun | K22: 5400 | L22: 0 | M22: Vacant
A23: 20 | B23: BBH-8-A | C23: =IFERROR(VLOOKUP($B23, 'Master Roster'!$A:$C, 3, FALSE), "") -> BBH | D23: =IFERROR(VLOOKUP($B23, 'Master Roster'!$A:$E, 5, FALSE), "") -> Kangwa Kunda | E23: =IFERROR(VLOOKUP($B23, 'Master Roster'!$A:$F, 6, FALSE), "") -> 260972024337 | F23: =IFERROR(VLOOKUP($B23, 'Master Roster'!$A:$H, 8, FALSE), "") -> 900 | G23: =IFERROR(VLOOKUP($B23, 'Master Roster'!$A:$G, 7, FALSE), "") -> 46198 | J23: Aug | K23: 7200 | L23: 900 | M23: 🟢 Open Window
A24: 21 | B24: BBH-8-B | C24: =IFERROR(VLOOKUP($B24, 'Master Roster'!$A:$C, 3, FALSE), "") -> BBH | D24: =IFERROR(VLOOKUP($B24, 'Master Roster'!$A:$E, 5, FALSE), "") -> Vacant | E24: =IFERROR(VLOOKUP($B24, 'Master Roster'!$A:$F, 6, FALSE), "") | F24: =IFERROR(VLOOKUP($B24, 'Master Roster'!$A:$H, 8, FALSE), "") -> 900 | G24: =IFERROR(VLOOKUP($B24, 'Master Roster'!$A:$G, 7, FALSE), "") | J24: Jun | K24: 5400 | L24: 0 | M24: Vacant
A25: 22 | B25: BBH-9-A | C25: =IFERROR(VLOOKUP($B25, 'Master Roster'!$A:$C, 3, FALSE), "") -> BBH | D25: =IFERROR(VLOOKUP($B25, 'Master Roster'!$A:$E, 5, FALSE), "") -> Felistus Mweemba | E25: =IFERROR(VLOOKUP($B25, 'Master Roster'!$A:$F, 6, FALSE), "") -> 260764785030 | F25: =IFERROR(VLOOKUP($B25, 'Master Roster'!$A:$H, 8, FALSE), "") -> 900 | G25: =IFERROR(VLOOKUP($B25, 'Master Roster'!$A:$G, 7, FALSE), "") -> 46182 | J25: Aug | K25: 7200 | L25: 900 | M25: 🟢 Open Window
A26: 23 | B26: BBH-9-B | C26: =IFERROR(VLOOKUP($B26, 'Master Roster'!$A:$C, 3, FALSE), "") -> BBH | D26: =IFERROR(VLOOKUP($B26, 'Master Roster'!$A:$E, 5, FALSE), "") -> Wendy Mpakise | E26: =IFERROR(VLOOKUP($B26, 'Master Roster'!$A:$F, 6, FALSE), "") -> 260971977845 | F26: =IFERROR(VLOOKUP($B26, 'Master Roster'!$A:$H, 8, FALSE), "") -> 900 | G26: =IFERROR(VLOOKUP($B26, 'Master Roster'!$A:$G, 7, FALSE), "") -> 46200 | J26: Jul | K26: 6300 | L26: 1800 | M26: ❌ OVERDUE / UNPAID
A27: 24 | B27: BBH-9-C | C27: =IFERROR(VLOOKUP($B27, 'Master Roster'!$A:$C, 3, FALSE), "") -> BBH | D27: =IFERROR(VLOOKUP($B27, 'Master Roster'!$A:$E, 5, FALSE), "") -> Vacant | E27: =IFERROR(VLOOKUP($B27, 'Master Roster'!$A:$F, 6, FALSE), "") | F27: =IFERROR(VLOOKUP($B27, 'Master Roster'!$A:$H, 8, FALSE), "") -> 900 | G27: =IFERROR(VLOOKUP($B27, 'Master Roster'!$A:$G, 7, FALSE), "") | J27: Jul | K27: 6300 | L27: 0 | M27: Vacant
A28: 25 | B28: CRV-16-A | C28: =IFERROR(VLOOKUP($B28, 'Master Roster'!$A:$C, 3, FALSE), "") -> CRV | D28: =IFERROR(VLOOKUP($B28, 'Master Roster'!$A:$E, 5, FALSE), "") -> Vacant | E28: =IFERROR(VLOOKUP($B28, 'Master Roster'!$A:$F, 6, FALSE), "") -> 20772046008 | F28: =IFERROR(VLOOKUP($B28, 'Master Roster'!$A:$H, 8, FALSE), "") -> 0 | G28: =IFERROR(VLOOKUP($B28, 'Master Roster'!$A:$G, 7, FALSE), "") -> 46223 | J28: Aug | K28: 0 | L28: 0 | M28: Vacant
A29: 26 | B29: CRV-16-B | C29: =IFERROR(VLOOKUP($B29, 'Master Roster'!$A:$C, 3, FALSE), "") -> CRV | D29: =IFERROR(VLOOKUP($B29, 'Master Roster'!$A:$E, 5, FALSE), "") -> Ackim Siamafuko | E29: =IFERROR(VLOOKUP($B29, 'Master Roster'!$A:$F, 6, FALSE), "") -> 20772046008 | F29: =IFERROR(VLOOKUP($B29, 'Master Roster'!$A:$H, 8, FALSE), "") -> 1200 | G29: =IFERROR(VLOOKUP($B29, 'Master Roster'!$A:$G, 7, FALSE), "") -> 46223 | J29: Aug | K29: 9600 | L29: 1200 | M29: 🟢 Open Window
... A31: 28 | B31: CRV-18-A | C31: =IFERROR(VLOOKUP($B31, 'Master Roster'!$A:$C, 3, FALSE), "") -> CRV | D31: =IFERROR(VLOOKUP($B31, 'Master Roster'!$A:$E, 5, FALSE), "") -> Christopher Tambule | E31: =IFERROR(VLOOKUP($B31, 'Master Roster'!$A:$F, 6, FALSE), "") -> 260972108866 | F31: =IFERROR(VLOOKUP($B31, 'Master Roster'!$A:$H, 8, FALSE), "") -> 1200 | G31: =IFERROR(VLOOKUP($B31, 'Master Roster'!$A:$G, 7, FALSE), "") -> 46190 | J31: Aug | K31: 9600 | L31: 1200 | M31: 🟢 Open Window
A32: 29 | B32: NWG-21-A | C32: =IFERROR(VLOOKUP($B32, 'Master Roster'!$A:$C, 3, FALSE), "") -> NWG | D32: =IFERROR(VLOOKUP($B32, 'Master Roster'!$A:$E, 5, FALSE), "") -> Lukundo Siame | E32: =IFERROR(VLOOKUP($B32, 'Master Roster'!$A:$F, 6, FALSE), "") -> 260760833629 | F32: =IFERROR(VLOOKUP($B32, 'Master Roster'!$A:$H, 8, FALSE), "") -> 1200 | G32: =IFERROR(VLOOKUP($B32, 'Master Roster'!$A:$G, 7, FALSE), "") -> 46191 | H32: -1150 | J32: Jul | K32: 8400 | L32: 1250 | M32: ❌ OVERDUE / UNPAID
A33: 30 | B33: NWG-21-B | C33: =IFERROR(VLOOKUP($B33, 'Master Roster'!$A:$C, 3, FALSE), "") -> NWG | D33: =IFERROR(VLOOKUP($B33, 'Master Roster'!$A:$E, 5, FALSE), "") -> Gabirel Kabwe | E33: =IFERROR(VLOOKUP($B33, 'Master Roster'!$A:$F, 6, FALSE), "") -> 260968723095 | F33: =IFERROR(VLOOKUP($B33, 'Master Roster'!$A:$H, 8, FALSE), "") -> 1200 | G33: =IFERROR(VLOOKUP($B33, 'Master Roster'!$A:$G, 7, FALSE), "") -> 46143 | J33: Aug | K33: 9600 | L33: 1200 | M33: ❌ OVERDUE / UNPAID
A34: 31 | B34: NWG-21-C | C34: =IFERROR(VLOOKUP($B34, 'Master Roster'!$A:$C, 3, FALSE), "") -> NWG | D34: =IFERROR(VLOOKUP($B34, 'Master Roster'!$A:$E, 5, FALSE), "") -> Chama Kampamba | E34: =IFERROR(VLOOKUP($B34, 'Master Roster'!$A:$F, 6, FALSE), "") -> 260770055753 | F34: =IFERROR(VLOOKUP($B34, 'Master Roster'!$A:$H, 8, FALSE), "") -> 1200 | G34: =IFERROR(VLOOKUP($B34, 'Master Roster'!$A:$G, 7, FALSE), "") -> 46179 | J34: Jul | K34: 8400 | L34: 2400 | M34: ❌ OVERDUE / UNPAID
A35: 32 | B35: NWG-21-D | C35: =IFERROR(VLOOKUP($B35, 'Master Roster'!$A:$C, 3, FALSE), "") -> NWG | D35: =IFERROR(VLOOKUP($B35, 'Master Roster'!$A:$E, 5, FALSE), "") -> Jairos Banda | E35: =IFERROR(VLOOKUP($B35, 'Master Roster'!$A:$F, 6, FALSE), "") -> 260776136398 | F35: =IFERROR(VLOOKUP($B35, 'Master Roster'!$A:$H, 8, FALSE), "") -> 1200 | G35: =IFERROR(VLOOKUP($B35, 'Master Roster'!$A:$G, 7, FALSE), "") -> 46174 | J35: Sep | K35: 10800 | L35: 0 | M35: ✅ Paid / Secured
A36: 33 | B36: NWG-22-A | C36: =IFERROR(VLOOKUP($B36, 'Master Roster'!$A:$C, 3, FALSE), "") -> NWG | D36: =IFERROR(VLOOKUP($B36, 'Master Roster'!$A:$E, 5, FALSE), "") -> Vacant | E36: =IFERROR(VLOOKUP($B36, 'Master Roster'!$A:$F, 6, FALSE), "") | F36: =IFERROR(VLOOKUP($B36, 'Master Roster'!$A:$H, 8, FALSE), "") -> 1200 | G36: =IFERROR(VLOOKUP($B36, 'Master Roster'!$A:$G, 7, FALSE), "") | J36: Jun | K36: 7200 | L36: 0 | M36: Vacant
A37: 34 | B37: NWG-22-B | C37: =IFERROR(VLOOKUP($B37, 'Master Roster'!$A:$C, 3, FALSE), "") -> NWG | D37: =IFERROR(VLOOKUP($B37, 'Master Roster'!$A:$E, 5, FALSE), "") -> David Mulila | E37: =IFERROR(VLOOKUP($B37, 'Master Roster'!$A:$F, 6, FALSE), "") -> 260775161085 | F37: =IFERROR(VLOOKUP($B37, 'Master Roster'!$A:$H, 8, FALSE), "") -> 1200 | G37: =IFERROR(VLOOKUP($B37, 'Master Roster'!$A:$G, 7, FALSE), "") -> 46191 | J37: Aug | K37: 9600 | L37: 1200 | M37: 🟢 Open Window
A38: 35 | B38: NWG-22-C | C38: =IFERROR(VLOOKUP($B38, 'Master Roster'!$A:$C, 3, FALSE), "") -> NWG | D38: =IFERROR(VLOOKUP($B38, 'Master Roster'!$A:$E, 5, FALSE), "") -> Ongani Madaliso Gabriel | E38: =IFERROR(VLOOKUP($B38, 'Master Roster'!$A:$F, 6, FALSE), "") -> 260771736585 | F38: =IFERROR(VLOOKUP($B38, 'Master Roster'!$A:$H, 8, FALSE), "") -> 1200 | G38: =IFERROR(VLOOKUP($B38, 'Master Roster'!$A:$G, 7, FALSE), "") -> 46174 | J38: Sep | K38: 10800 | L38: 0 | M38: ✅ Paid / Secured
A39: 36 | B39: NWG-22-D | C39: =IFERROR(VLOOKUP($B39, 'Master Roster'!$A:$C, 3, FALSE), "") -> NWG | D39: =IFERROR(VLOOKUP($B39, 'Master Roster'!$A:$E, 5, FALSE), "") -> Christopher Phiri | E39: =IFERROR(VLOOKUP($B39, 'Master Roster'!$A:$F, 6, FALSE), "") -> 260772109688 | F39: =IFERROR(VLOOKUP($B39, 'Master Roster'!$A:$H, 8, FALSE), "") -> 1200 | G39: =IFERROR(VLOOKUP($B39, 'Master Roster'!$A:$G, 7, FALSE), "") -> 46176 | J39: Sep | K39: 10800 | L39: 0 | M39: ✅ Paid / Secured
A40: 37 | B40: NWG-23-A | C40: =IFERROR(VLOOKUP($B40, 'Master Roster'!$A:$C, 3, FALSE), "") -> NWG | D40: =IFERROR(VLOOKUP($B40, 'Master Roster'!$A:$E, 5, FALSE), "") -> Vacant | E40: =IFERROR(VLOOKUP($B40, 'Master Roster'!$A:$F, 6, FALSE), "") -> 260973131421 | F40: =IFERROR(VLOOKUP($B40, 'Master Roster'!$A:$H, 8, FALSE), "") -> 1200 | G40: =IFERROR(VLOOKUP($B40, 'Master Roster'!$A:$G, 7, FALSE), "") -> 46198 | J40: Jul | K40: 8400 | L40: 0 | M40: Vacant
A41: 38 | B41: NWG-23-B | C41: =IFERROR(VLOOKUP($B41, 'Master Roster'!$A:$C, 3, FALSE), "") -> NWG | D41: =IFERROR(VLOOKUP($B41, 'Master Roster'!$A:$E, 5, FALSE), "") -> Catherine Mphande | E41: =IFERROR(VLOOKUP($B41, 'Master Roster'!$A:$F, 6, FALSE), "") -> 260963575803 | F41: =IFERROR(VLOOKUP($B41, 'Master Roster'!$A:$H, 8, FALSE), "") -> 1200 | G41: =IFERROR(VLOOKUP($B41, 'Master Roster'!$A:$G, 7, FALSE), "") -> 46187 | J41: Aug | K41: 9600 | L41: 1200 | M41: 🟢 Open Window
A42: 39 | B42: NWG-23-C | C42: =IFERROR(VLOOKUP($B42, 'Master Roster'!$A:$C, 3, FALSE), "") -> NWG | D42: =IFERROR(VLOOKUP($B42, 'Master Roster'!$A:$E, 5, FALSE), "") -> Grace Mwamba | E42: =IFERROR(VLOOKUP($B42, 'Master Roster'!$A:$F, 6, FALSE), "") -> 260957144512 | F42: =IFERROR(VLOOKUP($B42, 'Master Roster'!$A:$H, 8, FALSE), "") -> 1200 | G42: =IFERROR(VLOOKUP($B42, 'Master Roster'!$A:$G, 7, FALSE), "") -> 46184 | J42: Aug | K42: 9600 | L42: 1200 | M42: 🟢 Open Window
A43: 40 | B43: NWG-23-D | C43: =IFERROR(VLOOKUP($B43, 'Master Roster'!$A:$C, 3, FALSE), "") -> NWG | D43: =IFERROR(VLOOKUP($B43, 'Master Roster'!$A:$E, 5, FALSE), "") -> Lushomo gambwe | E43: =IFERROR(VLOOKUP($B43, 'Master Roster'!$A:$F, 6, FALSE), "") -> 260970183545 | F43: =IFERROR(VLOOKUP($B43, 'Master Roster'!$A:$H, 8, FALSE), "") -> 1200 | G43: =IFERROR(VLOOKUP($B43, 'Master Roster'!$A:$G, 7, FALSE), "") -> 46078 | J43: Aug | K43: 9600 | L43: 1200 | M43: 🟢 Open Window
A44: 41 | B44: NWG-23-E | C44: =IFERROR(VLOOKUP($B44, 'Master Roster'!$A:$C, 3, FALSE), "") -> NWG | D44: =IFERROR(VLOOKUP($B44, 'Master Roster'!$A:$E, 5, FALSE), "") -> Jacqueline Mwape | E44: =IFERROR(VLOOKUP($B44, 'Master Roster'!$A:$F, 6, FALSE), "") -> 260761423674 | F44: =IFERROR(VLOOKUP($B44, 'Master Roster'!$A:$H, 8, FALSE), "") -> 1200 | G44: =IFERROR(VLOOKUP($B44, 'Master Roster'!$A:$G, 7, FALSE), "") -> 46190 | J44: Aug | K44: 9600 | L44: 1200 | M44: 🟢 Open Window
A45: 42 | B45: NWG-24-A | C45: =IFERROR(VLOOKUP($B45, 'Master Roster'!$A:$C, 3, FALSE), "") -> NWG | D45: =IFERROR(VLOOKUP($B45, 'Master Roster'!$A:$E, 5, FALSE), "") -> Chami Soneka | E45: {=_xlfn.XLOOKUP(B45, 'Master Roster'!A:A, 'Master Roster'!F:F, "")} -> 260969410900 | F45: =IFERROR(VLOOKUP($B45, 'Master Roster'!$A:$H, 8, FALSE), "") -> 1200 | G45: =IFERROR(VLOOKUP($B45, 'Master Roster'!$A:$G, 7, FALSE), "") -> 46235 | J45: Sep | K45: 10800 | L45: 0 | M45: ✅ Paid / Secured
A46: 43 | B46: NWG-24-B | C46: =IFERROR(VLOOKUP($B46, 'Master Roster'!$A:$C, 3, FALSE), "") -> NWG | D46: =IFERROR(VLOOKUP($B46, 'Master Roster'!$A:$E, 5, FALSE), "") -> Kuwunda Makondo | E46: =IFERROR(VLOOKUP($B46, 'Master Roster'!$A:$F, 6, FALSE), "") -> 260774614576 | F46: =IFERROR(VLOOKUP($B46, 'Master Roster'!$A:$H, 8, FALSE), "") -> 1200 | G46: =IFERROR(VLOOKUP($B46, 'Master Roster'!$A:$G, 7, FALSE), "") -> 46263 | J46: Aug | K46: 9600 | L46: 1200 | M46: 🟢 Open Window
A47: 44 | B47: NWG-24-C | C47: =IFERROR(VLOOKUP($B47, 'Master Roster'!$A:$C, 3, FALSE), "") -> NWG | D47: =IFERROR(VLOOKUP($B47, 'Master Roster'!$A:$E, 5, FALSE), "") -> Chansa Chinyama | E47: =IFERROR(VLOOKUP($B47, 'Master Roster'!$A:$F, 6, FALSE), "") -> 260974051468 | F47: =IFERROR(VLOOKUP($B47, 'Master Roster'!$A:$H, 8, FALSE), "") -> 1200 | G47: =IFERROR(VLOOKUP($B47, 'Master Roster'!$A:$G, 7, FALSE), "") -> 46189 | J47: Jul | K47: 8400 | L47: 2400 | M47: ❌ OVERDUE / UNPAID
A48: 45 | B48: NWG-24-D | C48: =IFERROR(VLOOKUP($B48, 'Master Roster'!$A:$C, 3, FALSE), "") -> NWG | D48: =IFERROR(VLOOKUP($B48, 'Master Roster'!$A:$E, 5, FALSE), "") -> Kawina Florence | E48: =IFERROR(VLOOKUP($B48, 'Master Roster'!$A:$F, 6, FALSE), "") -> 260976534878 | F48: =IFERROR(VLOOKUP($B48, 'Master Roster'!$A:$H, 8, FALSE), "") -> 1200 | G48: =IFERROR(VLOOKUP($B48, 'Master Roster'!$A:$G, 7, FALSE), "") -> 46180 | J48: Jun | K48: 7200 | L48: 3600 | M48: ❌ OVERDUE / UNPAID
A49: 46 | B49: UPV-10-A | C49: =IFERROR(VLOOKUP($B49, 'Master Roster'!$A:$C, 3, FALSE), "") -> UPV | D49: =IFERROR(VLOOKUP($B49, 'Master Roster'!$A:$E, 5, FALSE), "") -> Emely Mwale | E49: =IFERROR(VLOOKUP($B49, 'Master Roster'!$A:$F, 6, FALSE), "") -> 260777238633 | F49: =IFERROR(VLOOKUP($B49, 'Master Roster'!$A:$H, 8, FALSE), "") -> 900 | G49: =IFERROR(VLOOKUP($B49, 'Master Roster'!$A:$G, 7, FALSE), "") -> 46178 | J49: Sep | K49: 8100 | L49: 0 | M49: ✅ Paid / Secured
A50: 47 | B50: UPV-10-B | C50: =IFERROR(VLOOKUP($B50, 'Master Roster'!$A:$C, 3, FALSE), "") -> UPV | D50: =IFERROR(VLOOKUP($B50, 'Master Roster'!$A:$E, 5, FALSE), "") -> Melody Mumba | E50: =IFERROR(VLOOKUP($B50, 'Master Roster'!$A:$F, 6, FALSE), "") -> 260973551911 | F50: =IFERROR(VLOOKUP($B50, 'Master Roster'!$A:$H, 8, FALSE), "") -> 900 | G50: =IFERROR(VLOOKUP($B50, 'Master Roster'!$A:$G, 7, FALSE), "") -> 46186 | J50: Aug | K50: 7200 | L50: 900 | M50: 🟢 Open Window
A51: 48 | B51: UPV-10-C | C51: =IFERROR(VLOOKUP($B51, 'Master Roster'!$A:$C, 3, FALSE), "") -> UPV | D51: =IFERROR(VLOOKUP($B51, 'Master Roster'!$A:$E, 5, FALSE), "") -> Sara Matakala | E51: =IFERROR(VLOOKUP($B51, 'Master Roster'!$A:$F, 6, FALSE), "") -> 260970522825 | F51: =IFERROR(VLOOKUP($B51, 'Master Roster'!$A:$H, 8, FALSE), "") -> 900 | G51: =IFERROR(VLOOKUP($B51, 'Master Roster'!$A:$G, 7, FALSE), "") -> 46198 | J51: Aug | K51: 7200 | L51: 900 | M51: 🟢 Open Window
A52: 49 | B52: UPV-10-D | C52: =IFERROR(VLOOKUP($B52, 'Master Roster'!$A:$C, 3, FALSE), "") -> UPV | D52: =IFERROR(VLOOKUP($B52, 'Master Roster'!$A:$E, 5, FALSE), "") -> Vacant | E52: =IFERROR(VLOOKUP($B52, 'Master Roster'!$A:$F, 6, FALSE), "") | F52: =IFERROR(VLOOKUP($B52, 'Master Roster'!$A:$H, 8, FALSE), "") -> 900 | G52: =IFERROR(VLOOKUP($B52, 'Master Roster'!$A:$G, 7, FALSE), "") | J52: Jun | K52: 5400 | L52: 0 | M52: Vacant
A53: 50 | B53: UPV-11-A | C53: =IFERROR(VLOOKUP($B53, 'Master Roster'!$A:$C, 3, FALSE), "") -> UPV | D53: =IFERROR(VLOOKUP($B53, 'Master Roster'!$A:$E, 5, FALSE), "") -> Gift Nankamba | E53: =IFERROR(VLOOKUP($B53, 'Master Roster'!$A:$F, 6, FALSE), "") -> 260970956759 | F53: =IFERROR(VLOOKUP($B53, 'Master Roster'!$A:$H, 8, FALSE), "") -> 1000 | G53: =IFERROR(VLOOKUP($B53, 'Master Roster'!$A:$G, 7, FALSE), "") -> 46178 | J53: Sep | K53: 9000 | L53: 0 | M53: ✅ Paid / Secured
A54: 51 | B54: UPV-12-A | C54: =IFERROR(VLOOKUP($B54, 'Master Roster'!$A:$C, 3, FALSE), "") -> UPV | D54: =IFERROR(VLOOKUP($B54, 'Master Roster'!$A:$E, 5, FALSE), "") -> chilulu chiliulu | E54: =IFERROR(VLOOKUP($B54, 'Master Roster'!$A:$F, 6, FALSE), "") -> 260975185330 | F54: =IFERROR(VLOOKUP($B54, 'Master Roster'!$A:$H, 8, FALSE), "") -> 1600 | G54: =IFERROR(VLOOKUP($B54, 'Master Roster'!$A:$G, 7, FALSE), "") -> 46182 | J54: Aug | K54: 12800 | L54: 1600 | M54: 🟢 Open Window
A55: 52 | B55: UPV-13-A | C55: =IFERROR(VLOOKUP($B55, 'Master Roster'!$A:$C, 3, FALSE), "") -> UPV | D55: =IFERROR(VLOOKUP($B55, 'Master Roster'!$A:$E, 5, FALSE), "") -> Chibesa Chisembe | E55: =IFERROR(VLOOKUP($B55, 'Master Roster'!$A:$F, 6, FALSE), "") -> 260970270037 | F55: =IFERROR(VLOOKUP($B55, 'Master Roster'!$A:$H, 8, FALSE), "") -> 1800 | G55: =IFERROR(VLOOKUP($B55, 'Master Roster'!$A:$G, 7, FALSE), "") -> 46175 | J55: Sep | K55: 16200 | L55: 0 | M55: ✅ Paid / Secured
A56: 53 | B56: UPV-14-A | C56: =IFERROR(VLOOKUP($B56, 'Master Roster'!$A:$C, 3, FALSE), "") -> UPV | D56: =IFERROR(VLOOKUP($B56, 'Master Roster'!$A:$E, 5, FALSE), "") -> Reuben Ngusulu | E56: =IFERROR(VLOOKUP($B56, 'Master Roster'!$A:$F, 6, FALSE), "") -> 260763503053 | F56: =IFERROR(VLOOKUP($B56, 'Master Roster'!$A:$H, 8, FALSE), "") -> 950 | G56: =IFERROR(VLOOKUP($B56, 'Master Roster'!$A:$G, 7, FALSE), "") -> 46184 | J56: Aug | K56: 7600 | L56: 950 | M56: 🟢 Open Window
A57: 54 | B57: UPV-15-A | C57: =IFERROR(VLOOKUP($B57, 'Master Roster'!$A:$C, 3, FALSE), "") -> UPV | D57: =IFERROR(VLOOKUP($B57, 'Master Roster'!$A:$E, 5, FALSE), "") -> Harriet nanyangwe | E57: =IFERROR(VLOOKUP($B57, 'Master Roster'!$A:$F, 6, FALSE), "") -> 260974130584 | F57: =IFERROR(VLOOKUP($B57, 'Master Roster'!$A:$H, 8, FALSE), "") -> 1100 | G57: =IFERROR(VLOOKUP($B57, 'Master Roster'!$A:$G, 7, FALSE), "") -> 46176 | H57: -400 | J57: Aug | K57: 8800 | L57: 700 | M57: ⏳ Grace Period
C58: =IFERROR(VLOOKUP($B58, 'Master Roster'!$A:$C, 3, FALSE), "") | D58: =IFERROR(VLOOKUP($B58, 'Master Roster'!$A:$E, 5, FALSE), "") | E58: =IFERROR(VLOOKUP($B58, 'Master Roster'!$A:$F, 6, FALSE), "") | F58: =IFERROR(VLOOKUP($B58, 'Master Roster'!$A:$H, 8, FALSE), "") | G58: =IFERROR(VLOOKUP($B58, 'Master Roster'!$A:$G, 7, FALSE), "")
C59: =IFERROR(VLOOKUP($B59, 'Master Roster'!$A:$C, 3, FALSE), "") | D59: =IFERROR(VLOOKUP($B59, 'Master Roster'!$A:$E, 5, FALSE), "") | E59: =IFERROR(VLOOKUP($B59, 'Master Roster'!$A:$F, 6, FALSE), "") | F59: =IFERROR(VLOOKUP($B59, 'Master Roster'!$A:$H, 8, FALSE), "") | G59: =IFERROR(VLOOKUP($B59, 'Master Roster'!$A:$G, 7, FALSE), "")
C60: =IFERROR(VLOOKUP($B60, 'Master Roster'!$A:$C, 3, FALSE), "") | D60: =IFERROR(VLOOKUP($B60, 'Master Roster'!$A:$E, 5, FALSE), "") | E60: =IFERROR(VLOOKUP($B60, 'Master Roster'!$A:$F, 6, FALSE), "") | F60: =IFERROR(VLOOKUP($B60, 'Master Roster'!$A:$H, 8, FALSE), "") | G60: =IFERROR(VLOOKUP($B60, 'Master Roster'!$A:$G, 7, FALSE), "")
C61: =IFERROR(VLOOKUP($B61, 'Master Roster'!$A:$C, 3, FALSE), "") | D61: =IFERROR(VLOOKUP($B61, 'Master Roster'!$A:$E, 5, FALSE), "") | E61: =IFERROR(VLOOKUP($B61, 'Master Roster'!$A:$F, 6, FALSE), "") | F61: =IFERROR(VLOOKUP($B61, 'Master Roster'!$A:$H, 8, FALSE), "") | G61: =IFERROR(VLOOKUP($B61, 'Master Roster'!$A:$G, 7, FALSE), "")
C62: =IFERROR(VLOOKUP($B62, 'Master Roster'!$A:$C, 3, FALSE), "") | D62: =IFERROR(VLOOKUP($B62, 'Master Roster'!$A:$E, 5, FALSE), "") | E62: =IFERROR(VLOOKUP($B62, 'Master Roster'!$A:$F, 6, FALSE), "") | F62: =IFERROR(VLOOKUP($B62, 'Master Roster'!$A:$H, 8, FALSE), "") | G62: =IFERROR(VLOOKUP($B62, 'Master Roster'!$A:$G, 7, FALSE), "")
C63: =IFERROR(VLOOKUP($B63, 'Master Roster'!$A:$C, 3, FALSE), "") | D63: =IFERROR(VLOOKUP($B63, 'Master Roster'!$A:$E, 5, FALSE), "") | E63: =IFERROR(VLOOKUP($B63, 'Master Roster'!$A:$F, 6, FALSE), "") | F63: =IFERROR(VLOOKUP($B63, 'Master Roster'!$A:$H, 8, FALSE), "") | G63: =IFERROR(VLOOKUP($B63, 'Master Roster'!$A:$G, 7, FALSE), "")
C64: =IFERROR(VLOOKUP($B64, 'Master Roster'!$A:$C, 3, FALSE), "") | D64: =IFERROR(VLOOKUP($B64, 'Master Roster'!$A:$E, 5, FALSE), "") | E64: =IFERROR(VLOOKUP($B64, 'Master Roster'!$A:$F, 6, FALSE), "") | F64: =IFERROR(VLOOKUP($B64, 'Master Roster'!$A:$H, 8, FALSE), "") | G64: =IFERROR(VLOOKUP($B64, 'Master Roster'!$A:$G, 7, FALSE), "")
C65: =IFERROR(VLOOKUP($B65, 'Master Roster'!$A:$C, 3, FALSE), "") | D65: =IFERROR(VLOOKUP($B65, 'Master Roster'!$A:$E, 5, FALSE), "") | E65: =IFERROR(VLOOKUP($B65, 'Master Roster'!$A:$F, 6, FALSE), "") | F65: =IFERROR(VLOOKUP($B65, 'Master Roster'!$A:$H, 8, FALSE), "") | G65: =IFERROR(VLOOKUP($B65, 'Master Roster'!$A:$G, 7, FALSE), "")
C66: =IFERROR(VLOOKUP($B66, 'Master Roster'!$A:$C, 3, FALSE), "") | D66: =IFERROR(VLOOKUP($B66, 'Master Roster'!$A:$E, 5, FALSE), "") | E66: =IFERROR(VLOOKUP($B66, 'Master Roster'!$A:$F, 6, FALSE), "") | F66: =IFERROR(VLOOKUP($B66, 'Master Roster'!$A:$H, 8, FALSE), "") | G66: =IFERROR(VLOOKUP($B66, 'Master Roster'!$A:$G, 7, FALSE), "")
C67: =IFERROR(VLOOKUP($B67, 'Master Roster'!$A:$C, 3, FALSE), "") | D67: =IFERROR(VLOOKUP($B67, 'Master Roster'!$A:$E, 5, FALSE), "") | E67: =IFERROR(VLOOKUP($B67, 'Master Roster'!$A:$F, 6, FALSE), "") | F67: =IFERROR(VLOOKUP($B67, 'Master Roster'!$A:$H, 8, FALSE), "") | G67: =IFERROR(VLOOKUP($B67, 'Master Roster'!$A:$G, 7, FALSE), "")
C68: =IFERROR(VLOOKUP($B68, 'Master Roster'!$A:$C, 3, FALSE), "") | D68: =IFERROR(VLOOKUP($B68, 'Master Roster'!$A:$E, 5, FALSE), "") | E68: =IFERROR(VLOOKUP($B68, 'Master Roster'!$A:$F, 6, FALSE), "") | F68: =IFERROR(VLOOKUP($B68, 'Master Roster'!$A:$H, 8, FALSE), "") | G68: =IFERROR(VLOOKUP($B68, 'Master Roster'!$A:$G, 7, FALSE), "")
C69: =IFERROR(VLOOKUP($B69, 'Master Roster'!$A:$C, 3, FALSE), "") | D69: =IFERROR(VLOOKUP($B69, 'Master Roster'!$A:$E, 5, FALSE), "") | E69: =IFERROR(VLOOKUP($B69, 'Master Roster'!$A:$F, 6, FALSE), "") | F69: =IFERROR(VLOOKUP($B69, 'Master Roster'!$A:$H, 8, FALSE), "") | G69: =IFERROR(VLOOKUP($B69, 'Master Roster'!$A:$G, 7, FALSE), "")
... C97: =IFERROR(VLOOKUP($B97, 'Master Roster'!$A:$C, 3, FALSE), "") | D97: =IFERROR(VLOOKUP($B97, 'Master Roster'!$A:$E, 5, FALSE), "") | E97: =IFERROR(VLOOKUP($B97, 'Master Roster'!$A:$F, 6, FALSE), "") | F97: =IFERROR(VLOOKUP($B97, 'Master Roster'!$A:$H, 8, FALSE), "") | G97: =IFERROR(VLOOKUP($B97, 'Master Roster'!$A:$G, 7, FALSE), "")

Sheet Receipt Template
B2: OFFICIAL RECEIPT | C2: Receipt No: | D2: {=IF(OR(ISBLANK(C5), C5=""), "", _xlfn.XLOOKUP(C5, 'Payments Log Archive'!A:A, 'Payments Log Archive'!N:N, "", 0, -1))} -> REC-0014
B5: Tenant ID: | C5: {=IF(OR(ISBLANK(C7), C7="Select"), "", _xlfn.XLOOKUP(C7, 'Monthly Billing Tab'!D4:D1001, 'Monthly Billing Tab'!B4:B1001, ""))} -> ANX-19-B
B6: Date: | C6: =TODAY() -> 46272
B7: Select Tenant Name: | C7: Chanda Lutashima
B8: Amount Paid: | C8: {=IF(OR(ISBLANK(C7), C7="Select"), "", LET(adj, _xlfn.XLOOKUP(C7, 'Monthly Billing Tab'!D4:D1001, 'Monthly Billing Tab'!H4:H1001, ""), IF(ISNUMBER(adj), ABS(adj), _xlfn.XLOOKUP(C7, 'Monthly Billing Tab'!D4:D1001, 'Monthly Billing Tab'!F4:F1001, ""))))} -> 1200
B9: Period Covered: | C9: {=IF(OR(ISBLANK(C7), C7="Select"), "", LET(entry_date, _xlfn.XLOOKUP(C7, 'Monthly Billing Tab'!D4:D1001, 'Monthly Billing Tab'!G4:G1001, 1), entry_day, DAY(entry_date), target_month, _xlfn.XLOOKUP(C7, 'Monthly Billing Tab'!D4:D1001, 'Monthly Billing Tab'!J4:J1001, ""), yr, IF(C10="", 2026, C10), IF(target_month="", "", LET(start_date, DATE(yr, MONTH(1&target_month), entry_day), TEXT(start_date, "d mmm yyyy") & " to " & TEXT(EDATE(start_date, 1) - 1, "d mmm yyyy")))))} -> 7 Sep 2026 to 6 Oct 2026
B11: Total Balance: | C11: {=IF(OR(ISBLANK(C7), C7="Select"), "", _xlfn.XLOOKUP(C7, 'Monthly Billing Tab'!D4:D1001, 'Monthly Billing Tab'!L4:L1001, ""))} -> 0
B12: Entry Date: | C12: =IF(OR(ISBLANK(C5), C5=""), "", VLOOKUP(C5, 'Master Roster'!A:G, 7, FALSE)) -> 46180
B13: WhatsApp: | C13: =IFERROR(__xludf.DUMMYFUNCTION("IF(OR(ISBLANK(C7), C7=""Select""), """", HYPERLINK(""https://wa.me/"" & IFERROR(INDEX(FILTER('Master Roster'!F:F, 'Master Roster'!E:E=C7, 'Master Roster'!F:F<>""""), 1), """") & ""?text="" & ENCODEURL(""Hello "" & IFERROR(IF(VLOOKUP(C5, 'Master Roster'!A:"&"J, 10, FALSE)=""Male"", ""Mr. "", ""Ms. ""), """") & C7 & "", this is your receipt for the payment of "" & C8 & "" covering "" & C9 & "". Thank you!""), ""Send WhatsApp Receipt""))"),"Send WhatsApp Receipt") -> Send WhatsApp Receipt
B15: Thank you for your payment!
C16: {=IF(OR(C4="", C4="--- Select ---"), "", HYPERLINK("https://wa.me/" & _xlfn.XLOOKUP(LEFT(C4, FIND(" - ", C4&" - ") - 1), 'Master Roster'!A:A, 'Master Roster'!F:F, "") & "?text=" & ENCODEURL("Hello " & IFERROR(IF(_xlfn.XLOOKUP(LEFT(C4, FIND(" - ", C4&" - ") - 1), 'Master Roster'!A:A, 'Master Roster'!J:J, "")="Male", "Mr. ", "Ms. "), "") & C7 & ", payment of K" & C8 & " received for " & C9 & ". Receipt No: " & D2), "💬 Send WhatsApp Receipt"))}

Sheet Payments Log Archive
A1: Payments Log Archive
A3: Unique ID | B3: Tenant Name | C3: Payment Date | D3: Month Covered | E3: Year | F3: Amount Paid | G3: Status | H3: Send Receipt | I3: Print Receipt | J3: Balance | K3: Cumulative Payments | L3: Receipt Issued | M3: Pending Receipts | N3: Receipt Number | O3: WhatsApp Receipt
A4: BBH-1-A | B4: {=IF(A4:A1002="", "", VLOOKUP(A4:A1002, 'Master Roster'!A:E, 5, FALSE))} -> Adrian mulale | C4: 2026-01-31 | D4: January | E4: 2026 | F4: 950 | G4: Paid | H4: 💬 Send Receipt | I4: Print Receipt | J4: =IF(A4="", "", IFERROR(VLOOKUP(A4, 'Master Roster'!A:H, 8, FALSE) - F4, "")) -> 0 | K4: {=IF(A4:A1002="", "", _xlfn.XLOOKUP(A4:A1002, 'Monthly Billing Tab'!B:B, 'Monthly Billing Tab'!K:K, ""))} -> 7600 | L4: FALSE | M4: =IFERROR(__xludf.DUMMYFUNCTION("LET(paid_ids, FILTER('Monthly Billing Tab'!B3:B1002, 'Monthly Billing Tab'!L3:L1002=0, 'Monthly Billing Tab'!B3:B1002<>"""", 'Monthly Billing Tab'!D3:D1002<>""Vacant""), paid_names, FILTER('Monthly Billing Tab'!D3:D1002, 'Monthly Billing Tab'!L3:L1002=0, "&"'Monthly Billing Tab'!B3:B1002<>"""", 'Monthly Billing Tab'!D3:D1002<>""Vacant""), paid_full, ARRAYFORMULA(paid_ids & "" - "" & paid_names), issued_full, FILTER(A4:A1002 & "" - "" & B4:B1002, L4:L1002=TRUE), VSTACK(""--- Select ---"", IFERROR(FILTER(paid_"&"full, ISNA(MATCH(paid_full, issued_full, 0))), ""No Pending Receipts"")))"),"--- Select ---") -> --- Select --- | N4: {=IF(A4:A1002="", "", "REC-" & TEXT(ROW(A4:A1002)-1, "0000"))} -> REC-0003 | O4: =IF(ISBLANK(A4), "", LET(entry_day, VLOOKUP(A4, 'Master Roster'!$A:$G, 7, FALSE), start_date, DATE(E4, MONTH(D4&" 1"), entry_day), end_date, EDATE(start_date, 1), period, TEXT(start_date, "mmm d, yyyy") & " - " & TEXT(end_date, "mmm d, yyyy"), HYPERLINK("https://wa.me/" & VLOOKUP(A4, 'Master Roster'!$A:$F, 6, FALSE) & "?text=" & ENCODEURL("Hello " & IFERROR(IF(VLOOKUP(A4, 'Master Roster'!$A:$J, 10, FALSE)="Male", "Mr. ", "Ms. "), "") & B4 & ", payment of K" & F4 & " received for " & period & ". Receipt No: " & N4), "Send Receipt"))) -> Send Receipt
A5: BBH-7-A | B5: Funny Muyamina | C5: 2026-01-05 | D5: January | E5: 2026 | F5: 900 | G5: Paid | H5: 💬 Send Receipt | I5: Print Receipt | J5: =IF(A5="", "", IFERROR(VLOOKUP(A5, 'Master Roster'!A:H, 8, FALSE) - F5, "")) -> 0 | K5: 7200 | L5: TRUE | M5: =IFERROR(__xludf.DUMMYFUNCTION("""COMPUTED_VALUE"""),"ANX-19-B - Chanda Lutashima") -> ANX-19-B - Chanda Lutashima | N5: REC-0004 | O5: =IF(ISBLANK(A5), "", LET(entry_day, VLOOKUP(A5, 'Master Roster'!$A:$G, 7, FALSE), start_date, DATE(E5, MONTH(D5&" 1"), entry_day), end_date, EDATE(start_date, 1), period, TEXT(start_date, "mmm d, yyyy") & " - " & TEXT(end_date, "mmm d, yyyy"), HYPERLINK("https://wa.me/" & VLOOKUP(A5, 'Master Roster'!$A:$F, 6, FALSE) & "?text=" & ENCODEURL("Hello " & IFERROR(IF(VLOOKUP(A5, 'Master Roster'!$A:$J, 10, FALSE)="Male", "Mr. ", "Ms. "), "") & B5 & ", payment of K" & F5 & " received for " & period & ". Receipt No: " & N5), "Send Receipt"))) -> Send Receipt
A6: BBH-1-A | B6: Adrian mulale | C6: 46178 | D6: June | E6: 2026 | F6: 950 | G6: Paid | H6: 💬 Send Receipt | I6: Print Receipt | J6: =IF(A6="", "", IFERROR(VLOOKUP(A6, 'Master Roster'!A:H, 8, FALSE) - F6, "")) -> 0 | K6: 7600 | L6: TRUE | M6: =IFERROR(__xludf.DUMMYFUNCTION("""COMPUTED_VALUE"""),"ANX-19-D - Lubono Ruthendo") -> ANX-19-D - Lubono Ruthendo | N6: REC-0005 | O6: =IF(ISBLANK(A6), "", LET(entry_day, VLOOKUP(A6, 'Master Roster'!$A:$G, 7, FALSE), start_date, DATE(E6, MONTH(D6&" 1"), entry_day), end_date, EDATE(start_date, 1), period, TEXT(start_date, "mmm d, yyyy") & " - " & TEXT(end_date, "mmm d, yyyy"), HYPERLINK("https://wa.me/" & VLOOKUP(A6, 'Master Roster'!$A:$F, 6, FALSE) & "?text=" & ENCODEURL("Hello " & IFERROR(IF(VLOOKUP(A6, 'Master Roster'!$A:$J, 10, FALSE)="Male", "Mr. ", "Ms. "), "") & B6 & ", payment of K" & F6 & " received for " & period & ". Receipt No: " & N6), "Send Receipt"))) -> Send Receipt
A7: BBH-6-C | B7: Zick Phiri | C7: 46178 | D7: June | E7: 2026 | F7: 900 | G7: Paid | H7: 💬 Send Receipt | I7: Print Receipt | J7: =IF(A7="", "", IFERROR(VLOOKUP(A7, 'Master Roster'!A:H, 8, FALSE) - F7, "")) -> 0 | K7: 7200 | L7: FALSE | M7: =IFERROR(__xludf.DUMMYFUNCTION("""COMPUTED_VALUE"""),"ANX-20-A - Steven Musonda") -> ANX-20-A - Steven Musonda | N7: REC-0006 | O7: =IF(ISBLANK(A7), "", LET(entry_day, VLOOKUP(A7, 'Master Roster'!$A:$G, 7, FALSE), start_date, DATE(E7, MONTH(D7&" 1"), entry_day), end_date, EDATE(start_date, 1), period, TEXT(start_date, "mmm d, yyyy") & " - " & TEXT(end_date, "mmm d, yyyy"), HYPERLINK("https://wa.me/" & VLOOKUP(A7, 'Master Roster'!$A:$F, 6, FALSE) & "?text=" & ENCODEURL("Hello " & IFERROR(IF(VLOOKUP(A7, 'Master Roster'!$A:$J, 10, FALSE)="Male", "Mr. ", "Ms. "), "") & B7 & ", payment of K" & F7 & " received for " & period & ". Receipt No: " & N7), "Send Receipt"))) -> Send Receipt
A8: BBH-8-A | B8: Kangwa Kunda | C8: 46178 | D8: June | E8: 2026 | F8: 900 | G8: Paid | H8: 💬 Send Receipt | I8: Print Receipt | J8: =IF(A8="", "", IFERROR(VLOOKUP(A8, 'Master Roster'!A:H, 8, FALSE) - F8, "")) -> 0 | K8: 7200 | L8: TRUE | M8: =IFERROR(__xludf.DUMMYFUNCTION("""COMPUTED_VALUE"""),"BBH-5-A - Wampa ") -> BBH-5-A - Wampa | N8: REC-0007 | O8: =IF(ISBLANK(A8), "", LET(entry_day, VLOOKUP(A8, 'Master Roster'!$A:$G, 7, FALSE), start_date, DATE(E8, MONTH(D8&" 1"), entry_day), end_date, EDATE(start_date, 1), period, TEXT(start_date, "mmm d, yyyy") & " - " & TEXT(end_date, "mmm d, yyyy"), HYPERLINK("https://wa.me/" & VLOOKUP(A8, 'Master Roster'!$A:$F, 6, FALSE) & "?text=" & ENCODEURL("Hello " & IFERROR(IF(VLOOKUP(A8, 'Master Roster'!$A:$J, 10, FALSE)="Male", "Mr. ", "Ms. "), "") & B8 & ", payment of K" & F8 & " received for " & period & ". Receipt No: " & N8), "Send Receipt"))) -> Send Receipt
A9: UPV-10-A | B9: Emely Mwale | C9: 46178 | D9: June | E9: 2026 | F9: 850 | G9: Paid | H9: 💬 Send Receipt | I9: Print Receipt | J9: =IF(A9="", "", IFERROR(VLOOKUP(A9, 'Master Roster'!A:H, 8, FALSE) - F9, "")) -> 50 | K9: 8100 | L9: FALSE | M9: =IFERROR(__xludf.DUMMYFUNCTION("""COMPUTED_VALUE"""),"CRV-17-A - Kwitu Khalu") -> CRV-17-A - Kwitu Khalu | N9: REC-0008 | O9: =IF(ISBLANK(A9), "", LET(entry_day, VLOOKUP(A9, 'Master Roster'!$A:$G, 7, FALSE), start_date, DATE(E9, MONTH(D9&" 1"), entry_day), end_date, EDATE(start_date, 1), period, TEXT(start_date, "mmm d, yyyy") & " - " & TEXT(end_date, "mmm d, yyyy"), HYPERLINK("https://wa.me/" & VLOOKUP(A9, 'Master Roster'!$A:$F, 6, FALSE) & "?text=" & ENCODEURL("Hello " & IFERROR(IF(VLOOKUP(A9, 'Master Roster'!$A:$J, 10, FALSE)="Male", "Mr. ", "Ms. "), "") & B9 & ", payment of K" & F9 & " received for " & period & ". Receipt No: " & N9), "Send Receipt"))) -> Send Receipt
A10: UPV-11-A | B10: Gift Nankamba | C10: 46178 | D10: June | E10: 2026 | F10: 1000 | G10: Paid | H10: 💬 Send Receipt | I10: Print Receipt | J10: =IF(A10="", "", IFERROR(VLOOKUP(A10, 'Master Roster'!A:H, 8, FALSE) - F10, "")) -> 0 | K10: 9000 | L10: FALSE | M10: =IFERROR(__xludf.DUMMYFUNCTION("""COMPUTED_VALUE"""),"NWG-21-D - Jairos Banda") -> NWG-21-D - Jairos Banda | N10: REC-0009 | O10: =IF(ISBLANK(A10), "", LET(entry_day, VLOOKUP(A10, 'Master Roster'!$A:$G, 7, FALSE), start_date, DATE(E10, MONTH(D10&" 1"), entry_day), end_date, EDATE(start_date, 1), period, TEXT(start_date, "mmm d, yyyy") & " - " & TEXT(end_date, "mmm d, yyyy"), HYPERLINK("https://wa.me/" & VLOOKUP(A10, 'Master Roster'!$A:$F, 6, FALSE) & "?text=" & ENCODEURL("Hello " & IFERROR(IF(VLOOKUP(A10, 'Master Roster'!$A:$J, 10, FALSE)="Male", "Mr. ", "Ms. "), "") & B10 & ", payment of K" & F10 & " received for " & period & ". Receipt No: " & N10), "Send Receipt"))) -> Send Receipt
A11: UPV-12-A | B11: chilulu chiliulu | C11: 46178 | D11: June | E11: 2026 | F11: 1600 | G11: Paid | H11: 💬 Send Receipt | I11: Print Receipt | J11: =IF(A11="", "", IFERROR(VLOOKUP(A11, 'Master Roster'!A:H, 8, FALSE) - F11, "")) -> 0 | K11: 12800 | L11: FALSE | M11: =IFERROR(__xludf.DUMMYFUNCTION("""COMPUTED_VALUE"""),"NWG-22-C - Ongani Madaliso Gabriel ") -> NWG-22-C - Ongani Madaliso Gabriel | N11: REC-0010 | O11: =IF(ISBLANK(A11), "", LET(entry_day, VLOOKUP(A11, 'Master Roster'!$A:$G, 7, FALSE), start_date, DATE(E11, MONTH(D11&" 1"), entry_day), end_date, EDATE(start_date, 1), period, TEXT(start_date, "mmm d, yyyy") & " - " & TEXT(end_date, "mmm d, yyyy"), HYPERLINK("https://wa.me/" & VLOOKUP(A11, 'Master Roster'!$A:$F, 6, FALSE) & "?text=" & ENCODEURL("Hello " & IFERROR(IF(VLOOKUP(A11, 'Master Roster'!$A:$J, 10, FALSE)="Male", "Mr. ", "Ms. "), "") & B11 & ", payment of K" & F11 & " received for " & period & ". Receipt No: " & N11), "Send Receipt"))) -> Send Receipt
A12: UPV-13-A | B12: Chibesa Chisembe | C12: 46178 | D12: June | E12: 2026 | F12: 1800 | G12: Paid | H12: 💬 Send Receipt | I12: Print Receipt | J12: =IF(A12="", "", IFERROR(VLOOKUP(A12, 'Master Roster'!A:H, 8, FALSE) - F12, "")) -> 0 | K12: 16200 | L12: FALSE | M12: =IFERROR(__xludf.DUMMYFUNCTION("""COMPUTED_VALUE"""),"NWG-22-D - Christopher Phiri") -> NWG-22-D - Christopher Phiri | N12: REC-0011 | O12: =IF(ISBLANK(A12), "", LET(entry_day, VLOOKUP(A12, 'Master Roster'!$A:$G, 7, FALSE), start_date, DATE(E12, MONTH(D12&" 1"), entry_day), end_date, EDATE(start_date, 1), period, TEXT(start_date, "mmm d, yyyy") & " - " & TEXT(end_date, "mmm d, yyyy"), HYPERLINK("https://wa.me/" & VLOOKUP(A12, 'Master Roster'!$A:$F, 6, FALSE) & "?text=" & ENCODEURL("Hello " & IFERROR(IF(VLOOKUP(A12, 'Master Roster'!$A:$J, 10, FALSE)="Male", "Mr. ", "Ms. "), "") & B12 & ", payment of K" & F12 & " received for " & period & ". Receipt No: " & N12), "Send Receipt"))) -> Send Receipt
A13: UPV-14-A | B13: Reuben Ngusulu | C13: 46178 | D13: June | E13: 2026 | F13: 950 | G13: Paid | H13: 💬 Send Receipt | I13: Print Receipt | J13: =IF(A13="", "", IFERROR(VLOOKUP(A13, 'Master Roster'!A:H, 8, FALSE) - F13, "")) -> 0 | K13: 7600 | L13: FALSE | M13: =IFERROR(__xludf.DUMMYFUNCTION("""COMPUTED_VALUE"""),"NWG-24-A - Chami Soneka") -> NWG-24-A - Chami Soneka | N13: REC-0012 | O13: =IF(ISBLANK(A13), "", LET(entry_day, VLOOKUP(A13, 'Master Roster'!$A:$G, 7, FALSE), start_date, DATE(E13, MONTH(D13&" 1"), entry_day), end_date, EDATE(start_date, 1), period, TEXT(start_date, "mmm d, yyyy") & " - " & TEXT(end_date, "mmm d, yyyy"), HYPERLINK("https://wa.me/" & VLOOKUP(A13, 'Master Roster'!$A:$F, 6, FALSE) & "?text=" & ENCODEURL("Hello " & IFERROR(IF(VLOOKUP(A13, 'Master Roster'!$A:$J, 10, FALSE)="Male", "Mr. ", "Ms. "), "") & B13 & ", payment of K" & F13 & " received for " & period & ". Receipt No: " & N13), "Send Receipt"))) -> Send Receipt
A14: CRV-17-A | B14: Kwitu Khalu | C14: 46178 | D14: June | E14: 2026 | F14: 900 | G14: Paid | H14: 💬 Send Receipt | I14: Print Receipt | J14: =IF(A14="", "", IFERROR(VLOOKUP(A14, 'Master Roster'!A:H, 8, FALSE) - F14, "")) -> 0 | K14: 8100 | L14: FALSE | M14: =IFERROR(__xludf.DUMMYFUNCTION("""COMPUTED_VALUE"""),"UPV-10-A - Emely Mwale") -> UPV-10-A - Emely Mwale | N14: REC-0013 | O14: =IF(ISBLANK(A14), "", LET(entry_day, VLOOKUP(A14, 'Master Roster'!$A:$G, 7, FALSE), start_date, DATE(E14, MONTH(D14&" 1"), entry_day), end_date, EDATE(start_date, 1), period, TEXT(start_date, "mmm d, yyyy") & " - " & TEXT(end_date, "mmm d, yyyy"), HYPERLINK("https://wa.me/" & VLOOKUP(A14, 'Master Roster'!$A:$F, 6, FALSE) & "?text=" & ENCODEURL("Hello " & IFERROR(IF(VLOOKUP(A14, 'Master Roster'!$A:$J, 10, FALSE)="Male", "Mr. ", "Ms. "), "") & B14 & ", payment of K" & F14 & " received for " & period & ". Receipt No: " & N14), "Send Receipt"))) -> Send Receipt
A15: ANX-19-B | B15: Chanda Lutashima | C15: 46178 | D15: June | E15: 2026 | F15: 1200 | G15: Paid | H15: 💬 Send Receipt | I15: Print Receipt | J15: =IF(A15="", "", IFERROR(VLOOKUP(A15, 'Master Roster'!A:H, 8, FALSE) - F15, "")) -> 0 | K15: 10800 | L15: FALSE | M15: =IFERROR(__xludf.DUMMYFUNCTION("""COMPUTED_VALUE"""),"UPV-11-A - Gift Nankamba") -> UPV-11-A - Gift Nankamba | N15: REC-0014 | O15: =IF(ISBLANK(A15), "", LET(entry_day, VLOOKUP(A15, 'Master Roster'!$A:$G, 7, FALSE), start_date, DATE(E15, MONTH(D15&" 1"), entry_day), end_date, EDATE(start_date, 1), period, TEXT(start_date, "mmm d, yyyy") & " - " & TEXT(end_date, "mmm d, yyyy"), HYPERLINK("https://wa.me/" & VLOOKUP(A15, 'Master Roster'!$A:$F, 6, FALSE) & "?text=" & ENCODEURL("Hello " & IFERROR(IF(VLOOKUP(A15, 'Master Roster'!$A:$J, 10, FALSE)="Male", "Mr. ", "Ms. "), "") & B15 & ", payment of K" & F15 & " received for " & period & ". Receipt No: " & N15), "Send Receipt"))) -> Send Receipt
A16: NWG-21-A | B16: Lukundo Siame | C16: 46178 | D16: June | E16: 2026 | F16: 1200 | G16: Paid | H16: 💬 Send Receipt | I16: Print Receipt | J16: =IF(A16="", "", IFERROR(VLOOKUP(A16, 'Master Roster'!A:H, 8, FALSE) - F16, "")) -> 0 | K16: 8400 | L16: FALSE | M16: =IFERROR(__xludf.DUMMYFUNCTION("""COMPUTED_VALUE"""),"UPV-13-A - Chibesa Chisembe") -> UPV-13-A - Chibesa Chisembe | N16: REC-0015 | O16: =IF(ISBLANK(A16), "", LET(entry_day, VLOOKUP(A16, 'Master Roster'!$A:$G, 7, FALSE), start_date, DATE(E16, MONTH(D16&" 1"), entry_day), end_date, EDATE(start_date, 1), period, TEXT(start_date, "mmm d, yyyy") & " - " & TEXT(end_date, "mmm d, yyyy"), HYPERLINK("https://wa.me/" & VLOOKUP(A16, 'Master Roster'!$A:$F, 6, FALSE) & "?text=" & ENCODEURL("Hello " & IFERROR(IF(VLOOKUP(A16, 'Master Roster'!$A:$J, 10, FALSE)="Male", "Mr. ", "Ms. "), "") & B16 & ", payment of K" & F16 & " received for " & period & ". Receipt No: " & N16), "Send Receipt"))) -> Send Receipt
A17: NWG-21-B | B17: Gabirel Kabwe | C17: 46178 | D17: June | E17: 2026 | F17: 1200 | G17: Paid | H17: 💬 Send Receipt | I17: Print Receipt | J17: =IF(A17="", "", IFERROR(VLOOKUP(A17, 'Master Roster'!A:H, 8, FALSE) - F17, "")) -> 0 | K17: 9600 | L17: FALSE | N17: REC-0016 | O17: =IF(ISBLANK(A17), "", LET(entry_day, VLOOKUP(A17, 'Master Roster'!$A:$G, 7, FALSE), start_date, DATE(E17, MONTH(D17&" 1"), entry_day), end_date, EDATE(start_date, 1), period, TEXT(start_date, "mmm d, yyyy") & " - " & TEXT(end_date, "mmm d, yyyy"), HYPERLINK("https://wa.me/" & VLOOKUP(A17, 'Master Roster'!$A:$F, 6, FALSE) & "?text=" & ENCODEURL("Hello " & IFERROR(IF(VLOOKUP(A17, 'Master Roster'!$A:$J, 10, FALSE)="Male", "Mr. ", "Ms. "), "") & B17 & ", payment of K" & F17 & " received for " & period & ". Receipt No: " & N17), "Send Receipt"))) -> Send Receipt
A18: NWG-21-C | B18: Chama Kampamba | C18: 46178 | D18: June | E18: 2026 | F18: 1200 | G18: Paid | H18: 💬 Send Receipt | I18: Print Receipt | J18: =IF(A18="", "", IFERROR(VLOOKUP(A18, 'Master Roster'!A:H, 8, FALSE) - F18, "")) -> 0 | K18: 8400 | L18: FALSE | N18: REC-0017 | O18: =IF(ISBLANK(A18), "", LET(entry_day, VLOOKUP(A18, 'Master Roster'!$A:$G, 7, FALSE), start_date, DATE(E18, MONTH(D18&" 1"), entry_day), end_date, EDATE(start_date, 1), period, TEXT(start_date, "mmm d, yyyy") & " - " & TEXT(end_date, "mmm d, yyyy"), HYPERLINK("https://wa.me/" & VLOOKUP(A18, 'Master Roster'!$A:$F, 6, FALSE) & "?text=" & ENCODEURL("Hello " & IFERROR(IF(VLOOKUP(A18, 'Master Roster'!$A:$J, 10, FALSE)="Male", "Mr. ", "Ms. "), "") & B18 & ", payment of K" & F18 & " received for " & period & ". Receipt No: " & N18), "Send Receipt"))) -> Send Receipt
A19: NWG-23-B | B19: Catherine Mphande | C19: 46178 | D19: June | E19: 2026 | F19: 1200 | G19: Paid | H19: 💬 Send Receipt | I19: Print Receipt | J19: =IF(A19="", "", IFERROR(VLOOKUP(A19, 'Master Roster'!A:H, 8, FALSE) - F19, "")) -> 0 | K19: 9600 | L19: FALSE | N19: REC-0018 | O19: =IF(ISBLANK(A19), "", LET(entry_day, VLOOKUP(A19, 'Master Roster'!$A:$G, 7, FALSE), start_date, DATE(E19, MONTH(D19&" 1"), entry_day), end_date, EDATE(start_date, 1), period, TEXT(start_date, "mmm d, yyyy") & " - " & TEXT(end_date, "mmm d, yyyy"), HYPERLINK("https://wa.me/" & VLOOKUP(A19, 'Master Roster'!$A:$F, 6, FALSE) & "?text=" & ENCODEURL("Hello " & IFERROR(IF(VLOOKUP(A19, 'Master Roster'!$A:$J, 10, FALSE)="Male", "Mr. ", "Ms. "), "") & B19 & ", payment of K" & F19 & " received for " & period & ". Receipt No: " & N19), "Send Receipt"))) -> Send Receipt
A20: NWG-23-D | B20: Lushomo gambwe | C20: 46178 | D20: June | E20: 2026 | F20: 1200 | G20: Paid | H20: 💬 Send Receipt | I20: Print Receipt | J20: =IF(A20="", "", IFERROR(VLOOKUP(A20, 'Master Roster'!A:H, 8, FALSE) - F20, "")) -> 0 | K20: 9600 | L20: FALSE | N20: REC-0019 | O20: =IF(ISBLANK(A20), "", LET(entry_day, VLOOKUP(A20, 'Master Roster'!$A:$G, 7, FALSE), start_date, DATE(E20, MONTH(D20&" 1"), entry_day), end_date, EDATE(start_date, 1), period, TEXT(start_date, "mmm d, yyyy") & " - " & TEXT(end_date, "mmm d, yyyy"), HYPERLINK("https://wa.me/" & VLOOKUP(A20, 'Master Roster'!$A:$F, 6, FALSE) & "?text=" & ENCODEURL("Hello " & IFERROR(IF(VLOOKUP(A20, 'Master Roster'!$A:$J, 10, FALSE)="Male", "Mr. ", "Ms. "), "") & B20 & ", payment of K" & F20 & " received for " & period & ". Receipt No: " & N20), "Send Receipt"))) -> Send Receipt
O21: =IF(ISBLANK(A21), "", LET(entry_day, VLOOKUP(A21, 'Master Roster'!$A:$G, 7, FALSE), start_date, DATE(E21, MONTH(D21&" 1"), entry_day), end_date, EDATE(start_date, 1), period, TEXT(start_date, "mmm d, yyyy") & " - " & TEXT(end_date, "mmm d, yyyy"), HYPERLINK("https://wa.me/" & VLOOKUP(A21, 'Master Roster'!$A:$F, 6, FALSE) & "?text=" & ENCODEURL("Hello " & IFERROR(IF(VLOOKUP(A21, 'Master Roster'!$A:$J, 10, FALSE)="Male", "Mr. ", "Ms. "), "") & B21 & ", payment of K" & F21 & " received for " & period & ". Receipt No: " & N21), "Send Receipt")))
H22: =IF(A22="", "", HYPERLINK("#gid=123456789", "💬 Send Receipt")) | I22: =IF(ISBLANK(A22), "", HYPERLINK("#gid=123456789", "Print Receipt")) | J22: =IF(A22="", "", IFERROR(VLOOKUP(A22, 'Master Roster'!A:H, 8, FALSE) - F22, "")) | L22: FALSE | O22: =IF(ISBLANK(A22), "", LET(entry_day, VLOOKUP(A22, 'Master Roster'!$A:$G, 7, FALSE), start_date, DATE(E22, MONTH(D22&" 1"), entry_day), end_date, EDATE(start_date, 1), period, TEXT(start_date, "mmm d, yyyy") & " - " & TEXT(end_date, "mmm d, yyyy"), HYPERLINK("https://wa.me/" & VLOOKUP(A22, 'Master Roster'!$A:$F, 6, FALSE) & "?text=" & ENCODEURL("Hello " & IFERROR(IF(VLOOKUP(A22, 'Master Roster'!$A:$J, 10, FALSE)="Male", "Mr. ", "Ms. "), "") & B22 & ", payment of K" & F22 & " received for " & period & ". Receipt No: " & N22), "Send Receipt")))
H23: =IF(A23="", "", HYPERLINK("#gid=123456789", "💬 Send Receipt")) | I23: =IF(ISBLANK(A23), "", HYPERLINK("#gid=123456789", "Print Receipt")) | J23: =IF(A23="", "", IFERROR(VLOOKUP(A23, 'Master Roster'!A:H, 8, FALSE) - F23, "")) | L23: FALSE | O23: =IF(ISBLANK(A23), "", LET(entry_day, VLOOKUP(A23, 'Master Roster'!$A:$G, 7, FALSE), start_date, DATE(E23, MONTH(D23&" 1"), entry_day), end_date, EDATE(start_date, 1), period, TEXT(start_date, "mmm d, yyyy") & " - " & TEXT(end_date, "mmm d, yyyy"), HYPERLINK("https://wa.me/" & VLOOKUP(A23, 'Master Roster'!$A:$F, 6, FALSE) & "?text=" & ENCODEURL("Hello " & IFERROR(IF(VLOOKUP(A23, 'Master Roster'!$A:$J, 10, FALSE)="Male", "Mr. ", "Ms. "), "") & B23 & ", payment of K" & F23 & " received for " & period & ". Receipt No: " & N23), "Send Receipt")))
H24: =IF(A24="", "", HYPERLINK("#gid=123456789", "💬 Send Receipt")) | I24: =IF(ISBLANK(A24), "", HYPERLINK("#gid=123456789", "Print Receipt")) | J24: =IF(A24="", "", IFERROR(VLOOKUP(A24, 'Master Roster'!A:H, 8, FALSE) - F24, "")) | L24: FALSE | O24: =IF(ISBLANK(A24), "", LET(entry_day, VLOOKUP(A24, 'Master Roster'!$A:$G, 7, FALSE), start_date, DATE(E24, MONTH(D24&" 1"), entry_day), end_date, EDATE(start_date, 1), period, TEXT(start_date, "mmm d, yyyy") & " - " & TEXT(end_date, "mmm d, yyyy"), HYPERLINK("https://wa.me/" & VLOOKUP(A24, 'Master Roster'!$A:$F, 6, FALSE) & "?text=" & ENCODEURL("Hello " & IFERROR(IF(VLOOKUP(A24, 'Master Roster'!$A:$J, 10, FALSE)="Male", "Mr. ", "Ms. "), "") & B24 & ", payment of K" & F24 & " received for " & period & ". Receipt No: " & N24), "Send Receipt")))
H25: =IF(A25="", "", HYPERLINK("#gid=123456789", "💬 Send Receipt")) | I25: =IF(ISBLANK(A25), "", HYPERLINK("#gid=123456789", "Print Receipt")) | J25: =IF(A25="", "", IFERROR(VLOOKUP(A25, 'Master Roster'!A:H, 8, FALSE) - F25, "")) | L25: FALSE | O25: =IF(ISBLANK(A25), "", LET(entry_day, VLOOKUP(A25, 'Master Roster'!$A:$G, 7, FALSE), start_date, DATE(E25, MONTH(D25&" 1"), entry_day), end_date, EDATE(start_date, 1), period, TEXT(start_date, "mmm d, yyyy") & " - " & TEXT(end_date, "mmm d, yyyy"), HYPERLINK("https://wa.me/" & VLOOKUP(A25, 'Master Roster'!$A:$F, 6, FALSE) & "?text=" & ENCODEURL("Hello " & IFERROR(IF(VLOOKUP(A25, 'Master Roster'!$A:$J, 10, FALSE)="Male", "Mr. ", "Ms. "), "") & B25 & ", payment of K" & F25 & " received for " & period & ". Receipt No: " & N25), "Send Receipt")))
H26: =IF(A26="", "", HYPERLINK("#gid=123456789", "💬 Send Receipt")) | I26: =IF(ISBLANK(A26), "", HYPERLINK("#gid=123456789", "Print Receipt")) | J26: =IF(A26="", "", IFERROR(VLOOKUP(A26, 'Master Roster'!A:H, 8, FALSE) - F26, "")) | L26: FALSE | O26: =IF(ISBLANK(A26), "", LET(entry_day, VLOOKUP(A26, 'Master Roster'!$A:$G, 7, FALSE), start_date, DATE(E26, MONTH(D26&" 1"), entry_day), end_date, EDATE(start_date, 1), period, TEXT(start_date, "mmm d, yyyy") & " - " & TEXT(end_date, "mmm d, yyyy"), HYPERLINK("https://wa.me/" & VLOOKUP(A26, 'Master Roster'!$A:$F, 6, FALSE) & "?text=" & ENCODEURL("Hello " & IFERROR(IF(VLOOKUP(A26, 'Master Roster'!$A:$J, 10, FALSE)="Male", "Mr. ", "Ms. "), "") & B26 & ", payment of K" & F26 & " received for " & period & ". Receipt No: " & N26), "Send Receipt")))
H27: =IF(A27="", "", HYPERLINK("#gid=123456789", "💬 Send Receipt")) | I27: =IF(ISBLANK(A27), "", HYPERLINK("#gid=123456789", "Print Receipt")) | J27: =IF(A27="", "", IFERROR(VLOOKUP(A27, 'Master Roster'!A:H, 8, FALSE) - F27, "")) | L27: FALSE | O27: =IF(ISBLANK(A27), "", LET(entry_day, VLOOKUP(A27, 'Master Roster'!$A:$G, 7, FALSE), start_date, DATE(E27, MONTH(D27&" 1"), entry_day), end_date, EDATE(start_date, 1), period, TEXT(start_date, "mmm d, yyyy") & " - " & TEXT(end_date, "mmm d, yyyy"), HYPERLINK("https://wa.me/" & VLOOKUP(A27, 'Master Roster'!$A:$F, 6, FALSE) & "?text=" & ENCODEURL("Hello " & IFERROR(IF(VLOOKUP(A27, 'Master Roster'!$A:$J, 10, FALSE)="Male", "Mr. ", "Ms. "), "") & B27 & ", payment of K" & F27 & " received for " & period & ". Receipt No: " & N27), "Send Receipt")))
H28: =IF(A28="", "", HYPERLINK("#gid=123456789", "💬 Send Receipt")) | I28: =IF(ISBLANK(A28), "", HYPERLINK("#gid=123456789", "Print Receipt")) | J28: =IF(A28="", "", IFERROR(VLOOKUP(A28, 'Master Roster'!A:H, 8, FALSE) - F28, "")) | L28: FALSE | O28: =IF(ISBLANK(A28), "", LET(entry_day, VLOOKUP(A28, 'Master Roster'!$A:$G, 7, FALSE), start_date, DATE(E28, MONTH(D28&" 1"), entry_day), end_date, EDATE(start_date, 1), period, TEXT(start_date, "mmm d, yyyy") & " - " & TEXT(end_date, "mmm d, yyyy"), HYPERLINK("https://wa.me/" & VLOOKUP(A28, 'Master Roster'!$A:$F, 6, FALSE) & "?text=" & ENCODEURL("Hello " & IFERROR(IF(VLOOKUP(A28, 'Master Roster'!$A:$J, 10, FALSE)="Male", "Mr. ", "Ms. "), "") & B28 & ", payment of K" & F28 & " received for " & period & ". Receipt No: " & N28), "Send Receipt")))
H29: =IF(A29="", "", HYPERLINK("#gid=123456789", "💬 Send Receipt")) | I29: =IF(ISBLANK(A29), "", HYPERLINK("#gid=123456789", "Print Receipt")) | J29: =IF(A29="", "", IFERROR(VLOOKUP(A29, 'Master Roster'!A:H, 8, FALSE) - F29, "")) | L29: FALSE | O29: =IF(ISBLANK(A29), "", LET(entry_day, VLOOKUP(A29, 'Master Roster'!$A:$G, 7, FALSE), start_date, DATE(E29, MONTH(D29&" 1"), entry_day), end_date, EDATE(start_date, 1), period, TEXT(start_date, "mmm d, yyyy") & " - " & TEXT(end_date, "mmm d, yyyy"), HYPERLINK("https://wa.me/" & VLOOKUP(A29, 'Master Roster'!$A:$F, 6, FALSE) & "?text=" & ENCODEURL("Hello " & IFERROR(IF(VLOOKUP(A29, 'Master Roster'!$A:$J, 10, FALSE)="Male", "Mr. ", "Ms. "), "") & B29 & ", payment of K" & F29 & " received for " & period & ". Receipt No: " & N29), "Send Receipt")))
H30: =IF(A30="", "", HYPERLINK("#gid=123456789", "💬 Send Receipt")) | I30: =IF(ISBLANK(A30), "", HYPERLINK("#gid=123456789", "Print Receipt")) | J30: =IF(A30="", "", IFERROR(VLOOKUP(A30, 'Master Roster'!A:H, 8, FALSE) - F30, "")) | L30: FALSE | O30: =IF(ISBLANK(A30), "", LET(entry_day, VLOOKUP(A30, 'Master Roster'!$A:$G, 7, FALSE), start_date, DATE(E30, MONTH(D30&" 1"), entry_day), end_date, EDATE(start_date, 1), period, TEXT(start_date, "mmm d, yyyy") & " - " & TEXT(end_date, "mmm d, yyyy"), HYPERLINK("https://wa.me/" & VLOOKUP(A30, 'Master Roster'!$A:$F, 6, FALSE) & "?text=" & ENCODEURL("Hello " & IFERROR(IF(VLOOKUP(A30, 'Master Roster'!$A:$J, 10, FALSE)="Male", "Mr. ", "Ms. "), "") & B30 & ", payment of K" & F30 & " received for " & period & ". Receipt No: " & N30), "Send Receipt")))
H31: =IF(A31="", "", HYPERLINK("#gid=123456789", "💬 Send Receipt")) | I31: =IF(ISBLANK(A31), "", HYPERLINK("#gid=123456789", "Print Receipt")) | J31: =IF(A31="", "", IFERROR(VLOOKUP(A31, 'Master Roster'!A:H, 8, FALSE) - F31, "")) | L31: FALSE | O31: =IF(ISBLANK(A31), "", LET(entry_day, VLOOKUP(A31, 'Master Roster'!$A:$G, 7, FALSE), start_date, DATE(E31, MONTH(D31&" 1"), entry_day), end_date, EDATE(start_date, 1), period, TEXT(start_date, "mmm d, yyyy") & " - " & TEXT(end_date, "mmm d, yyyy"), HYPERLINK("https://wa.me/" & VLOOKUP(A31, 'Master Roster'!$A:$F, 6, FALSE) & "?text=" & ENCODEURL("Hello " & IFERROR(IF(VLOOKUP(A31, 'Master Roster'!$A:$J, 10, FALSE)="Male", "Mr. ", "Ms. "), "") & B31 & ", payment of K" & F31 & " received for " & period & ". Receipt No: " & N31), "Send Receipt")))
H32: =IF(A32="", "", HYPERLINK("#gid=123456789", "💬 Send Receipt")) | I32: =IF(ISBLANK(A32), "", HYPERLINK("#gid=123456789", "Print Receipt")) | J32: =IF(A32="", "", IFERROR(VLOOKUP(A32, 'Master Roster'!A:H, 8, FALSE) - F32, "")) | L32: FALSE | O32: =IF(ISBLANK(A32), "", LET(entry_day, VLOOKUP(A32, 'Master Roster'!$A:$G, 7, FALSE), start_date, DATE(E32, MONTH(D32&" 1"), entry_day), end_date, EDATE(start_date, 1), period, TEXT(start_date, "mmm d, yyyy") & " - " & TEXT(end_date, "mmm d, yyyy"), HYPERLINK("https://wa.me/" & VLOOKUP(A32, 'Master Roster'!$A:$F, 6, FALSE) & "?text=" & ENCODEURL("Hello " & IFERROR(IF(VLOOKUP(A32, 'Master Roster'!$A:$J, 10, FALSE)="Male", "Mr. ", "Ms. "), "") & B32 & ", payment of K" & F32 & " received for " & period & ". Receipt No: " & N32), "Send Receipt")))
H33: =IF(A33="", "", HYPERLINK("#gid=123456789", "💬 Send Receipt")) | I33: =IF(ISBLANK(A33), "", HYPERLINK("#gid=123456789", "Print Receipt")) | J33: =IF(A33="", "", IFERROR(VLOOKUP(A33, 'Master Roster'!A:H, 8, FALSE) - F33, "")) | L33: FALSE | O33: =IF(ISBLANK(A33), "", LET(entry_day, VLOOKUP(A33, 'Master Roster'!$A:$G, 7, FALSE), start_date, DATE(E33, MONTH(D33&" 1"), entry_day), end_date, EDATE(start_date, 1), period, TEXT(start_date, "mmm d, yyyy") & " - " & TEXT(end_date, "mmm d, yyyy"), HYPERLINK("https://wa.me/" & VLOOKUP(A33, 'Master Roster'!$A:$F, 6, FALSE) & "?text=" & ENCODEURL("Hello " & IFERROR(IF(VLOOKUP(A33, 'Master Roster'!$A:$J, 10, FALSE)="Male", "Mr. ", "Ms. "), "") & B33 & ", payment of K" & F33 & " received for " & period & ". Receipt No: " & N33), "Send Receipt")))
... H1002: =IF(A1002="", "", HYPERLINK("#gid=123456789", "💬 Send Receipt")) | I1002: =IF(ISBLANK(A1002), "", HYPERLINK("#gid=123456789", "Print Receipt")) | J1002: =IF(A1002="", "", IFERROR(VLOOKUP(A1002, 'Master Roster'!A:H, 8, FALSE) - F1002, "")) | L1002: FALSE | O1002: =IF(ISBLANK(A1002), "", LET(entry_day, VLOOKUP(A1002, 'Master Roster'!$A:$G, 7, FALSE), start_date, DATE(E1002, MONTH(D1002&" 1"), entry_day), end_date, EDATE(start_date, 1), period, TEXT(start_date, "mmm d, yyyy") & " - " & TEXT(end_date, "mmm d, yyyy"), HYPERLINK("https://wa.me/" & VLOOKUP(A1002, 'Master Roster'!$A:$F, 6, FALSE) & "?text=" & ENCODEURL("Hello " & IFERROR(IF(VLOOKUP(A1002, 'Master Roster'!$A:$J, 10, FALSE)="Male", "Mr. ", "Ms. "), "") & B1002 & ", payment of K" & F1002 & " received for " & period & ". Receipt No: " & N1002), "Send Receipt")))

Sheet Calc_Data
A1: Calc_Data | G1: Status | H1: Count | J1: =IFERROR(__xludf.DUMMYFUNCTION("QUERY('Monthly Billing Tab'!M3:M1002, ""select M, count(M) where M is not null group by M label M 'Billing Status', count(M) 'Count'"", 1)"),"Billing Status") -> Billing Status | K1: =IFERROR(__xludf.DUMMYFUNCTION("""COMPUTED_VALUE"""),"Count") -> Count | L1: Amount
G2: Active Tenants | H2: ='Available Bed Spaces'!I8 -> 47 | J2: =IFERROR(__xludf.DUMMYFUNCTION("""COMPUTED_VALUE"""),"Vacant") -> Vacant | K2: =IFERROR(__xludf.DUMMYFUNCTION("""COMPUTED_VALUE"""),7.0) -> 7 | L2: =SUMIF('Monthly Billing Tab'!M:M, J2, 'Monthly Billing Tab'!F:F) -> 6000 | N2: =IFERROR(__xludf.DUMMYFUNCTION("SORT(UNIQUE(FILTER('Master Roster'!E4:E1002, 'Master Roster'!E4:E1002 <> """", 'Master Roster'!E4:E1002 <> ""Vacant"")))"),"Ackim Siamafuko") -> Ackim Siamafuko
A3: Total Expected Revenue | B3: =SUM('Master Roster'!H4:H1002) -> 56250 | D3: =IFERROR(__xludf.DUMMYFUNCTION("{""Select""; SORT(FILTER('Monthly Billing Tab'!D4:D1002, 'Monthly Billing Tab'!D4:D1002<>""""))}"),"Select") -> Select | G3: Vacant | H3: ='Available Bed Spaces'!I6 -> 7 | J3: =IFERROR(__xludf.DUMMYFUNCTION("""COMPUTED_VALUE"""),"⏳ Grace Period") -> ⏳ Grace Period | K3: =IFERROR(__xludf.DUMMYFUNCTION("""COMPUTED_VALUE"""),6.0) -> 6 | L3: =SUMIF('Monthly Billing Tab'!M:M, J3, 'Monthly Billing Tab'!F:F) -> 5900 | N3: =IFERROR(__xludf.DUMMYFUNCTION("""COMPUTED_VALUE"""),"Adrian mulale") -> Adrian mulale
A4: Active Tenants | B4: =COUNTIFS('Master Roster'!E4:E1002, "<>Vacant", 'Master Roster'!E4:E1002, "<>Reserved", 'Master Roster'!E4:E1002, "<>") -> 47 | D4: =IFERROR(__xludf.DUMMYFUNCTION("""COMPUTED_VALUE"""),"Ackim Siamafuko") -> Ackim Siamafuko | G4: Reserved | H4: ='Available Bed Spaces'!J6 -> 0 | J4: =IFERROR(__xludf.DUMMYFUNCTION("""COMPUTED_VALUE"""),"✅ Paid / Secured") -> ✅ Paid / Secured | K4: =IFERROR(__xludf.DUMMYFUNCTION("""COMPUTED_VALUE"""),12.0) -> 12 | L4: =SUMIF('Monthly Billing Tab'!M:M, J4, 'Monthly Billing Tab'!F:F) -> 13200 | N4: =IFERROR(__xludf.DUMMYFUNCTION("""COMPUTED_VALUE"""),"Catherine Mphande") -> Catherine Mphande
A5: Total Beds | B5: =COUNTA('Master Roster'!D4:D1002) -> 54 | D5: =IFERROR(__xludf.DUMMYFUNCTION("""COMPUTED_VALUE"""),"Adrian mulale") -> Adrian mulale | J5: =IFERROR(__xludf.DUMMYFUNCTION("""COMPUTED_VALUE"""),"❌ OVERDUE / UNPAID") -> ❌ OVERDUE / UNPAID | K5: =IFERROR(__xludf.DUMMYFUNCTION("""COMPUTED_VALUE"""),10.0) -> 10 | L5: =SUMIF('Monthly Billing Tab'!M:M, J5, 'Monthly Billing Tab'!F:F) -> 10550 | N5: =IFERROR(__xludf.DUMMYFUNCTION("""COMPUTED_VALUE"""),"Chama Kampamba") -> Chama Kampamba
A6: Occupancy Rate | B6: =B4/B5 -> 0.87037037 | D6: =IFERROR(__xludf.DUMMYFUNCTION("""COMPUTED_VALUE"""),"Catherine Mphande") -> Catherine Mphande | J6: =IFERROR(__xludf.DUMMYFUNCTION("""COMPUTED_VALUE"""),"🟢 Open Window") -> 🟢 Open Window | K6: =IFERROR(__xludf.DUMMYFUNCTION("""COMPUTED_VALUE"""),19.0) -> 19 | L6: =SUMIF('Monthly Billing Tab'!M:M, J6, 'Monthly Billing Tab'!F:F) -> 20600 | N6: =IFERROR(__xludf.DUMMYFUNCTION("""COMPUTED_VALUE"""),"Chami Soneka") -> Chami Soneka
A7: Total Debt | B7: =SUM('Monthly Billing Tab'!L4:L49) -> 43000 | D7: =IFERROR(__xludf.DUMMYFUNCTION("""COMPUTED_VALUE"""),"Chama Kampamba") -> Chama Kampamba | L7: =SUM(L2:L6) -> 56250 | N7: =IFERROR(__xludf.DUMMYFUNCTION("""COMPUTED_VALUE"""),"Chanda Lutashima") -> Chanda Lutashima
A8: Total Grace Period | B8: =SUMIFS('Monthly Billing Tab'!L:L, 'Monthly Billing Tab'!M:M, "⏳ Grace Period") -> 5500 | D8: =IFERROR(__xludf.DUMMYFUNCTION("""COMPUTED_VALUE"""),"Chami Soneka") -> Chami Soneka | N8: =IFERROR(__xludf.DUMMYFUNCTION("""COMPUTED_VALUE"""),"Chansa Chinyama") -> Chansa Chinyama
A9: Total Open Window | B9: =IFERROR(__xludf.DUMMYFUNCTION("SUM(IFERROR(FILTER('Monthly Billing Tab'!K4:K1002 - (MONTH(TODAY()) * 'Monthly Billing Tab'!F4:F1002 + IFERROR('Monthly Billing Tab'!H4:H1002, 0)), 'Monthly Billing Tab'!M4:M1002=""🟢 Open Window""), 0))"),-20600.0) -> -20600 | D9: =IFERROR(__xludf.DUMMYFUNCTION("""COMPUTED_VALUE"""),"Chanda Lutashima") -> Chanda Lutashima | N9: =IFERROR(__xludf.DUMMYFUNCTION("""COMPUTED_VALUE"""),"Chibesa Chisembe") -> Chibesa Chisembe
D10: =IFERROR(__xludf.DUMMYFUNCTION("""COMPUTED_VALUE"""),"Chansa Chinyama") -> Chansa Chinyama | N10: =IFERROR(__xludf.DUMMYFUNCTION("""COMPUTED_VALUE"""),"chilulu chiliulu") -> chilulu chiliulu
D11: =IFERROR(__xludf.DUMMYFUNCTION("""COMPUTED_VALUE"""),"Chibesa Chisembe") -> Chibesa Chisembe | N11: =IFERROR(__xludf.DUMMYFUNCTION("""COMPUTED_VALUE"""),"Christopher Phiri") -> Christopher Phiri
D12: =IFERROR(__xludf.DUMMYFUNCTION("""COMPUTED_VALUE"""),"chilulu chiliulu") -> chilulu chiliulu | N12: =IFERROR(__xludf.DUMMYFUNCTION("""COMPUTED_VALUE"""),"Christopher Tambule") -> Christopher Tambule
D13: =IFERROR(__xludf.DUMMYFUNCTION("""COMPUTED_VALUE"""),"Christopher Phiri") -> Christopher Phiri | N13: =IFERROR(__xludf.DUMMYFUNCTION("""COMPUTED_VALUE"""),"Collins Mubanga") -> Collins Mubanga
D14: =IFERROR(__xludf.DUMMYFUNCTION("""COMPUTED_VALUE"""),"Christopher Tambule") -> Christopher Tambule | N14: =IFERROR(__xludf.DUMMYFUNCTION("""COMPUTED_VALUE"""),"David Mulila") -> David Mulila
D15: =IFERROR(__xludf.DUMMYFUNCTION("""COMPUTED_VALUE"""),"Collins Mubanga") -> Collins Mubanga | N15: =IFERROR(__xludf.DUMMYFUNCTION("""COMPUTED_VALUE"""),"Emely Mwale") -> Emely Mwale
D16: =IFERROR(__xludf.DUMMYFUNCTION("""COMPUTED_VALUE"""),"David Mulila") -> David Mulila | N16: =IFERROR(__xludf.DUMMYFUNCTION("""COMPUTED_VALUE"""),"Felistus Mweemba") -> Felistus Mweemba
D17: =IFERROR(__xludf.DUMMYFUNCTION("""COMPUTED_VALUE"""),"Emely Mwale") -> Emely Mwale | N17: =IFERROR(__xludf.DUMMYFUNCTION("""COMPUTED_VALUE"""),"Funny Muyamina") -> Funny Muyamina
D18: =IFERROR(__xludf.DUMMYFUNCTION("""COMPUTED_VALUE"""),"Felistus Mweemba") -> Felistus Mweemba | N18: =IFERROR(__xludf.DUMMYFUNCTION("""COMPUTED_VALUE"""),"Gabirel Kabwe") -> Gabirel Kabwe
D19: =IFERROR(__xludf.DUMMYFUNCTION("""COMPUTED_VALUE"""),"Funny Muyamina") -> Funny Muyamina | N19: =IFERROR(__xludf.DUMMYFUNCTION("""COMPUTED_VALUE"""),"Gift Nankamba") -> Gift Nankamba
D20: =IFERROR(__xludf.DUMMYFUNCTION("""COMPUTED_VALUE"""),"Gabirel Kabwe") -> Gabirel Kabwe | N20: =IFERROR(__xludf.DUMMYFUNCTION("""COMPUTED_VALUE"""),"Grace Mwamba") -> Grace Mwamba
D21: =IFERROR(__xludf.DUMMYFUNCTION("""COMPUTED_VALUE"""),"Gift Nankamba") -> Gift Nankamba | N21: =IFERROR(__xludf.DUMMYFUNCTION("""COMPUTED_VALUE"""),"Harriet nanyangwe") -> Harriet nanyangwe
D22: =IFERROR(__xludf.DUMMYFUNCTION("""COMPUTED_VALUE"""),"Grace Mwamba") -> Grace Mwamba | N22: =IFERROR(__xludf.DUMMYFUNCTION("""COMPUTED_VALUE"""),"Himalikiti Saviour") -> Himalikiti Saviour
D23: =IFERROR(__xludf.DUMMYFUNCTION("""COMPUTED_VALUE"""),"Harriet nanyangwe") -> Harriet nanyangwe | N23: =IFERROR(__xludf.DUMMYFUNCTION("""COMPUTED_VALUE"""),"Jackson Mwanza") -> Jackson Mwanza
D24: =IFERROR(__xludf.DUMMYFUNCTION("""COMPUTED_VALUE"""),"Himalikiti Saviour") -> Himalikiti Saviour | N24: =IFERROR(__xludf.DUMMYFUNCTION("""COMPUTED_VALUE"""),"Jacqueline Mwape") -> Jacqueline Mwape
D25: =IFERROR(__xludf.DUMMYFUNCTION("""COMPUTED_VALUE"""),"Jackson Mwanza") -> Jackson Mwanza | N25: =IFERROR(__xludf.DUMMYFUNCTION("""COMPUTED_VALUE"""),"Jairos Banda") -> Jairos Banda
D26: =IFERROR(__xludf.DUMMYFUNCTION("""COMPUTED_VALUE"""),"Jacqueline Mwape") -> Jacqueline Mwape | N26: =IFERROR(__xludf.DUMMYFUNCTION("""COMPUTED_VALUE"""),"Josephine Nyirenda ") -> Josephine Nyirenda
D27: =IFERROR(__xludf.DUMMYFUNCTION("""COMPUTED_VALUE"""),"Jairos Banda") -> Jairos Banda | N27: =IFERROR(__xludf.DUMMYFUNCTION("""COMPUTED_VALUE"""),"Kangwa Kunda") -> Kangwa Kunda
D28: =IFERROR(__xludf.DUMMYFUNCTION("""COMPUTED_VALUE"""),"Josephine Nyirenda ") -> Josephine Nyirenda | N28: =IFERROR(__xludf.DUMMYFUNCTION("""COMPUTED_VALUE"""),"Kawina Florence") -> Kawina Florence
D29: =IFERROR(__xludf.DUMMYFUNCTION("""COMPUTED_VALUE"""),"Kangwa Kunda") -> Kangwa Kunda | N29: =IFERROR(__xludf.DUMMYFUNCTION("""COMPUTED_VALUE"""),"Kuwunda Makondo") -> Kuwunda Makondo
D30: =IFERROR(__xludf.DUMMYFUNCTION("""COMPUTED_VALUE"""),"Kawina Florence") -> Kawina Florence | N30: =IFERROR(__xludf.DUMMYFUNCTION("""COMPUTED_VALUE"""),"Kwitu Khalu") -> Kwitu Khalu
D31: =IFERROR(__xludf.DUMMYFUNCTION("""COMPUTED_VALUE"""),"Kuwunda Makondo") -> Kuwunda Makondo | N31: =IFERROR(__xludf.DUMMYFUNCTION("""COMPUTED_VALUE"""),"Lubono Ruthendo") -> Lubono Ruthendo
D32: =IFERROR(__xludf.DUMMYFUNCTION("""COMPUTED_VALUE"""),"Kwitu Khalu") -> Kwitu Khalu | N32: =IFERROR(__xludf.DUMMYFUNCTION("""COMPUTED_VALUE"""),"Lukundo Siame") -> Lukundo Siame
D33: =IFERROR(__xludf.DUMMYFUNCTION("""COMPUTED_VALUE"""),"Lubono Ruthendo") -> Lubono Ruthendo | N33: =IFERROR(__xludf.DUMMYFUNCTION("""COMPUTED_VALUE"""),"Lushomo gambwe") -> Lushomo gambwe
D34: =IFERROR(__xludf.DUMMYFUNCTION("""COMPUTED_VALUE"""),"Lukundo Siame") -> Lukundo Siame | N34: =IFERROR(__xludf.DUMMYFUNCTION("""COMPUTED_VALUE"""),"McDonald") -> McDonald
D35: =IFERROR(__xludf.DUMMYFUNCTION("""COMPUTED_VALUE"""),"Lushomo gambwe") -> Lushomo gambwe | N35: =IFERROR(__xludf.DUMMYFUNCTION("""COMPUTED_VALUE"""),"Melody Mumba") -> Melody Mumba
D36: =IFERROR(__xludf.DUMMYFUNCTION("""COMPUTED_VALUE"""),"McDonald") -> McDonald | N36: =IFERROR(__xludf.DUMMYFUNCTION("""COMPUTED_VALUE"""),"Nanga Obrien") -> Nanga Obrien
D37: =IFERROR(__xludf.DUMMYFUNCTION("""COMPUTED_VALUE"""),"Melody Mumba") -> Melody Mumba | N37: =IFERROR(__xludf.DUMMYFUNCTION("""COMPUTED_VALUE"""),"Ongani Madaliso Gabriel ") -> Ongani Madaliso Gabriel
D38: =IFERROR(__xludf.DUMMYFUNCTION("""COMPUTED_VALUE"""),"Nanga Obrien") -> Nanga Obrien | N38: =IFERROR(__xludf.DUMMYFUNCTION("""COMPUTED_VALUE"""),"Prosper Kalayi") -> Prosper Kalayi
D39: =IFERROR(__xludf.DUMMYFUNCTION("""COMPUTED_VALUE"""),"Ongani Madaliso Gabriel ") -> Ongani Madaliso Gabriel | N39: =IFERROR(__xludf.DUMMYFUNCTION("""COMPUTED_VALUE"""),"Reuben Ngusulu") -> Reuben Ngusulu
D40: =IFERROR(__xludf.DUMMYFUNCTION("""COMPUTED_VALUE"""),"Prosper Kalayi") -> Prosper Kalayi | N40: =IFERROR(__xludf.DUMMYFUNCTION("""COMPUTED_VALUE"""),"Samantha Musako (Kakompe)") -> Samantha Musako (Kakompe)
D41: =IFERROR(__xludf.DUMMYFUNCTION("""COMPUTED_VALUE"""),"Reuben Ngusulu") -> Reuben Ngusulu | N41: =IFERROR(__xludf.DUMMYFUNCTION("""COMPUTED_VALUE"""),"Sara Matakala") -> Sara Matakala
D42: =IFERROR(__xludf.DUMMYFUNCTION("""COMPUTED_VALUE"""),"Samantha Musako (Kakompe)") -> Samantha Musako (Kakompe) | N42: =IFERROR(__xludf.DUMMYFUNCTION("""COMPUTED_VALUE"""),"Shadrach Munganini") -> Shadrach Munganini
D43: =IFERROR(__xludf.DUMMYFUNCTION("""COMPUTED_VALUE"""),"Sara Matakala") -> Sara Matakala | N43: =IFERROR(__xludf.DUMMYFUNCTION("""COMPUTED_VALUE"""),"Steven Musonda") -> Steven Musonda
D44: =IFERROR(__xludf.DUMMYFUNCTION("""COMPUTED_VALUE"""),"Shadrach Munganini") -> Shadrach Munganini | N44: =IFERROR(__xludf.DUMMYFUNCTION("""COMPUTED_VALUE"""),"Treasure Simeenda") -> Treasure Simeenda
D45: =IFERROR(__xludf.DUMMYFUNCTION("""COMPUTED_VALUE"""),"Steven Musonda") -> Steven Musonda | N45: =IFERROR(__xludf.DUMMYFUNCTION("""COMPUTED_VALUE"""),"Wampa ") -> Wampa
D46: =IFERROR(__xludf.DUMMYFUNCTION("""COMPUTED_VALUE"""),"Treasure Simeenda") -> Treasure Simeenda | N46: =IFERROR(__xludf.DUMMYFUNCTION("""COMPUTED_VALUE"""),"Wendy Mpakise") -> Wendy Mpakise
D47: =IFERROR(__xludf.DUMMYFUNCTION("""COMPUTED_VALUE"""),"Vacant") -> Vacant | N47: =IFERROR(__xludf.DUMMYFUNCTION("""COMPUTED_VALUE"""),"Wisdom Bwani") -> Wisdom Bwani
D48: =IFERROR(__xludf.DUMMYFUNCTION("""COMPUTED_VALUE"""),"Vacant") -> Vacant | N48: =IFERROR(__xludf.DUMMYFUNCTION("""COMPUTED_VALUE"""),"Zick Phiri") -> Zick Phiri
D49: =IFERROR(__xludf.DUMMYFUNCTION("""COMPUTED_VALUE"""),"Vacant") -> Vacant
D50: =IFERROR(__xludf.DUMMYFUNCTION("""COMPUTED_VALUE"""),"Vacant") -> Vacant
D51: =IFERROR(__xludf.DUMMYFUNCTION("""COMPUTED_VALUE"""),"Vacant") -> Vacant
D52: =IFERROR(__xludf.DUMMYFUNCTION("""COMPUTED_VALUE"""),"Vacant") -> Vacant
D53: =IFERROR(__xludf.DUMMYFUNCTION("""COMPUTED_VALUE"""),"Vacant") -> Vacant
D54: =IFERROR(__xludf.DUMMYFUNCTION("""COMPUTED_VALUE"""),"Wampa ") -> Wampa
D55: =IFERROR(__xludf.DUMMYFUNCTION("""COMPUTED_VALUE"""),"Wendy Mpakise") -> Wendy Mpakise
D56: =IFERROR(__xludf.DUMMYFUNCTION("""COMPUTED_VALUE"""),"Wisdom Bwani") -> Wisdom Bwani
D57: =IFERROR(__xludf.DUMMYFUNCTION("""COMPUTED_VALUE"""),"Zick Phiri") -> Zick Phiri
A60: =IFERROR(__xludf.DUMMYFUNCTION("QUERY('Master Roster'!A3:J1002, ""SELECT C, COUNT(A) WHERE E != 'Vacant' AND E != 'Reserved' AND E IS NOT NULL GROUP BY C LABEL C 'House/Block', COUNT(A) 'Occupied Beds'"")"),"House/Block") -> House/Block | B60: =IFERROR(__xludf.DUMMYFUNCTION("""COMPUTED_VALUE"""),"Occupied Beds") -> Occupied Beds | D60: =IFERROR(__xludf.DUMMYFUNCTION("QUERY('Master Roster'!A3:J1002, ""SELECT C, SUM(H) WHERE C IS NOT NULL GROUP BY C LABEL C 'House/Block', SUM(H) 'Expected Revenue'"")"),"House/Block") -> House/Block | E60: =IFERROR(__xludf.DUMMYFUNCTION("""COMPUTED_VALUE"""),"Expected Revenue") -> Expected Revenue
A61: =IFERROR(__xludf.DUMMYFUNCTION("""COMPUTED_VALUE"""),"ANX") -> ANX | B61: =IFERROR(__xludf.DUMMYFUNCTION("""COMPUTED_VALUE"""),5.0) -> 5 | D61: =IFERROR(__xludf.DUMMYFUNCTION("""COMPUTED_VALUE"""),"ANX") -> ANX | E61: =IFERROR(__xludf.DUMMYFUNCTION("""COMPUTED_VALUE"""),6200.0) -> 6200
A62: =IFERROR(__xludf.DUMMYFUNCTION("""COMPUTED_VALUE"""),"BBH") -> BBH | B62: =IFERROR(__xludf.DUMMYFUNCTION("""COMPUTED_VALUE"""),16.0) -> 16 | D62: =IFERROR(__xludf.DUMMYFUNCTION("""COMPUTED_VALUE"""),"BBH") -> BBH | E62: =IFERROR(__xludf.DUMMYFUNCTION("""COMPUTED_VALUE"""),16300.0) -> 16300
A63: =IFERROR(__xludf.DUMMYFUNCTION("""COMPUTED_VALUE"""),"CRV") -> CRV | B63: =IFERROR(__xludf.DUMMYFUNCTION("""COMPUTED_VALUE"""),3.0) -> 3 | D63: =IFERROR(__xludf.DUMMYFUNCTION("""COMPUTED_VALUE"""),"CRV") -> CRV | E63: =IFERROR(__xludf.DUMMYFUNCTION("""COMPUTED_VALUE"""),3300.0) -> 3300
A64: =IFERROR(__xludf.DUMMYFUNCTION("""COMPUTED_VALUE"""),"NWG") -> NWG | B64: =IFERROR(__xludf.DUMMYFUNCTION("""COMPUTED_VALUE"""),15.0) -> 15 | D64: =IFERROR(__xludf.DUMMYFUNCTION("""COMPUTED_VALUE"""),"NWG") -> NWG | E64: =IFERROR(__xludf.DUMMYFUNCTION("""COMPUTED_VALUE"""),20400.0) -> 20400
A65: =IFERROR(__xludf.DUMMYFUNCTION("""COMPUTED_VALUE"""),"UPV") -> UPV | B65: =IFERROR(__xludf.DUMMYFUNCTION("""COMPUTED_VALUE"""),8.0) -> 8 | D65: =IFERROR(__xludf.DUMMYFUNCTION("""COMPUTED_VALUE"""),"UPV") -> UPV | E65: =IFERROR(__xludf.DUMMYFUNCTION("""COMPUTED_VALUE"""),10050.0) -> 10050

Sheet Payments Log
A1: Payments Log
A3: Unique ID | B3: Tenant Name | C3: January | D3: February | E3: March | F3: April | G3: May | H3: June | I3: July | J3: August | K3: September | L3: October | M3: November | N3: December | O3: Yearly Total
A4: Monthly Total | C4: {=BYCOL(C5:N1002, LAMBDA(c, SUM(c)))} -> 41100 | D4: 41100 | E4: 41100 | F4: 41100 | G4: 41100 | H4: 39300 | I4: 38100 | J4: 31750 | K4: 9500 | L4: 0 | M4: 0 | N4: 0 | O4: =SUM(C4:N4) -> 324150
A5: =IFERROR(__xludf.DUMMYFUNCTION("FILTER('Master Roster'!A4:A1002, 'Master Roster'!A4:A1002<>"""")"),"BBH-1-A") -> BBH-1-A | B5: =IFERROR(VLOOKUP($A5, 'Master Roster'!$A:$E, 5, FALSE), "") -> Adrian mulale | C5: {=MAKEARRAY(COUNTA(A5:A1002), 12, LAMBDA(r, c, LET(tenant, INDEX(B5:B1002, r, 1), id, INDEX(A5:A1002, r, 1), target, IFERROR(VLOOKUP(id, 'Monthly Billing Tab'!$B$4:$J$48, 9, FALSE), ""), rent, IFERROR(VLOOKUP(id, 'Monthly Billing Tab'!$B$4:$F$48, 5, FALSE), ""), IF(tenant="Vacant", "", IF(target="", "", IF(MONTH(INDEX($C$3:$N$3, 1, c)&" 1") <= IFERROR(MONTH(target&" 1"), 0), rent, ""))))))} -> 950 | D5: 950 | E5: 950 | F5: 950 | G5: 950 | H5: 950 | I5: 950 | J5: 950 | O5: {=BYROW(C5:INDIRECT("N" & (COUNTA(A5:A1002)+2)), LAMBDA(r, SUM(r)))} -> 7600
A6: =IFERROR(__xludf.DUMMYFUNCTION("""COMPUTED_VALUE"""),"BBH-2-A") -> BBH-2-A | B6: =IFERROR(VLOOKUP($A6, 'Master Roster'!$A:$E, 5, FALSE), "") -> Wisdom Bwani | C6: 900 | D6: 900 | E6: 900 | F6: 900 | G6: 900 | H6: 900 | I6: 900 | J6: 900 | O6: 7200
A7: =IFERROR(__xludf.DUMMYFUNCTION("""COMPUTED_VALUE"""),"BBH-2-B") -> BBH-2-B | B7: =IFERROR(VLOOKUP($A7, 'Master Roster'!$A:$E, 5, FALSE), "") -> Jackson Mwanza | C7: 900 | D7: 900 | E7: 900 | F7: 900 | G7: 900 | H7: 900 | I7: 900 | O7: 6300
A8: =IFERROR(__xludf.DUMMYFUNCTION("""COMPUTED_VALUE"""),"BBH-3-A") -> BBH-3-A | B8: =IFERROR(VLOOKUP($A8, 'Master Roster'!$A:$E, 5, FALSE), "") -> Prosper Kalayi | C8: 900 | D8: 900 | E8: 900 | F8: 900 | G8: 900 | H8: 900 | I8: 900 | J8: 900 | O8: 7200
A9: =IFERROR(__xludf.DUMMYFUNCTION("""COMPUTED_VALUE"""),"BBH-3-B") -> BBH-3-B | B9: =IFERROR(VLOOKUP($A9, 'Master Roster'!$A:$E, 5, FALSE), "") -> Shadrach Munganini | C9: 900 | D9: 900 | E9: 900 | F9: 900 | G9: 900 | H9: 900 | I9: 900 | J9: 900 | O9: 7200
A10: =IFERROR(__xludf.DUMMYFUNCTION("""COMPUTED_VALUE"""),"BBH-3-C") -> BBH-3-C | B10: =IFERROR(VLOOKUP($A10, 'Master Roster'!$A:$E, 5, FALSE), "") -> Collins Mubanga | C10: 900 | D10: 900 | E10: 900 | F10: 900 | G10: 900 | H10: 900 | I10: 900 | J10: 900 | O10: 7200
A11: =IFERROR(__xludf.DUMMYFUNCTION("""COMPUTED_VALUE"""),"BBH-4-A") -> BBH-4-A | B11: =IFERROR(VLOOKUP($A11, 'Master Roster'!$A:$E, 5, FALSE), "") -> Himalikiti Saviour | C11: 950 | D11: 950 | E11: 950 | F11: 950 | G11: 950 | H11: 950 | I11: 950 | O11: 6650
A12: =IFERROR(__xludf.DUMMYFUNCTION("""COMPUTED_VALUE"""),"BBH-5-A") -> BBH-5-A | B12: =IFERROR(VLOOKUP($A12, 'Master Roster'!$A:$E, 5, FALSE), "") -> Wampa | C12: 0 | D12: 0 | E12: 0 | F12: 0 | G12: 0 | H12: 0 | I12: 0 | O12: 0
A13: =IFERROR(__xludf.DUMMYFUNCTION("""COMPUTED_VALUE"""),"BBH-6-A") -> BBH-6-A | B13: =IFERROR(VLOOKUP($A13, 'Master Roster'!$A:$E, 5, FALSE), "") -> McDonald | C13: 900 | D13: 900 | E13: 900 | F13: 900 | G13: 900 | O13: 4500
A14: =IFERROR(__xludf.DUMMYFUNCTION("""COMPUTED_VALUE"""),"BBH-6-B") -> BBH-6-B | B14: =IFERROR(VLOOKUP($A14, 'Master Roster'!$A:$E, 5, FALSE), "") -> Nanga Obrien | C14: 900 | D14: 900 | E14: 900 | F14: 900 | G14: 900 | O14: 4500
A15: =IFERROR(__xludf.DUMMYFUNCTION("""COMPUTED_VALUE"""),"BBH-6-C") -> BBH-6-C | B15: =IFERROR(VLOOKUP($A15, 'Master Roster'!$A:$E, 5, FALSE), "") -> Zick Phiri | C15: 900 | D15: 900 | E15: 900 | F15: 900 | G15: 900 | H15: 900 | I15: 900 | J15: 900 | O15: 7200
A16: =IFERROR(__xludf.DUMMYFUNCTION("""COMPUTED_VALUE"""),"BBH-7-A") -> BBH-7-A | B16: =IFERROR(VLOOKUP($A16, 'Master Roster'!$A:$E, 5, FALSE), "") -> Funny Muyamina | C16: 900 | D16: 900 | E16: 900 | F16: 900 | G16: 900 | H16: 900 | I16: 900 | J16: 900 | O16: 7200
A17: =IFERROR(__xludf.DUMMYFUNCTION("""COMPUTED_VALUE"""),"BBH-7-B") -> BBH-7-B | B17: =IFERROR(VLOOKUP($A17, 'Master Roster'!$A:$E, 5, FALSE), "") -> Treasure Simeenda | C17: 900 | D17: 900 | E17: 900 | F17: 900 | G17: 900 | H17: 900 | I17: 900 | J17: 900 | O17: 7200
A18: =IFERROR(__xludf.DUMMYFUNCTION("""COMPUTED_VALUE"""),"BBH-7-C") -> BBH-7-C | B18: =IFERROR(VLOOKUP($A18, 'Master Roster'!$A:$E, 5, FALSE), "") -> Vacant | O18: 0
A19: =IFERROR(__xludf.DUMMYFUNCTION("""COMPUTED_VALUE"""),"BBH-8-A") -> BBH-8-A | B19: =IFERROR(VLOOKUP($A19, 'Master Roster'!$A:$E, 5, FALSE), "") -> Kangwa Kunda | C19: 900 | D19: 900 | E19: 900 | F19: 900 | G19: 900 | H19: 900 | I19: 900 | J19: 900 | O19: 7200
A20: =IFERROR(__xludf.DUMMYFUNCTION("""COMPUTED_VALUE"""),"BBH-8-B") -> BBH-8-B | B20: =IFERROR(VLOOKUP($A20, 'Master Roster'!$A:$E, 5, FALSE), "") -> Vacant | O20: 0
A21: =IFERROR(__xludf.DUMMYFUNCTION("""COMPUTED_VALUE"""),"BBH-9-A") -> BBH-9-A | B21: =IFERROR(VLOOKUP($A21, 'Master Roster'!$A:$E, 5, FALSE), "") -> Felistus Mweemba | C21: 900 | D21: 900 | E21: 900 | F21: 900 | G21: 900 | H21: 900 | I21: 900 | J21: 900 | O21: 7200
A22: =IFERROR(__xludf.DUMMYFUNCTION("""COMPUTED_VALUE"""),"BBH-9-B") -> BBH-9-B | B22: =IFERROR(VLOOKUP($A22, 'Master Roster'!$A:$E, 5, FALSE), "") -> Wendy Mpakise | C22: 900 | D22: 900 | E22: 900 | F22: 900 | G22: 900 | H22: 900 | I22: 900 | O22: 6300
A23: =IFERROR(__xludf.DUMMYFUNCTION("""COMPUTED_VALUE"""),"BBH-9-C") -> BBH-9-C | B23: =IFERROR(VLOOKUP($A23, 'Master Roster'!$A:$E, 5, FALSE), "") -> Vacant | O23: 0
A24: =IFERROR(__xludf.DUMMYFUNCTION("""COMPUTED_VALUE"""),"UPV-10-A") -> UPV-10-A | B24: =IFERROR(VLOOKUP($A24, 'Master Roster'!$A:$E, 5, FALSE), "") -> Emely Mwale | O24: 0
A25: =IFERROR(__xludf.DUMMYFUNCTION("""COMPUTED_VALUE"""),"UPV-10-B") -> UPV-10-B | B25: =IFERROR(VLOOKUP($A25, 'Master Roster'!$A:$E, 5, FALSE), "") -> Melody Mumba | O25: 0
A26: =IFERROR(__xludf.DUMMYFUNCTION("""COMPUTED_VALUE"""),"UPV-10-C") -> UPV-10-C | B26: =IFERROR(VLOOKUP($A26, 'Master Roster'!$A:$E, 5, FALSE), "") -> Sara Matakala | O26: 0
A27: =IFERROR(__xludf.DUMMYFUNCTION("""COMPUTED_VALUE"""),"UPV-10-D") -> UPV-10-D | B27: =IFERROR(VLOOKUP($A27, 'Master Roster'!$A:$E, 5, FALSE), "") -> Vacant | O27: 0
A28: =IFERROR(__xludf.DUMMYFUNCTION("""COMPUTED_VALUE"""),"UPV-11-A") -> UPV-11-A | B28: =IFERROR(VLOOKUP($A28, 'Master Roster'!$A:$E, 5, FALSE), "") -> Gift Nankamba | O28: 0
A29: =IFERROR(__xludf.DUMMYFUNCTION("""COMPUTED_VALUE"""),"UPV-12-A") -> UPV-12-A | B29: =IFERROR(VLOOKUP($A29, 'Master Roster'!$A:$E, 5, FALSE), "") -> chilulu chiliulu | O29: 0
A30: =IFERROR(__xludf.DUMMYFUNCTION("""COMPUTED_VALUE"""),"UPV-13-A") -> UPV-13-A | B30: =IFERROR(VLOOKUP($A30, 'Master Roster'!$A:$E, 5, FALSE), "") -> Chibesa Chisembe | O30: 0
A31: =IFERROR(__xludf.DUMMYFUNCTION("""COMPUTED_VALUE"""),"UPV-14-A") -> UPV-14-A | B31: =IFERROR(VLOOKUP($A31, 'Master Roster'!$A:$E, 5, FALSE), "") -> Reuben Ngusulu | O31: 0
A32: =IFERROR(__xludf.DUMMYFUNCTION("""COMPUTED_VALUE"""),"UPV-15-A") -> UPV-15-A | B32: =IFERROR(VLOOKUP($A32, 'Master Roster'!$A:$E, 5, FALSE), "") -> Harriet nanyangwe | O32: 0
A33: =IFERROR(__xludf.DUMMYFUNCTION("""COMPUTED_VALUE"""),"CRV-16-A") -> CRV-16-A | B33: =IFERROR(VLOOKUP($A33, 'Master Roster'!$A:$E, 5, FALSE), "") -> Vacant | O33: 0
A34: =IFERROR(__xludf.DUMMYFUNCTION("""COMPUTED_VALUE"""),"CRV-16-B") -> CRV-16-B | B34: =IFERROR(VLOOKUP($A34, 'Master Roster'!$A:$E, 5, FALSE), "") -> Ackim Siamafuko | C34: 1200 | D34: 1200 | E34: 1200 | F34: 1200 | G34: 1200 | H34: 1200 | I34: 1200 | J34: 1200 | O34: 9600
A35: =IFERROR(__xludf.DUMMYFUNCTION("""COMPUTED_VALUE"""),"CRV-17-A") -> CRV-17-A | B35: =IFERROR(VLOOKUP($A35, 'Master Roster'!$A:$E, 5, FALSE), "") -> Kwitu Khalu | C35: 900 | D35: 900 | E35: 900 | F35: 900 | G35: 900 | H35: 900 | I35: 900 | J35: 900 | K35: 900 | O35: 8100
A36: =IFERROR(__xludf.DUMMYFUNCTION("""COMPUTED_VALUE"""),"CRV-18-A") -> CRV-18-A | B36: =IFERROR(VLOOKUP($A36, 'Master Roster'!$A:$E, 5, FALSE), "") -> Christopher Tambule | C36: 1200 | D36: 1200 | E36: 1200 | F36: 1200 | G36: 1200 | H36: 1200 | I36: 1200 | J36: 1200 | O36: 9600
A37: =IFERROR(__xludf.DUMMYFUNCTION("""COMPUTED_VALUE"""),"ANX-19-A") -> ANX-19-A | B37: =IFERROR(VLOOKUP($A37, 'Master Roster'!$A:$E, 5, FALSE), "") -> Samantha Musako (Kakompe) | C37: 1200 | D37: 1200 | E37: 1200 | F37: 1200 | G37: 1200 | H37: 1200 | I37: 1200 | J37: 1200 | O37: 9600
A38: =IFERROR(__xludf.DUMMYFUNCTION("""COMPUTED_VALUE"""),"ANX-19-B") -> ANX-19-B | B38: =IFERROR(VLOOKUP($A38, 'Master Roster'!$A:$E, 5, FALSE), "") -> Chanda Lutashima | C38: 1200 | D38: 1200 | E38: 1200 | F38: 1200 | G38: 1200 | H38: 1200 | I38: 1200 | J38: 1200 | K38: 1200 | O38: 10800
A39: =IFERROR(__xludf.DUMMYFUNCTION("""COMPUTED_VALUE"""),"ANX-19-C") -> ANX-19-C | B39: =IFERROR(VLOOKUP($A39, 'Master Roster'!$A:$E, 5, FALSE), "") -> Josephine Nyirenda | C39: 1200 | D39: 1200 | E39: 1200 | F39: 1200 | G39: 1200 | H39: 1200 | I39: 1200 | J39: 1200 | O39: 9600
A40: =IFERROR(__xludf.DUMMYFUNCTION("""COMPUTED_VALUE"""),"ANX-19-D") -> ANX-19-D | B40: =IFERROR(VLOOKUP($A40, 'Master Roster'!$A:$E, 5, FALSE), "") -> Lubono Ruthendo | C40: 1200 | D40: 1200 | E40: 1200 | F40: 1200 | G40: 1200 | H40: 1200 | I40: 1200 | J40: 1200 | K40: 1200 | O40: 10800
A41: =IFERROR(__xludf.DUMMYFUNCTION("""COMPUTED_VALUE"""),"ANX-20-A") -> ANX-20-A | B41: =IFERROR(VLOOKUP($A41, 'Master Roster'!$A:$E, 5, FALSE), "") -> Steven Musonda | C41: 1400 | D41: 1400 | E41: 1400 | F41: 1400 | G41: 1400 | H41: 1400 | I41: 1400 | J41: 1400 | K41: 1400 | O41: 12600
A42: =IFERROR(__xludf.DUMMYFUNCTION("""COMPUTED_VALUE"""),"NWG-21-A") -> NWG-21-A | B42: =IFERROR(VLOOKUP($A42, 'Master Roster'!$A:$E, 5, FALSE), "") -> Lukundo Siame | C42: 1200 | D42: 1200 | E42: 1200 | F42: 1200 | G42: 1200 | H42: 1200 | I42: 1200 | O42: 8400
A43: =IFERROR(__xludf.DUMMYFUNCTION("""COMPUTED_VALUE"""),"NWG-21-B") -> NWG-21-B | B43: =IFERROR(VLOOKUP($A43, 'Master Roster'!$A:$E, 5, FALSE), "") -> Gabirel Kabwe | C43: 1200 | D43: 1200 | E43: 1200 | F43: 1200 | G43: 1200 | H43: 1200 | I43: 1200 | J43: 1200 | O43: 9600
A44: =IFERROR(__xludf.DUMMYFUNCTION("""COMPUTED_VALUE"""),"NWG-21-C") -> NWG-21-C | B44: =IFERROR(VLOOKUP($A44, 'Master Roster'!$A:$E, 5, FALSE), "") -> Chama Kampamba | C44: 1200 | D44: 1200 | E44: 1200 | F44: 1200 | G44: 1200 | H44: 1200 | I44: 1200 | O44: 8400
A45: =IFERROR(__xludf.DUMMYFUNCTION("""COMPUTED_VALUE"""),"NWG-21-D") -> NWG-21-D | B45: =IFERROR(VLOOKUP($A45, 'Master Roster'!$A:$E, 5, FALSE), "") -> Jairos Banda | C45: 1200 | D45: 1200 | E45: 1200 | F45: 1200 | G45: 1200 | H45: 1200 | I45: 1200 | J45: 1200 | K45: 1200 | O45: 10800
A46: =IFERROR(__xludf.DUMMYFUNCTION("""COMPUTED_VALUE"""),"NWG-22-A") -> NWG-22-A | B46: =IFERROR(VLOOKUP($A46, 'Master Roster'!$A:$E, 5, FALSE), "") -> Vacant | O46: 0
A47: =IFERROR(__xludf.DUMMYFUNCTION("""COMPUTED_VALUE"""),"NWG-22-B") -> NWG-22-B | B47: =IFERROR(VLOOKUP($A47, 'Master Roster'!$A:$E, 5, FALSE), "") -> David Mulila | C47: 1200 | D47: 1200 | E47: 1200 | F47: 1200 | G47: 1200 | H47: 1200 | I47: 1200 | J47: 1200 | O47: 9600
A48: =IFERROR(__xludf.DUMMYFUNCTION("""COMPUTED_VALUE"""),"NWG-22-C") -> NWG-22-C | B48: =IFERROR(VLOOKUP($A48, 'Master Roster'!$A:$E, 5, FALSE), "") -> Ongani Madaliso Gabriel | C48: 1200 | D48: 1200 | E48: 1200 | F48: 1200 | G48: 1200 | H48: 1200 | I48: 1200 | J48: 1200 | K48: 1200 | O48: 10800
A49: =IFERROR(__xludf.DUMMYFUNCTION("""COMPUTED_VALUE"""),"NWG-22-D") -> NWG-22-D | B49: =IFERROR(VLOOKUP($A49, 'Master Roster'!$A:$E, 5, FALSE), "") -> Christopher Phiri | C49: 1200 | D49: 1200 | E49: 1200 | F49: 1200 | G49: 1200 | H49: 1200 | I49: 1200 | J49: 1200 | K49: 1200 | O49: 10800
A50: =IFERROR(__xludf.DUMMYFUNCTION("""COMPUTED_VALUE"""),"NWG-23-A") -> NWG-23-A | B50: =IFERROR(VLOOKUP($A50, 'Master Roster'!$A:$E, 5, FALSE), "") -> Vacant | O50: 0
A51: =IFERROR(__xludf.DUMMYFUNCTION("""COMPUTED_VALUE"""),"NWG-23-B") -> NWG-23-B | B51: =IFERROR(VLOOKUP($A51, 'Master Roster'!$A:$E, 5, FALSE), "") -> Catherine Mphande | C51: 1200 | D51: 1200 | E51: 1200 | F51: 1200 | G51: 1200 | H51: 1200 | I51: 1200 | J51: 1200 | O51: 9600
A52: =IFERROR(__xludf.DUMMYFUNCTION("""COMPUTED_VALUE"""),"NWG-23-C") -> NWG-23-C | B52: =IFERROR(VLOOKUP($A52, 'Master Roster'!$A:$E, 5, FALSE), "") -> Grace Mwamba | C52: 1200 | D52: 1200 | E52: 1200 | F52: 1200 | G52: 1200 | H52: 1200 | I52: 1200 | J52: 1200 | O52: 9600
A53: =IFERROR(__xludf.DUMMYFUNCTION("""COMPUTED_VALUE"""),"NWG-23-D") -> NWG-23-D | B53: =IFERROR(VLOOKUP($A53, 'Master Roster'!$A:$E, 5, FALSE), "") -> Lushomo gambwe | C53: 1200 | D53: 1200 | E53: 1200 | F53: 1200 | G53: 1200 | H53: 1200 | I53: 1200 | J53: 1200 | O53: 9600
A54: =IFERROR(__xludf.DUMMYFUNCTION("""COMPUTED_VALUE"""),"NWG-23-E") -> NWG-23-E | B54: =IFERROR(VLOOKUP($A54, 'Master Roster'!$A:$E, 5, FALSE), "") -> Jacqueline Mwape | C54: 1200 | D54: 1200 | E54: 1200 | F54: 1200 | G54: 1200 | H54: 1200 | I54: 1200 | J54: 1200 | O54: 9600
A55: =IFERROR(__xludf.DUMMYFUNCTION("""COMPUTED_VALUE"""),"NWG-24-A") -> NWG-24-A | B55: =IFERROR(VLOOKUP($A55, 'Master Roster'!$A:$E, 5, FALSE), "") -> Chami Soneka | C55: 1200 | D55: 1200 | E55: 1200 | F55: 1200 | G55: 1200 | H55: 1200 | I55: 1200 | J55: 1200 | K55: 1200 | O55: 10800
A56: =IFERROR(__xludf.DUMMYFUNCTION("""COMPUTED_VALUE"""),"NWG-24-B") -> NWG-24-B | B56: =IFERROR(VLOOKUP($A56, 'Master Roster'!$A:$E, 5, FALSE), "") -> Kuwunda Makondo | C56: 1200 | D56: 1200 | E56: 1200 | F56: 1200 | G56: 1200 | H56: 1200 | I56: 1200 | J56: 1200 | O56: 9600
A57: =IFERROR(__xludf.DUMMYFUNCTION("""COMPUTED_VALUE"""),"NWG-24-C") -> NWG-24-C | B57: =IFERROR(VLOOKUP($A57, 'Master Roster'!$A:$E, 5, FALSE), "") -> Chansa Chinyama | C57: 1200 | D57: 1200 | E57: 1200 | F57: 1200 | G57: 1200 | H57: 1200 | I57: 1200
A58: =IFERROR(__xludf.DUMMYFUNCTION("""COMPUTED_VALUE"""),"NWG-24-D") -> NWG-24-D | B58: =IFERROR(VLOOKUP($A58, 'Master Roster'!$A:$E, 5, FALSE), "") -> Kawina Florence | C58: 1200 | D58: 1200 | E58: 1200 | F58: 1200 | G58: 1200 | H58: 1200
B59: =IFERROR(VLOOKUP($A59, 'Master Roster'!$A:$E, 5, FALSE), "")
B60: =IFERROR(VLOOKUP($A60, 'Master Roster'!$A:$E, 5, FALSE), "")
B61: =IFERROR(VLOOKUP($A61, 'Master Roster'!$A:$E, 5, FALSE), "")
B62: =IFERROR(VLOOKUP($A62, 'Master Roster'!$A:$E, 5, FALSE), "")
B63: =IFERROR(VLOOKUP($A63, 'Master Roster'!$A:$E, 5, FALSE), "")
B64: =IFERROR(VLOOKUP($A64, 'Master Roster'!$A:$E, 5, FALSE), "")
B65: =IFERROR(VLOOKUP($A65, 'Master Roster'!$A:$E, 5, FALSE), "")
B66: =IFERROR(VLOOKUP($A66, 'Master Roster'!$A:$E, 5, FALSE), "")
B67: =IFERROR(VLOOKUP($A67, 'Master Roster'!$A:$E, 5, FALSE), "")
B68: =IFERROR(VLOOKUP($A68, 'Master Roster'!$A:$E, 5, FALSE), "")
B69: =IFERROR(VLOOKUP($A69, 'Master Roster'!$A:$E, 5, FALSE), "")
B70: =IFERROR(VLOOKUP($A70, 'Master Roster'!$A:$E, 5, FALSE), "")
... B100: =IFERROR(VLOOKUP($A100, 'Master Roster'!$A:$E, 5, FALSE), "")

Sheet Receipt Tracking
A1: Receipt Tracking
A3: Receipt Number | B3: Payment Date | C3: Room | D3: Tenant Name | E3: Amount Paid
A4: {=IF(B4:B1002="", "", TEXT(B4:B1002, "YYYYMMDD") & "-" & C4:C1002)} -> 20260605-BBH-1-A | B4: =IFERROR(__xludf.DUMMYFUNCTION("QUERY('Payments Log Archive'!A4:F1002, ""select C where C is not null"", 0)"),46178.0) -> 46178 | C4: {=IF(D4:D1002="", "", IFERROR(INDEX('Master Roster'!$A:$A, MATCH(D4:D1002, 'Master Roster'!$E:$E, 0)), ""))} -> BBH-1-A | D4: =IFERROR(__xludf.DUMMYFUNCTION("QUERY('Payments Log Archive'!A4:F1002, ""select B where C is not null"", 0)"),"Adrian mulale") -> Adrian mulale | E4: =IFERROR(__xludf.DUMMYFUNCTION("QUERY('Payments Log Archive'!A4:F1002, ""select F where C is not null"", 0)"),950.0) -> 950
A5: 20260605-BBH-1-A | B5: =IFERROR(__xludf.DUMMYFUNCTION("""COMPUTED_VALUE"""),46178.0) -> 46178 | C5: BBH-1-A | D5: =IFERROR(__xludf.DUMMYFUNCTION("""COMPUTED_VALUE"""),"Zick Phiri") -> Zick Phiri | E5: =IFERROR(__xludf.DUMMYFUNCTION("""COMPUTED_VALUE"""),900.0) -> 900
A6: 20260605-BBH-1-A | B6: =IFERROR(__xludf.DUMMYFUNCTION("""COMPUTED_VALUE"""),46178.0) -> 46178 | C6: BBH-1-A | D6: =IFERROR(__xludf.DUMMYFUNCTION("""COMPUTED_VALUE"""),"Kangwa Kunda") -> Kangwa Kunda | E6: =IFERROR(__xludf.DUMMYFUNCTION("""COMPUTED_VALUE"""),900.0) -> 900
A7: 20260605-BBH-1-A | B7: =IFERROR(__xludf.DUMMYFUNCTION("""COMPUTED_VALUE"""),46178.0) -> 46178 | C7: BBH-1-A | D7: =IFERROR(__xludf.DUMMYFUNCTION("""COMPUTED_VALUE"""),"Emely Mwale") -> Emely Mwale | E7: =IFERROR(__xludf.DUMMYFUNCTION("""COMPUTED_VALUE"""),850.0) -> 850
A8: 20260605-BBH-1-A | B8: =IFERROR(__xludf.DUMMYFUNCTION("""COMPUTED_VALUE"""),46178.0) -> 46178 | C8: BBH-1-A | D8: =IFERROR(__xludf.DUMMYFUNCTION("""COMPUTED_VALUE"""),"Gift Nankamba") -> Gift Nankamba | E8: =IFERROR(__xludf.DUMMYFUNCTION("""COMPUTED_VALUE"""),1000.0) -> 1000
A9: 20260605-BBH-1-A | B9: =IFERROR(__xludf.DUMMYFUNCTION("""COMPUTED_VALUE"""),46178.0) -> 46178 | C9: BBH-1-A | D9: =IFERROR(__xludf.DUMMYFUNCTION("""COMPUTED_VALUE"""),"chilulu chiliulu") -> chilulu chiliulu | E9: =IFERROR(__xludf.DUMMYFUNCTION("""COMPUTED_VALUE"""),1600.0) -> 1600
A10: 20260605-BBH-1-A | B10: =IFERROR(__xludf.DUMMYFUNCTION("""COMPUTED_VALUE"""),46178.0) -> 46178 | C10: BBH-1-A | D10: =IFERROR(__xludf.DUMMYFUNCTION("""COMPUTED_VALUE"""),"Chibesa Chisembe") -> Chibesa Chisembe | E10: =IFERROR(__xludf.DUMMYFUNCTION("""COMPUTED_VALUE"""),1800.0) -> 1800
A11: 20260605-BBH-1-A | B11: =IFERROR(__xludf.DUMMYFUNCTION("""COMPUTED_VALUE"""),46178.0) -> 46178 | C11: BBH-1-A | D11: =IFERROR(__xludf.DUMMYFUNCTION("""COMPUTED_VALUE"""),"Reuben Ngusulu") -> Reuben Ngusulu | E11: =IFERROR(__xludf.DUMMYFUNCTION("""COMPUTED_VALUE"""),950.0) -> 950
A12: 20260605-BBH-1-A | B12: =IFERROR(__xludf.DUMMYFUNCTION("""COMPUTED_VALUE"""),46178.0) -> 46178 | C12: BBH-1-A | D12: =IFERROR(__xludf.DUMMYFUNCTION("""COMPUTED_VALUE"""),"Kwitu Khalu") -> Kwitu Khalu | E12: =IFERROR(__xludf.DUMMYFUNCTION("""COMPUTED_VALUE"""),900.0) -> 900
A13: 20260605-BBH-1-A | B13: =IFERROR(__xludf.DUMMYFUNCTION("""COMPUTED_VALUE"""),46178.0) -> 46178 | C13: BBH-1-A | D13: =IFERROR(__xludf.DUMMYFUNCTION("""COMPUTED_VALUE"""),"Chanda Lutashima") -> Chanda Lutashima | E13: =IFERROR(__xludf.DUMMYFUNCTION("""COMPUTED_VALUE"""),1200.0) -> 1200
A14: 20260605-BBH-1-A | B14: =IFERROR(__xludf.DUMMYFUNCTION("""COMPUTED_VALUE"""),46178.0) -> 46178 | C14: BBH-1-A | D14: =IFERROR(__xludf.DUMMYFUNCTION("""COMPUTED_VALUE"""),"Lukundo Siame") -> Lukundo Siame | E14: =IFERROR(__xludf.DUMMYFUNCTION("""COMPUTED_VALUE"""),1200.0) -> 1200
A15: 20260605-BBH-1-A | B15: =IFERROR(__xludf.DUMMYFUNCTION("""COMPUTED_VALUE"""),46178.0) -> 46178 | C15: BBH-1-A | D15: =IFERROR(__xludf.DUMMYFUNCTION("""COMPUTED_VALUE"""),"Gabirel Kabwe") -> Gabirel Kabwe | E15: =IFERROR(__xludf.DUMMYFUNCTION("""COMPUTED_VALUE"""),1200.0) -> 1200
A16: 20260605-BBH-1-A | B16: =IFERROR(__xludf.DUMMYFUNCTION("""COMPUTED_VALUE"""),46178.0) -> 46178 | C16: BBH-1-A | D16: =IFERROR(__xludf.DUMMYFUNCTION("""COMPUTED_VALUE"""),"Chama Kampamba") -> Chama Kampamba | E16: =IFERROR(__xludf.DUMMYFUNCTION("""COMPUTED_VALUE"""),1200.0) -> 1200
A17: 20260605-BBH-1-A | B17: =IFERROR(__xludf.DUMMYFUNCTION("""COMPUTED_VALUE"""),46178.0) -> 46178 | C17: BBH-1-A | D17: =IFERROR(__xludf.DUMMYFUNCTION("""COMPUTED_VALUE"""),"Catherine Mphande") -> Catherine Mphande | E17: =IFERROR(__xludf.DUMMYFUNCTION("""COMPUTED_VALUE"""),1200.0) -> 1200
A18: 20260605-BBH-1-A | B18: =IFERROR(__xludf.DUMMYFUNCTION("""COMPUTED_VALUE"""),46178.0) -> 46178 | C18: BBH-1-A | D18: =IFERROR(__xludf.DUMMYFUNCTION("""COMPUTED_VALUE"""),"Lushomo gambwe") -> Lushomo gambwe | E18: =IFERROR(__xludf.DUMMYFUNCTION("""COMPUTED_VALUE"""),1200.0) -> 1200
